Workbook

Sheet Claude Log
A1: Turn # | B1: Date | C1: User Request | D1: Action Taken | E1: Details | F1: Outcome
A2: 1 | B2: 46196 | C2: Turn the STACK funding model into a tool a non-financial developer can drive: bucket tab colours, a guided single Input tab with a funding-strategy selector, a restructured output Cashflow, a strategy-driven engine, a Summary verdict and 5-way comparison, and full protection. | D2: Completed all four passes. | E2: Tab colours (Input yellow, Output green, Engine red) + bucket banners. Inputs: inserted Funding strategy selector, follow-on dropdowns, own-land Yes/No, commencement date, mezzanine inputs, derived switches, tooltips on every input, and conditional greying of not-required inputs. Split the monthly senior schedule to a red Engine tab and rebuilt Cashflow as a phase by calendar-month grid with year subtotals, net movement and cumulative position. Made senior, mezzanine, partner, land and the waterfall strategy-driven (unused sources to zero, waterfall collapses to all-to-developer with no partner). Added Summary plain-English headline, gentle margin flag and a 5-way funding snapshot. Locked all but the yellow input cells and protected sheets + structure with password STACK. | F2: All routes reconcile (Engine!B26=0, Waterfall!F39=0); Cashflow cumulative ties to project profit; workbook protected.
A3: 2 | B3: 46196 | C3: Cashflow tab needed headlines: add a horizontal section header across the column groups (a Months band as the example). | D3: Added a horizontal section-header band to the Cashflow output. | E3: Unprotected Cashflow, inserted a band row above the date header (now row 4): merged labels 'Cashflow by phase' over A:B, 'Months (from commencement date)' over month columns C:AF, 'Calendar-year subtotals' over AG:AJ, 'Total' over AK, navy fill white bold. Re-froze at C5 so the band and month labels stay visible; re-protected with STACK. | F3: Band renders; date headers intact (Jul 26 onwards); net movement and cumulative still tie to project profit (£614,633); Engine!B26 reconciliation = 0.
A4: 3 | B4: 46196 | C4: On Cashflow, frozen rows 1-4 and columns A-B were not showing; the freeze (5/C) had scrolled out of view. | D4: Reset the Cashflow view and re-applied the freeze. | E4: Unprotected Cashflow, cleared the freeze, scrolled to A1 (top-left), re-froze 4 rows and 2 columns (freeze region A1:B4), set the cursor to C5, re-protected with STACK. | F4: Freeze confirmed at A1:B4; the banner, subtitle, Months band and date headers (rows 1-4) plus the Phase and Line item columns (A-B) are pinned and visible.
A5: 4 | B5: 46196 | C5: Make the Inputs tab user interface more presentable and user-friendly, as far as Excel allows. | D5: Restyled the Inputs tab into a clean, form-like layout. | E5: Hid gridlines; unified Arial fonts and sizes; consistent navy section bands; yellow editable cells with blue figures, grey calculated cells, soft grey italic single-line guidance notes; centred units; tidied column widths and row heights; added a 'type only in the yellow cells' hint; froze the title rows. No formulas or wiring changed; conditional greying, dropdowns and tooltips preserved. | F5: Inputs reads as a clean form; gridlines off, freeze at rows 1-2; reconciliations still 0; C5 editable, C25 locked; tab re-protected with STACK.
A6: 5 | B6: 46196 | C6: Asked how to unlock and re-lock the protected sheets so they can adjust text wrapping themselves across this and other tabs. | D6: Provided unlock/re-lock instructions (no workbook edits made). | E6: Explained Review > Unprotect Sheet with password STACK per tab; workbook structure only needs unlocking to add/move/delete/rename sheets; wrap via Home > Wrap Text then AutoFit Row Height; re-lock via Review > Protect Sheet (password STACK, default tick-boxes) and Protect Workbook. Noted per-cell lock states persist so yellow inputs stay editable. | F6: Guidance given; offered to do the wrapping pass and re-protect myself if preferred.
A7: 6 | B7: 46196 | C7: Asked to detail the full project history in the log so it can be referenced and resumed in a new session. | D7: Added a full PROJECT REFERENCE handoff section to the Claude Log. | E7: Below the turn log (rows 9 to 29): workbook purpose, tab buckets and colours, Inputs layout and key cell addresses, derived switches, Engine/Cashflow/Waterfall/Summary/Comparison roles, how the strategy drives results, mezzanine and off-plan treatment, reconciliation cells, determinism, protection and password, house rules, base case, and history with open items. | F7: Claude Log is now a self-contained handoff; reconciliations unchanged (Engine!B26=0, Waterfall!F39=0).
A8: 7 | B8: 46198 | C8: Asked for a full review of the workbook and the Claude Log to understand what the STACK funding model is and why it was built, ahead of stepping through external RE modelling templates to benchmark and improve STACK. | D8: Read every tab (Read Me, Inputs, Engine, Cashflow, Waterfall, Summary, Sensitivity, Comparison) and the Claude Log handoff section; summarised architecture, mechanics and reconciliation state back to the user. | E8: Confirmed: deterministic funding engine, Inputs the only editable tab, no circular references. Base case JV plus land-for-equity, profit about 614,633 pounds, PoC 19.5% vs 20% target. Reconciliations read 0 (Engine!B26, Waterfall!F39). Noted self-flagged gaps for the benchmarking pass: funding engine not a full appraisal, single revenue receipt at completion, off-plan pre-sale timing illustrative, no time-based IRR by design, deferred PULSE baseline handoff and fold into the appraisal engine. | F8: Review complete; awaiting the first external template to benchmark STACK against.
A9: 8 | B9: 46198 | C9: Benchmark STACK against the first external template: Original-Apartment-Acquisition-Model-v2.5.xlsx (received from the connected Excel model). | D9: Reviewed the apartment model's structure, returns logic, debt and waterfall via a shared overview file; produced a side-by-side comparison and a prioritised list of improvement candidates for STACK. | E9: Apartment model = US multifamily value-add ACQUISITION model: annual over 10-15yr hold, monthly lease-up modules roll into Annual Cash Flow, levered+unlevered IRR/EM, LP/GP promote waterfall with IRR or EM hurdles, debt sized on LTV with amortisation (PMT/-PV), DSCR and debt yield, triangular hold-period IRR/EM matrix, purchase-price-method toggle. STACK = UK ground-up DEVELOPMENT funding engine: monthly 30mo, deterministic, profit-on-cost not IRR, funding stack + 3-party land-for-equity waterfall, 5 funding configurations. Top improvement candidates flagged: (1) add time-based project and per-route IRR + equity multiple over the existing monthly cashflow; (2) credit-metrics block (peak LTC/LTGDV drawn, interest cover, profit-on-GDV); (3) IRR-vs-EM hurdle toggle in waterfall; (4) phased sales absorption modelled on the lease-up rollup, for off-plan. | F9: Comparison delivered to user; no model changes yet, awaiting direction on which enhancements to action.
A10: 9 | B10: 46198 | C10: Action benchmark improvement 1 from the apartment-model comparison: add time-based IRR and equity multiple, and test the model so STACK is not weakened. | D10: Built a live time-based returns block on Engine, surfaced it on Summary, added per-route equity multiple and IRR on Comparison, tested across all four funding routes, and fixed an IRR convergence bug found during testing. | E10: Engine rows 32-41: monthly dated vectors. Project (unlevered) cash flow = Cashflow net movement excluding finance (C24-C19); Equity (levered) cash flow = cash-equity draws (row 14) plus contributed land in month 1 plus the completion distribution (NDV less senior and mezz redemption). These feed Project IRR/EM (B38/B39) and Equity IRR/EM (B40/B41). Initially used XIRR; testing showed XIRR returned about 0% for the Debt-financed and Off-plan routes (equity drawn late, single terminal inflow), so switched both IRR cells to an annualised periodic IRR =(1+IRR(range,0.02))^12-1, which is correct on the regular monthly dates and stable across all routes. Summary block rows 34-37 link the live figures (green). Comparison rows 39-40: whole-project equity multiple for all five routes (rigorous), and equity IRR with column F live and the four closed-form routes annualised from the multiple over the programme (labelled as estimates), caveat note row 41. New cells locked; Engine, Summary, Comparison re-protected with STACK. | F10: All reconciliations read 0 across all four routes (Engine!B26, Waterfall!F39); Cashflow cumulative still ties to project profit (614,633 pounds). Base case JV: Project IRR 20.9%, Equity IRR 32.3%, Equity multiple 1.49x. Sheets re-protected; base case restored.
A11: 10 | B11: 46198 | C11: Proceed with benchmark improvement 2 from the apartment-model comparison: add a credit and margin metrics block (the development analogue to the apartment model's DSCR and debt-yield guardrails). | D11: Added a live, route-aware Credit & margin metrics block to the Summary tab, with error guards, and tested it across all four funding routes; caught and fixed a profit-on-cost denominator inconsistency during testing. | E11: Summary rows 39-45 (new section, locked, green cross-sheet links). Metrics: Senior loan-to-cost = sized facility / cost ex finance (Inputs C54/C53) with the 60% limit; Senior loan-to-GDV (C54/C23) with the 55% limit; Peak senior exposure incl. rolled interest (Engine B22) and as % of GDV; Profit on cost (linked to existing headline B5 for consistency); Profit on GDV (margin); Finance cost / GDV; Profit cover of finance (profit / finance cost), all wrapped in IFERROR. Initially computed profit on cost as B6/C53 (ex finance) which gave 21.2% and disagreed with the model headline 19.5% (the model uses all-in cost incl finance); fixed by linking B43 to B5. Zero-debt guard verified on the self-funded route (finance cover shows n/a, leverage shows dashes). | F11: All four routes reconcile (Engine!B26=0, Waterfall!F39=0). Base JV: LTC 60.0% (binding) vs LTGDV 45.1% (cap 55%), peak exposure 1,856,987 pounds (48.2% of GDV), profit on GDV 16.0%, finance cost 6.9% of GDV, profit cover 2.3x. Self-funded n/a guard works. Base case restored to Joint venture; Summary and Inputs re-protected with STACK.
A12: 11 | B12: 46198 | C12: Proceed with benchmark improvement 3: an IRR-vs-equity-multiple hurdle toggle in the JV waterfall, mirroring the apartment model's hurdle switch, kept deterministic. | D12: Added a JV promote hurdle-basis toggle and an equity-multiple hurdle input on Inputs, wired the Waterfall Tier 2 preferred-return accrual to switch between the two bases, made the tier header live, and tested both bases and a non-JV route. | E12: Inputs rows 58-60 (appended, no row inserts, so all documented addresses C44/C53/C54/C56 stay put): banded sub-section 'JV promote hurdle (optional test)'; C59 dropdown 'Preferred return / Equity multiple' (default Preferred return so base case is unchanged); C60 equity multiple hurdle 1.30x; conditional greying when not JV (Inputs C20=0); both cells unlocked. Waterfall C21/D21/E21 changed from =Inputs!C20*cap*((1+C44)^period-1) to wrap the factor in IF(Inputs!C59="Equity multiple",(Inputs!C60-1),((1+C44)^period-1)); deterministic (computed on contributed capital, no IRR solve). A19 header now live ="Tier 2, return hurdle ("&Inputs!C59&")". Total to equity is fixed at F12, so the toggle only reallocates between pref (pro-rata to all parties) and promote (sponsor only). | F12: Tested: JV+Equity multiple (1.30x) lifts pref pool to 377,030 pounds, cuts sponsor promote to 118,801, sponsor multiple 2.51x to 2.29x, partner/landowner to 1.39x; JV+Preferred return restores base (pref 220,851, promote 196,891, sponsor 2.51x); Self-funded shows no effect (pref 0). All states reconcile (Waterfall!F39=0, Engine!B26=0). Base case restored; Inputs and Waterfall re-protected with STACK.
A13: 12 | B13: 46198 | C13: Proceed with benchmark improvement 4 (full depth): model off-plan pre-sales so pre-sale cash funds the build, cuts rolled-up interest and lifts profit, gated and tested. User chose the full financing integration over timing-only. | D13: Added an off-plan pre-sales switch and proportion on Inputs; wired the Engine so pre-sale receipts reduce the monthly senior draw (lower balance, lower interest); updated the Waterfall and the equity IRR vector for the pre-sale debt reduction; re-timed the Cashflow sales into the construction period; tested off vs on across routes. | E13: Inputs rows 62-64 (appended, no address shift): switch C63 (Yes/No, default No so base case unchanged) and C64 pre-sale proportion of NDV (50%), greyed when off. Engine: row6 pre-sale applied = active x prop x NDV spread over construction, capped at each month's cost; row12 draw =MIN(MAX(0,cost-presale),headroom); row14 equity =MAX(0,cost-presale)-draw; row13 closing unchanged so balance and interest fall; B30 = total pre-sale reduction; B26 reconciliation adds B30. Waterfall F11/F39 subtract Engine B30. Engine equity-CF (row35) completion term changed to NDV-B30-B20-B29 to stay consistent. Cashflow row20/21 recognise pre-sale GDV (Engine row6 grossed up) during construction with the remainder at completion; net movement and finance (lower interest) flow through. All formulas reduce exactly to the originals when the switch is off. | F13: Tested off vs on, JV and Self-funded. Base/off byte-identical and restored. JV at 50%: profit 614,633 to 789,509 = +174,876 = exactly the interest saved (264,676 to 89,800); Project IRR 20.9% to 38.2%, Equity multiple 1.49x to 2.50x. Self-funded: profit unchanged (no debt, nothing to save), IRR still improves on earlier cash. Every state reconciles (Engine!B26=0, Waterfall!F39=0) and the Cashflow cumulative ties to profit. Base case restored (pre-sales off, Joint venture); Inputs, Engine, Waterfall, Cashflow re-protected with STACK.
... A49: 48 | B49: 46198 | C49: User asked to confirm the log and PROJECT REFERENCE are updated. | D49: Confirmed the turn log is current and topped up the PROJECT REFERENCE for the developer-facing decision layer added since the last refresh. | E49: Turn log: every turn (1-48) is recorded. PROJECT REFERENCE was last refreshed at turn 39; updated the Key input addresses (added Consider band C115), the Summary entry (DECISION block A18-A20 with RAG, the graduated RAG verdict and gap-in-points), Protection (added C115 to the unlocked list), and History (added the developer-facing RAG verdict and Go/Consider/No-Go layer). Reference now matches the current workbook. | F49: Log and PROJECT REFERENCE both current. No model values changed; reconciliations 0 (Engine B26, Waterfall F39); base case profit 614,633; sheets protected.
A50: PROJECT REFERENCE (to resume this build in a new session)
A51: Workbook | C51: STACK_Funding_Engine_Final.xlsx. A deterministic property development funding engine. The developer types only on the Inputs tab; every other tab computes and is read only. No circular references anywhere.
A52: Tab buckets and colours | C52: Input (yellow tab): Inputs. Output (green tabs): Summary, Cashflow, Comparison. Engine (red tabs): Waterfall, Sensitivity, Engine. Read Me is a plain cover. Claude Log (grey) is this journal and is left unprotected.
A53: Inputs tab layout | C53: The only tab you type on. Section bands at rows 4 Funding strategy, 12 Strategy switches, 22 Scheme, 37 Funding terms, 49 Derived sizing. Yellow cells are editable, grey cells are calculated and locked. Every input has a dropdown or tooltip; inputs a route does not need go grey with a Not required note.
A54: Funding strategy selector | C54: Inputs C5 dropdown: Self-funded, Debt-financed, Joint venture, Off-plan. Follow-ons: C6 debt structure (Senior loan only or Senior plus mezzanine), C7 JV partner contributes (Cash, Land or Both), C8 senior alongside the JV (Yes or No), C9 do you already own the land (Yes or No), C10 commencement date, C11 mezzanine rate, C21 mezzanine combined loan to cost.
A55: Derived switches, Inputs C13 to C20 | C55: C13 use senior, C14 use mezzanine, C15 partner provides cash, C16 partner provides land, C17 land treated as contributed equity, C18 land is a cash purchase, C19 effective partner cash split, C20 preferred return and promote active. They turn the dropdown choices into 1 or 0 drivers for the engine.
A56: Key input cell addresses | C56: GDV C23, sales costs C24, NDV derived C25 (now also grown by sales growth), construction C26, professional fees C27, statutory C28, acquisition and legal C29, land value C30, SDLT C31, programme C32, construction start C33, end C34, completion C35, DM fee C38, senior LTC C39, senior LTGDV C40, senior rate C41, arrangement C42, exit C43, preferred return C44, partner cash split C45, residual to capital C46, target profit on cost C47. Improvement-program inputs: hurdle basis C59 and EM hurdle C60; pre-sales switch C63 and proportion C64; corporation tax rate C67; GP catch-up C70 and carry C71; reporting currency C78 (derived symbol C79, code C80); contingency C83; void holding per month C86; interest basis C89; build profile C92; build inflation C95 and sales growth C96; funding sequence C100; decision Consider band C115 (profit on cost points below target before the call drops from Consider to No Go). Net saleable area C74 and plots C75 are derived from the optional unit-mix table A102:E112. Effective build cost C97 = build x (1+contingency) x (1+inflation) to construction midpoint, used by C51.
A57: Derived sizing, Inputs | C57: Development management fee C50, cash development cost C51, total cash uses C52 = C51 plus C50 plus C18 times (C30 plus C31), total project cost C53 = C52 plus C17 times C30, senior facility C54 = C13 times MIN(C39 times C53, C40 times C23), sponsor cash split C55, promote C56.
A58: Engine tab (red) | C58: Monthly senior schedule, columns C to AF (months 1-30). Row 6 pre-sale receipts reduce the monthly draw. Anchors in column B: B17 senior close, B18 arrangement, B19 exit, B20 redemption, B21 total finance and holding cost (incl mezzanine B28 and void holding B31), B22 peak, B23 cash equity, B24 sponsor, B25 partner, B26 reconciliation reads 0, B27 mezzanine facility, B28 mezzanine interest, B29 mezzanine redemption, B30 total pre-sale debt reduction, B31 void holding cost. Rows 32-41 time-based returns: Project IRR B38, Project EM B39, Equity IRR B40, Equity EM B41 (all IFERROR-guarded). Rows 43-46 after-tax: tax B43, after-tax profit B44, after-tax IRR B45, after-tax EM B46. Rows 46-53 per-party cash flows and IRRs (Sponsor B51, Partner B52, Landowner B53). The schedule responds to interest basis C89 (Average adds half a month on each draw), build profile C92 (S-curve), and funding sequence C100 (Equity first funds the front-end). No circular reference.
A59: Cashflow tab (green output) | C59: Appraisal cashflow by phase down the side and calendar month across. Row 3 section band, row 4 month dates derived from the commencement date Inputs C10. Phases: Acquisition, Design and pre-construction, Construction, Finance, Sales and disposal. Calendar-year subtotal columns AG to AJ, project total AK. Net movement and cumulative cash position at the foot; the cumulative ends at project profit. Frozen at A1 to B4. When off-plan pre-sales are on, sales (rows 20 and 21) are recognised across construction with the balance at completion, so the cumulative shows a lower peak funding need and still ends at project profit.
A60: Waterfall tab (red engine) | C60: Three parties: Sponsor C, Funding partner D, Landowner E. Senior and mezzanine redeemed first, then return of capital, then the Tier 2 return hurdle (basis switchable on Inputs C59: preferred-return rate, or equity-multiple hurdle C60), then the residual split. Optional GP catch-up and carry on Inputs C70/C71 (pref, then 100% catch-up, then carry). F11 and F39 net off pre-sale debt reduction Engine B30 and void holding B31. The sponsor Tier 3 take is a plug, C28 = F26 minus (C27+D27+E27), so distribution is always complete even when total equity capital is zero (full pre-sale funding). Reconciliation F39 reads 0.
A61: Summary tab (green output) | C61: Redesigned as a one-page dashboard. Rows 1-3 title and live verdict; row 4 dynamic currency banner. Three panels (rows 5-25): Scheme and Timing; Sources and Uses (amount, percent, per sq ft, per plot, balancing to total cost, check E25); Return Metrics (Project, Equity, Equity after-tax IRR/MOIC/profit, and per-party contribution, distribution, profit, multiple and IRR at row 17). DECISION block A18-A20: RAG status A19 (GO green / CONSIDER amber / NO GO red) from profit on cost versus target and the Consider band C115, with a live gap-to-target reason A20. The verdict A3 and the decision word carry RAG conditional formatting; A3 states the gap in points (reconciled to the shown percentages), a graduated call (comfortably clears, clears, marginally under broadly in line, thinner than you would like, well short, or loses money), and a plain-English safety-cushion line. AUDIT CHECKS J19:N25 (six OK/CHECK). Below: Credit and margin, Viability, Residual Land Value (34-36), After-tax returns (47-51), 5-way routes (37-44). Charts: Uses doughnut, Profit by party. Load-bearing profit cell M8.
A62: Comparison tab (green output) | C62: The five strategies side by side. Columns C, D, E and G (Self-funded, Bank-financed, Mixed, Off-plan) are independent closed-form estimates. Column F links the exact engine and follows the route selected on Inputs; its header F14 updates to the selected route. Two added rows: whole-project equity multiple for all five routes, and equity IRR (column F live, the four closed-form routes annualised from the multiple over the programme).
... A70: History and open items | C70: Built over many turns: tab colours and banners; guided Input tab; Cashflow and engine restructure; verdict and 5-way comparison; Inputs UI. Benchmarked against five external templates; added time-based IRR and equity multiple, a credit and margin block, a JV hurdle-basis toggle, full off-plan pre-sales, an after-tax layer and a GP catch-up and carry. Redesigned the Summary into a one-page dashboard. Then a twelve-item improvement program: selectable currency; Tier 1 contingency, residual land value, sell-down void cost; Tier 2 average-balance interest, S-curve drawdown, inflation and sales growth, equity-first; Tier 3 break-even headroom, per-party IRR, unit-mix schedule; Tier 4 audit flags. A combined 18-scenario stress test found and fixed two edge-case faults (IRR/EM guards; waterfall sponsor-plug for zero-equity distribution). Then a developer-facing layer: a RAG verdict and a Go/Consider/No-Go decision block from profit on cost versus the target and a developer-set Consider band C115, with graduated wording, a gap-in-points that reconciles to the shown figures, and a break-even safety cushion. Every feature gated or one-way; base case unchanged (profit about 614,633 in the selected currency); all reconciliations 0. Open item: fold into the appraisal engine and the PULSE baseline handoff.

Sheet Read Me
A1: STACK funding engine
A2: Funding stack and waterfall, built as a deterministic engine you can drive and stress-test, in the same shape as the appraisal engine.
A4: Purpose | B4: The engine for STACK funding. It demonstrates the settled architecture: funding is a stack of sources plus a distribution waterfall, and every named approach is a configuration of that one structure. Built to be driven and tested, not just read.
A6: How the sheets layer (the engine map)
A7: 1. Inputs | B7: The single source of truth. Blue cells are yours to change; green cells derive. Each input carries its basis.
A8: 2. Cashflow | B8: Spreads cash uses over the programme and rolls up senior debt month by month. Interest accrues on the opening balance, so there is no circular reference. The reconciliation cell confirms cash uses are fully funded.
A9: 3. Waterfall | B9: Repays senior debt, returns capital, pays the preferred return, then splits the residual with the sponsor promote. The pref accrues on capital, so it is deterministic. The reconciliation cell confirms senior plus all takes equals the NDV.
A10: 4. Summary | B10: The review surface: headline outputs, funding at peak, the viability verdict, and each party outcome. Change an input and watch it move.
A11: 5. Sensitivity | B11: Two grids. One tests scheme viability as GDV and build cost move. One tests the JV deal terms as the preferred return and promote move. Both re-derive live, not as native data tables.
A12: 6. Comparison | B12: The same scheme funded five ways, the proof that an approach is a configuration. Finance is a transparent estimate; the JV column links the exact figures.
A14: Design locked in conversation
A15: Funding is the axis | B15: Funding structure changes the cashflow shape. Geography is a parametric tailoring layer on top, not a separate engine.
A16: Land-for-equity | B16: In. Land is a capital contribution at its agreed valuation, not a cash purchase. The landowner joins the waterfall, so the return is land value plus a profit share.
A17: Determinism | B17: Pref accrues on capital and the promote is on profit hurdles, not IRR hurdles, so the engine derives rather than solves. No number is invented; each traces to an input and a rule.
A19: Deferred to the next sub-steps
A20: Next | B20: Objective-awareness layer, then the PULSE financial-baseline handoff, then folding this into the appraisal engine to form one STACK model. Off-plan revenue timing is shown illustratively until the cashflow is extended for it.
A22: Conventions
A23: Colours | B23: Blue is an input you change. Green is derived or linked. Black bold is a subtotal. Amber and cream mark headline outputs and verdicts.
A24: House style | B24: UK spelling throughout. No em dashes or en dashes anywhere. The names are Flitrr, PULSE, ROUTE, STACK.
A25: Disclaimer | B25: Illustrative figures for design purposes. Not investment, financial, or valuation advice.

Sheet Summary
A1: OUTPUT | Funding and returns summary | X1: Sponsor | Y1: =K15 -> 332161.91
A2: Flitrr STACK | funding engine (reference model). Every figure derives from Inputs through the Cashflow and Waterfall. | X2: Partner | Y2: =L15 -> 135966.13
A3: ="This scheme is funded by "&Inputs!$C$5&" and makes about "&Inputs!$C$79&TEXT($M$8,"#,##0")&" profit, a "&TEXT($M$8/(Inputs!$C$53+Engine!$B$21),"0.0%")&" profit on cost. "&IF((ROUND($M$8/(Inputs!$C$53+Engine!$B$21)*100,1)-ROUND(Inputs!$C$47*100,1))=0,"That is in line with your "&TEXT(Inputs!$C$47,"0.0%")&" target.","That is "&TEXT(ABS((ROUND($M$8/(Inputs!$C$53+Engine!$B$21)*100,1)-ROUND(Inputs!$C$47*100,1))),"0.0")&" points "&IF((ROUND($M$8/(Inputs!$C$53+Engine!$B$21)*100,1)-ROUND(Inputs!$C$47*100,1))>0,"above","below")&" your "&TEXT(Inputs!$C$47,"0.0%")&" target.")&" "&IF($M$8<=0,"On these numbers the scheme loses money, so this is a No Go.",IF(($M$8/(Inputs!$C$53+Engine!$B$21)-Inputs!$C$47)>=Inputs!$C$115,"That comfortably clears your hurdle, a strong margin, so this looks like a Go.",IF(($M$8/(Inputs!$C$53+Engine!$B$21)-Inputs!$C$47)>=0,"That clears your hurdle, so this is a Go.",IF(($M$8/(Inputs!$C$53+Engine!$B$21)-Inputs!$C$47)>=-Inputs!$C$115/2,"That is marginally under your target, broadly in line, so treat it as Consider.",IF(($M$8/(Inputs!$C$53+Engine!$B$21)-Inputs!$C$47)>=-Inputs!$C$115,"That is below your target, so the margin is thinner than you would like, a Consider.","That is well short of your hurdle, the numbers do not work as they stand, so this is a No Go.")))))&IF($M$8>0," As a safety cushion, sale values could come in about "&TEXT($M$8/Inputs!$C$25,"0.0%")&" below plan before the profit disappears.","") -> This scheme is funded by Joint venture and makes about ₦614,633 profit, a 19.5% profit on cost. That is 0.5 points below your 20.0% target. That is marginally under your target, broadly in line, so treat it as Consider. As a safety cushion, sale values could come in about 16.3% below plan before the profit disappears. | X3: Landowner | Y3: =M15 -> 223504.65
A4: ="All amounts in "&Inputs!$C$80&" ("&Inputs!$C$79&")" -> All amounts in NGN (₦)
A5: SCHEME & TIMING | D5: SOURCES & USES | J5: RETURN METRICS
A6: Funding route | B6: =Inputs!$C$5 -> Joint venture | E6: =Inputs!$C$79 -> ₦ | F6: % total | G6: =Inputs!$C$79&"/ft²" -> ₦/ft² | H6: =Inputs!$C$79&"/plot" -> ₦/plot | K6: IRR | L6: MOIC | M6: Profit
A7: GDV | B7: =Inputs!$C$23 -> 3850000 | D7: USES | J7: Project (unlevered) | K7: =Engine!$B$38 -> 0.20863441 | L7: =Engine!$B$39 -> 1.3038711 | M7: =Inputs!$C$25-Inputs!$C$53 -> 879309
A8: NDV (net of sales costs) | B8: =Inputs!$C$25 -> 3773000 | D8: Land at value | E8: =Inputs!$C$30 -> 525000 | F8: =IFERROR(E8/$E$15,0) -> 0.18142919 | G8: =IF(Inputs!$C$74="","",E8/Inputs!$C$74) | H8: =IF(Inputs!$C$75="","",E8/Inputs!$C$75) | J8: Equity (levered) | K8: =Engine!$B$40 -> 0.32250519 | L8: =Engine!$B$41 -> 1.4890586 | M8: =Inputs!$C$25-(Inputs!$C$53+Engine!$B$21) -> 614632.69
A9: Net saleable area (sq ft) | B9: =IF(Inputs!$C$74="","–",Inputs!$C$74) -> – | D9: SDLT | E9: =Inputs!$C$18*Inputs!$C$31 -> 0 | F9: =IFERROR(E9/$E$15,0) -> 0 | G9: =IF(Inputs!$C$74="","",E9/Inputs!$C$74) | H9: =IF(Inputs!$C$75="","",E9/Inputs!$C$75) | J9: Equity (after-tax) | K9: =Engine!$B$45 -> 0.25042974 | L9: =Engine!$B$46 -> 1.3667939 | M9: =Engine!$B$44 -> 460974.52
A10: Number of plots / units | B10: =IF(Inputs!$C$75="","–",Inputs!$C$75) -> – | D10: Construction | E10: =Inputs!$C$97 -> 2014249 | F10: =IFERROR(E10/$E$15,0) -> 0.69608296 | G10: =IF(Inputs!$C$74="","",E10/Inputs!$C$74) | H10: =IF(Inputs!$C$75="","",E10/Inputs!$C$75)
A11: TIMING | D11: Professional fees | E11: =Inputs!$C$27 -> 221567 | F11: =IFERROR(E11/$E$15,0) -> 0.076568991 | G11: =IF(Inputs!$C$74="","",E11/Inputs!$C$74) | H11: =IF(Inputs!$C$75="","",E11/Inputs!$C$75) | J11: PARTNERSHIP (by party)
A12: Programme (months) | B12: =Inputs!$C$32 -> 30 | D12: Statutory | E12: =Inputs!$C$28 -> 48000 | F12: =IFERROR(E12/$E$15,0) -> 0.016587811 | G12: =IF(Inputs!$C$74="","",E12/Inputs!$C$74) | H12: =IF(Inputs!$C$75="","",E12/Inputs!$C$75) | K12: Sponsor | L12: Partner | M12: Landowner
A13: Commencement | B13: =Inputs!$C$10 -> 46204 | D13: Acquisition & legal | E13: =Inputs!$C$29 -> 7875 | F13: =IFERROR(E13/$E$15,0) -> 0.0027214378 | G13: =IF(Inputs!$C$74="","",E13/Inputs!$C$74) | H13: =IF(Inputs!$C$75="","",E13/Inputs!$C$75) | J13: Contribution | K13: =Waterfall!$C$6 -> 219530.12 | L13: =Waterfall!$D$6 -> 512236.95 | M13: =Waterfall!$E$6 -> 525000
A14: Completion | B14: =EDATE(Inputs!$C$10,Inputs!$C$35-1) -> 47088 | D14: Development management fee | E14: =Inputs!$C$50 -> 77000 | F14: =IFERROR(E14/$E$15,0) -> 0.026609614 | G14: =IF(Inputs!$C$74="","",E14/Inputs!$C$74) | H14: =IF(Inputs!$C$75="","",E14/Inputs!$C$75) | J14: Distribution | K14: =Waterfall!$C$33 -> 551692.03 | L14: =Waterfall!$D$33 -> 648203.08 | M14: =Waterfall!$E$33 -> 748504.65
A15: Pre-sales (off-plan) | B15: =Inputs!$C$63 -> No | D15: Total project cost | E15: =Inputs!$C$53 -> 2893691 | F15: =IFERROR(E15/$E$15,0) -> 1 | G15: =IF(Inputs!$C$74="","",E15/Inputs!$C$74) | H15: =IF(Inputs!$C$75="","",E15/Inputs!$C$75) | J15: Profit | K15: =Waterfall!$C$35 -> 332161.91 | L15: =Waterfall!$D$35 -> 135966.13 | M15: =Waterfall!$E$35 -> 223504.65
A16: Target profit on cost | B16: =Inputs!$C$47 -> 0.2 | D16: Finance cost (memo) | E16: =Engine!$B$21 -> 264676.31 | J16: Equity multiple | K16: =Waterfall!$C$36 -> 2.5130585 | L16: =Waterfall!$D$36 -> 1.265436 | M16: =Waterfall!$E$36 -> 1.4257231
D17: SOURCES | J17: IRR (p.a.) | K17: =Engine!$B$51 -> 5.0465773 | L17: =Engine!$B$52 -> 0.60907431 | M17: =Engine!$B$53 -> 0.15808038
A18: DECISION | D18: Senior debt | E18: =Inputs!$C$52-Engine!$B$23-Engine!$B$30-Engine!$B$27 -> 1636923.9 | F18: =IFERROR(E18/$E$24,0) -> 0.56568719 | G18: =IF(Inputs!$C$74="","",E18/Inputs!$C$74) | H18: =IF(Inputs!$C$75="","",E18/Inputs!$C$75) | J18: Per-party IRR reflects the timing of each party's own cash. It runs high where capital goes in late and thin (e.g. sponsor cash after senior), and lower for land contributed from day one.
A19: =IF($M$8<=0,"NO GO",IF($M$8/(Inputs!$C$53+Engine!$B$21)>=Inputs!$C$47,"GO",IF($M$8/(Inputs!$C$53+Engine!$B$21)>=Inputs!$C$47-Inputs!$C$115,"CONSIDER","NO GO"))) -> CONSIDER | D19: Mezzanine | E19: =Engine!$B$27 -> 0 | F19: =IFERROR(E19/$E$24,0) -> 0 | G19: =IF(Inputs!$C$74="","",E19/Inputs!$C$74) | H19: =IF(Inputs!$C$75="","",E19/Inputs!$C$75) | J19: AUDIT CHECKS
A20: =IF((ROUND($M$8/(Inputs!$C$53+Engine!$B$21)*100,1)-ROUND(Inputs!$C$47*100,1))=0,"(in line with target)","("&TEXT(ABS((ROUND($M$8/(Inputs!$C$53+Engine!$B$21)*100,1)-ROUND(Inputs!$C$47*100,1))),"0.0")&" points "&IF((ROUND($M$8/(Inputs!$C$53+Engine!$B$21)*100,1)-ROUND(Inputs!$C$47*100,1))>0,"above","below")&" target)") -> (0.5 points below target) | D20: Pre-sale receipts | E20: =Engine!$B$30 -> 0 | F20: =IFERROR(E20/$E$24,0) -> 0 | G20: =IF(Inputs!$C$74="","",E20/Inputs!$C$74) | H20: =IF(Inputs!$C$75="","",E20/Inputs!$C$75) | J20: Cash uses reconciliation | M20: =IF(ABS(Engine!$B$26)<1,"OK","CHECK") -> OK
D21: Sponsor equity | E21: =Engine!$B$24 -> 219530.12 | F21: =IFERROR(E21/$E$24,0) -> 0.075865088 | G21: =IF(Inputs!$C$74="","",E21/Inputs!$C$74) | H21: =IF(Inputs!$C$75="","",E21/Inputs!$C$75) | J21: Waterfall reconciliation | M21: =IF(ABS(Waterfall!$F$39)<1,"OK","CHECK") -> OK
D22: Funding partner equity | E22: =Engine!$B$25 -> 512236.95 | F22: =IFERROR(E22/$E$24,0) -> 0.17701854 | G22: =IF(Inputs!$C$74="","",E22/Inputs!$C$74) | H22: =IF(Inputs!$C$75="","",E22/Inputs!$C$75) | J22: Cashflow ties to profit | M22: =IF(ABS(Cashflow!$AK$25-$M$8)<1,"OK","CHECK") -> OK
D23: Contributed land (equity) | E23: =IF(Inputs!$C$17=1,Inputs!$C$30,0) -> 525000 | F23: =IFERROR(E23/$E$24,0) -> 0.18142919 | G23: =IF(Inputs!$C$74="","",E23/Inputs!$C$74) | H23: =IF(Inputs!$C$75="","",E23/Inputs!$C$75) | J23: Sources equal uses | M23: =IF(ABS($E$25)<1,"OK","CHECK") -> OK
D24: Total sources | E24: =SUM(E18:E23) -> 2893691 | F24: =IFERROR(E24/$E$24,0) -> 1 | G24: =IF(Inputs!$C$74="","",E24/Inputs!$C$74) | H24: =IF(Inputs!$C$75="","",E24/Inputs!$C$75) | J24: Sales cover senior and mezzanine | M24: =IF(Inputs!$C$25>=Engine!$B$20+Engine!$B$29,"OK","CHECK") -> OK
D25: Sources less uses (check) | E25: =E24-E15 -> 0 | J25: Project profit not negative | M25: =IF($M$8>=0,"OK","CHECK") -> OK
A28: CREDIT & MARGIN | J28: VIABILITY
A29: Senior loan-to-cost | B29: =IFERROR(Inputs!$C$54/Inputs!$C$53,0) -> 0.6 | D29: Limit (LTC) | E29: =Inputs!$C$39 -> 0.6 | J29: Viability verdict | K29: =IF($M$8/(Inputs!$C$53+Engine!$B$21)>=Inputs!$C$47,"On or above target","Below target") -> Below target
A30: Senior loan-to-GDV | B30: =IFERROR(Inputs!$C$54/Inputs!$C$23,0) -> 0.45096483 | D30: Limit (LTGDV) | E30: =Inputs!$C$40 -> 0.55 | J30: Margin vs target | K30: =$M$8/(Inputs!$C$53+Engine!$B$21)-Inputs!$C$47 -> -0.0053954365
A31: Peak senior exposure | B31: =Engine!$B$22 -> 1856987.1 | D31: Peak / GDV | E31: =IFERROR(Engine!$B$22/Inputs!$C$23,0) -> 0.48233432 | J31: Preferred return covered | K31: =IF(Waterfall!$F$17>=Waterfall!$F$21,"Yes, in full",IF(Waterfall!$F$22>0,"Partly","No")) -> Yes, in full
A32: Profit on cost | B32: =$M$8/(Inputs!$C$53+Engine!$B$21) -> 0.19460456 | D32: Profit on GDV (margin) | E32: =$M$8/Inputs!$C$23 -> 0.15964485 | J32: Promote / carry earned | K32: =IF(Waterfall!$F$26>0,"Yes","No") -> Yes
A33: Finance cost / GDV | B33: =IFERROR(Engine!$B$21/Inputs!$C$23,0) -> 0.068747093 | D33: Profit cover of finance | E33: =IFERROR($M$8/Engine!$B$21,"n/a") -> 2.3222052 | J33: Residual to final tier | K33: =Waterfall!$F$26 -> 393781.43
A34: RESIDUAL LAND VALUE (indicative)
A35: Max land bid for target profit on cost | B35: =Inputs!$C$25/(1+Inputs!$C$47)-Engine!$B$21-(Inputs!$C$53-Inputs!$C$30) -> 510799.36 | D35: Current land value | E35: =Inputs!$C$30 -> 525000 | G35: Headroom vs current | H35: =B35-E35 -> -14200.642 | J35: RLV per plot | K35: =IFERROR(B35/Inputs!$C$75,"–") -> –
A36: Indicative: finance and non-land costs held at the current scheme. Above this land price, profit on cost falls below target. Solving the finance feedback exactly needs iteration, which STACK avoids by design.
A37: FUNDING ROUTES COMPARED (this scheme)
A38: Strategy | B38: Cash in | D38: Profit | E38: Return on cash | F38: PoC | G38: Trade-off
A39: Self-funded | B39: =Comparison!$C$33 -> 2842941 | D39: =Comparison!$C$35 -> 930059 | E39: =Comparison!$C$36 -> 1.3271468 | F39: =Comparison!$C$32 -> 0.32714678 | G39: Most cash in, no debt, simplest to run
A40: Bank-financed | B40: =Comparison!$D$33 -> 1390908.9 | D40: =Comparison!$D$35 -> 676326.52 | E40: =Comparison!$D$36 -> 1.4862479 | F40: =Comparison!$D$32 -> 0.21840421 | G40: Senior debt lowers cash in, adds interest
A41: Mixed (senior + mezz) | B41: =Comparison!$E$33 -> 916137.74 | D41: =Comparison!$E$35 -> 582509.46 | E41: =Comparison!$E$36 -> 1.6358318 | F41: =Comparison!$E$32 -> 0.18257677 | G41: Senior plus mezzanine, least cash in
A42: Joint venture (selected) | B42: =Comparison!$F$33 -> 219530.12 | D42: =Comparison!$F$35 -> 332161.91 | E42: =Comparison!$F$36 -> 2.5130585 | F42: =Comparison!$F$32 -> 0.19460456 | G42: Land-for-equity, profit shared (live route)
A43: Off-plan | B43: =Comparison!$G$33 -> 1339783.4 | D43: =Comparison!$G$35 -> 864371.51 | E43: =Comparison!$G$36 -> 1.6451577 | F43: =Comparison!$G$32 -> 0.29717495 | G43: Pre-sales fund the build, less interest
A44: Cash in and profit are your slice; the live route links the engine, the others are closed-form estimates.

Sheet Inputs
A1: INPUT | Inputs
A2: Single source of truth. Blue cells are assumptions you change; everything downstream derives from here. Each input carries its basis, the trace the product will show.
A3: ="Type only in the yellow cells. The grey cells are worked out for you and are locked. All amounts in "&$C$80&" ("&$C$79&")." -> Type only in the yellow cells. The grey cells are worked out for you and are locked. All amounts in NGN (₦).
A4: Funding strategy
A5: Funding strategy | C5: Joint venture | E5: Choose how the scheme is funded. This is the main switch and it drives every other tab.
A6: Debt structure (if Debt-financed) | C6: Senior loan only | E6: =IF($C$5="Debt-financed","Senior alone, or senior plus mezzanine.","Not required, applies to Debt-financed only.") -> Not required, applies to Debt-financed only.
A7: JV partner contributes (if Joint venture) | C7: Both | E7: =IF($C$5="Joint venture","What the partner brings: Cash, Land, or Both.","Not required, applies to Joint venture only.") -> What the partner brings: Cash, Land, or Both.
A8: Senior debt alongside the JV? (if Joint venture) | C8: Yes | E8: =IF($C$5="Joint venture","Whether senior debt sits alongside the partner equity.","Not required, applies to Joint venture only.") -> Whether senior debt sits alongside the partner equity.
A9: Do you already own the land? | C9: No | E9: Yes means the land is your contribution at its value. No means you buy it for cash and pay SDLT.
A10: Project commencement date | C10: 46204 | D10: date | E10: The calendar start. Month 1 of the cashflow is this month.
A11: Mezzanine interest rate (if mezzanine) | C11: 0.12 | D11: % pa | E11: =IF($C$14=1,"Rate on the mezzanine top-up. Typical 10 to 14% pa.","Not required, applies to the mezzanine branch only.") -> Not required, applies to the mezzanine branch only.
A12: Strategy switches (derived, read only)
A13: Use senior debt | C13: =IF($C$5="Self-funded",0,IF($C$5="Joint venture",IF($C$8="Yes",1,0),1)) -> 1 | E13: Derived from your selections.
A14: Use mezzanine | C14: =IF(AND($C$5="Debt-financed",$C$6="Senior plus mezzanine"),1,0) -> 0 | E14: Derived from your selections.
A15: Partner provides cash | C15: =IF(AND($C$5="Joint venture",OR($C$7="Cash",$C$7="Both")),1,0) -> 1 | E15: Derived from your selections.
A16: Partner provides land | C16: =IF(AND($C$5="Joint venture",OR($C$7="Land",$C$7="Both")),1,0) -> 1 | E16: Derived from your selections.
A17: Land treated as contributed equity | C17: =IF(OR($C$9="Yes",$C$16=1),1,0) -> 1 | E17: Land joins the waterfall as equity, rather than being bought for cash.
A18: Land is a cash purchase (plus SDLT) | C18: =IF($C$17=1,0,1) -> 0 | E18: Land and SDLT become a cash cost funded by debt or equity.
A19: Funding partner cash split (effective) | C19: =IF($C$15=1,$C$45,0) -> 0.7 | E19: Share of cash equity the partner funds. Zero unless a Joint venture with cash.
A20: Preferred return and promote active | C20: =IF($C$5="Joint venture",1,0) -> 1 | E20: Preferred return and promote apply on the Joint venture route only.
A21: Mezzanine combined loan to cost (if mezzanine) | C21: 0.75 | D21: % | E21: =IF($C$14=1,"Basis: senior plus mezzanine lifts cost gearing, typical 70 to 80%.","Not required, applies to the mezzanine branch only.") -> Not required, applies to the mezzanine branch only.
A22: Scheme
A23: Gross development value (GDV) | C23: 3850000 | D23: =$C$79 -> ₦ | E23: Sale value of the finished scheme.
A24: Sales costs (agent and legal) | C24: 0.02 | D24: % | E24: Deducted from GDV.
A25: Net development value (NDV) | C25: =Inputs!$C$23*(1+Inputs!$C$96)^(Inputs!$C$35/12)*(1-Inputs!$C$24) -> 3773000 | D25: =$C$79 -> ₦ | E25: Derived. What the project receives on sale.
A26: Construction cost | C26: 2014249 | D26: =$C$79 -> ₦ | E26: Build cost, all elements.
A27: Professional fees | C27: 221567 | D27: =$C$79 -> ₦ | E27: Design and consultant team.
A28: Statutory (S106 / CIL and other) | C28: 48000 | D28: =$C$79 -> ₦ | E28: Planning obligations and levies.
A29: Acquisition and legal | C29: 7875 | D29: =$C$79 -> ₦ | E29: Deal and legal costs at the front.
A30: Land value (agreed) | C30: 525000 | D30: =$C$79 -> ₦ | E30: Agreed worth of the land.
A31: SDLT if land is purchased for cash | C31: 26250 | D31: =$C$79 -> ₦ | E31: =IF($C$18=1,"Stamp duty on the cash land purchase.","Not required, the land is contributed not purchased.") -> Not required, the land is contributed not purchased.
A32: Programme | C32: 30 | D32: mo | E32: Total project length.
A33: Construction start month | C33: 7 | D33: mo | E33: When build draws begin.
A34: Construction end month | C34: 27 | D34: mo | E34: When build draws finish.
A35: Completion and sale month | C35: 30 | D35: mo | E35: When the NDV is received.
A37: Funding terms
A38: Development management fee (% of GDV) | C38: 0.02 | D38: % | E38: Basis: typically 1.5 to 3% of GDV. Paid to the sponsor.
A39: Senior debt, loan to cost cap | C39: 0.6 | D39: % | E39: =IF($C$13=1,"Basis: regional LTC 50 to 70%.","Not required, this route uses no senior debt.") -> Basis: regional LTC 50 to 70%.
A40: Senior debt, loan to GDV cap | C40: 0.55 | D40: % | E40: =IF($C$13=1,"Basis: regional LTGDV cap.","Not required, this route uses no senior debt.") -> Basis: regional LTGDV cap.
A41: Senior interest rate | C41: 0.09 | D41: % pa | E41: =IF($C$13=1,"Basis: 6.5 to 9%. Rolled up, not paid in cash.","Not required, this route uses no senior debt.") -> Basis: 6.5 to 9%. Rolled up, not paid in cash.
A42: Senior arrangement fee | C42: 0.015 | D42: % | E42: =IF($C$13=1,"Basis: 1 to 2% of facility.","Not required, this route uses no senior debt.") -> Basis: 1 to 2% of facility.
A43: Senior exit fee | C43: 0.01 | D43: % | E43: =IF($C$13=1,"Basis: 1 to 2% on redemption.","Not required, this route uses no senior debt.") -> Basis: 1 to 2% on redemption.
A44: Preferred return (all equity) | C44: 0.1 | D44: % pa | E44: =IF($C$20=1,"Basis: JV preferred return hurdle.","Not required, applies to Joint venture only.") -> Basis: JV preferred return hurdle.
A45: Cash equity split, funding partner | C45: 0.7 | D45: % | E45: =IF($C$20=1,"Basis: JV term. Sponsor funds the remainder.","Not required, applies to Joint venture only.") -> Basis: JV term. Sponsor funds the remainder.
A46: Residual profit to capital (pro-rata) | C46: 0.5 | D46: % | E46: =IF($C$20=1,"Basis: JV waterfall. Remainder is the promote.","Not required, applies to Joint venture only.") -> Basis: JV waterfall. Remainder is the promote.
A47: Target profit on cost (hurdle) | C47: 0.2 | D47: % | E47: Basis: SME hurdle 15 to 20%.
A49: Derived sizing
A50: Development management fee | C50: =Inputs!$C$38*Inputs!$C$23 -> 77000 | D50: =$C$79 -> ₦ | E50: Fee in money terms.
A51: Cash development cost (ex land, ex SDLT) | C51: =Inputs!$C$97+Inputs!$C$27+Inputs!$C$28+Inputs!$C$29 -> 2291691 | D51: =$C$79 -> ₦ | E51: Core build and soft costs in cash.
A52: Total cash uses (ex land, incl fee) | C52: =Inputs!$C$51+Inputs!$C$50+Inputs!$C$18*(Inputs!$C$30+Inputs!$C$31) -> 2368691 | D52: =$C$79 -> ₦ | E52: Cash the project spends, before finance.
A53: Total project cost (incl land at valuation) | C53: =Inputs!$C$52+Inputs!$C$17*Inputs!$C$30 -> 2893691 | D53: =$C$79 -> ₦ | E53: Full cost including land at value.
A54: Senior facility limit | C54: =Inputs!$C$13*MIN(Inputs!$C$39*Inputs!$C$53,Inputs!$C$40*Inputs!$C$23) -> 1736214.6 | D54: =$C$79 -> ₦ | E54: Lower of the two caps binds.
A55: Sponsor cash equity split | C55: =1-Inputs!$C$45 -> 0.3 | D55: % | E55: Remainder of the cash equity.
A56: Promote to sponsor (residual) | C56: =1-Inputs!$C$46 -> 0.5 | D56: % | E56: Sponsor reward above the pref.
A58: JV promote hurdle (optional test)
A59: Promote hurdle basis (JV) | C59: Preferred return | E59: Test basis for the JV promote hurdle. Preferred return uses the preferred return rate above; Equity multiple uses the multiple hurdle below.
A60: Equity multiple hurdle | C60: 1.3 | D60: x | E60: Partner and landowner must reach this multiple on their capital before the sponsor promote applies. Used only when the basis is Equity multiple.
A62: OFF-PLAN PRE-SALES (optional)
A63: Model pre-sales | C63: No | E63: Turn on to fund construction with pre-sale receipts during the build. Reduces the senior balance and rolled-up interest. Default No leaves the base case unchanged.
A64: Pre-sale proportion of NDV | C64: 0.5 | D64: % | E64: Share of net sales received in stages across construction. Each month is capped at that month's cost; any surplus completes at the end.
A66: TAX (after-tax returns)
A67: Corporation tax rate | C67: 0.25 | D67: % | E67: UK corporation tax on project profit, after finance costs (which are deductible). Drives the after-tax returns on the Summary. Set 0% to ignore tax; pre-tax figures are never affected.
A69: GP CATCH-UP AND CARRY (JV, optional)
A70: Use GP catch-up and carry | C70: No | E70: Turn on to replace the simple residual split with an institutional pref then GP catch-up then carry. Default No keeps the existing residual-to-capital plus sponsor promote. JV routes only.
A71: Carried interest (GP carry) | C71: 0.2 | D71: % | E71: GP share of profit above the preferred return. With a 100% catch-up, the GP receives all residual after pref until it reaches this share of the profit above capital, then the split runs at this carry.
A73: SCHEME METRICS (optional, for per-unit display)
A74: Net saleable area | C74: =IF($B$111>0,$B$111,"") | D74: sq ft | E74: Optional. Net saleable / sellable floor area. Drives the per square foot column on the Summary dashboard. Leave blank to hide it.
A75: Number of plots / units | C75: =IF($B$110>0,$B$110,"") | D75: # | E75: Optional. Number of plots or units. Drives the per plot column on the Summary dashboard. Leave blank to hide it.
A77: CURRENCY
A78: Reporting currency | C78: NGN | E78: Reporting currency for the whole workbook. Drives the currency banner on every tab. Amounts are shown without a symbol; the banner states the unit.
A79: Currency symbol (derived) | C79: =CHOOSE(MATCH($C$78,{"GBP";"USD";"EUR";"NGN";"SAR";"CNY"},0),"£","$","€","₦","﷼","¥") -> ₦
A80: Currency code (derived) | C80: =$C$78 -> NGN
A82: CONTINGENCY
A83: Construction contingency (% of build cost) | C83: 0 | D83: % | E83: Buffer on the build cost. Best practice 5 to 7.5%. Flows into cost, finance sizing and the cashflow. Default 0% leaves the base case unchanged.
A85: SELL-DOWN / VOID
A86: Holding cost during void (per month) | C86: 0 | D86: /mo | E86: Running cost per month on unsold units between construction end and sale (rates, service charge, marketing, security). Applies over the void window (sale month minus construction-end month). Default 0 leaves the base case unchanged.
A88: INTEREST BASIS
A89: Interest accrual basis | C89: Opening balance | E89: Opening balance is the simple roll-up. Average balance also charges half a month of interest on each new drawdown (more precise, slightly higher finance cost). Default Opening balance leaves the base case unchanged.
A91: CONSTRUCTION PROFILE
A92: Build cost drawdown profile | C92: Even | E92: Even spreads build cost equally across the construction months. S-curve back-loads then tapers (slow start, mid peak), which changes interest timing. Total build cost is unchanged either way. Default Even leaves the base case unchanged.
A94: INFLATION / ESCALATION
A95: Build cost inflation (% pa) | C95: 0 | D95: % pa | E95: Escalates the build cost to the construction midpoint. Default 0 leaves the base case unchanged.
A96: Sales value growth (% pa) | C96: 0 | D96: % pa | E96: Grows GDV from today to the sale month. Net development value derives from the grown GDV. Default 0 leaves the base case unchanged.
A97: Effective build cost (derived) | C97: =Inputs!$C$26*(1+Inputs!$C$83)*(1+Inputs!$C$95)^((Inputs!$C$33+Inputs!$C$34)/2/12) -> 2014249
A99: FUNDING SEQUENCE
A100: Funding sequence | C100: Debt first | E100: Debt first draws senior to its cap, then equity (current). Equity first funds the front-end (land and pre-construction) from equity and draws senior for construction, which lowers early interest but deploys equity sooner. Default Debt first leaves the base case unchanged.
A102: UNIT MIX (optional, drives area and plots)
A103: Unit type | B103: Count | C103: Area each (sq ft) | D103: Price each | E103: Line GDV
E104: =IF(B104="","",B104*D104)
E105: =IF(B105="","",B105*D105)
E106: =IF(B106="","",B106*D106)
E107: =IF(B107="","",B107*D107)
E108: =IF(B108="","",B108*D108)
E109: =IF(B109="","",B109*D109)
A110: Totals | B110: =SUM(B104:B109) -> 0 | E110: =SUM(E104:E109) -> 0
A111: Total saleable area (sq ft) | B111: =SUMPRODUCT(B104:B109,C104:C109) -> 0
A112: GDV from mix less GDV input | B112: =IF(SUM(B104:B109)=0,"–",E110-$C$23) -> –
A114: DECISION RULE
A115: Consider band (points below target) | C115: 0.05 | D115: pts | E115: If profit on cost is within this many points below your target, the decision shows CONSIDER (amber); further below shows NO GO (red); at or above target shows GO (green).

Sheet Cashflow
A1: OUTPUT | Cashflow by phase and month
A2: ="Costs by phase and the sale, spread across the calendar from your commencement date. The cumulative cash position is the funding requirement, ending at project profit. All amounts in "&Inputs!$C$80&" ("&Inputs!$C$79&")." -> Costs by phase and the sale, spread across the calendar from your commencement date. The cumulative cash position is the funding requirement, ending at project profit. All amounts in NGN (₦).
A3: Cashflow by phase | C3: Months (from commencement date) | AG3: Calendar-year subtotals | AK3: Total
A4: Phase | B4: Line item | C4: =Inputs!$C$10 -> 46204 | D4: =EDATE($C$4,COLUMN()-3) -> 46235 | E4: =EDATE($C$4,COLUMN()-3) -> 46266 | F4: =EDATE($C$4,COLUMN()-3) -> 46296 | G4: =EDATE($C$4,COLUMN()-3) -> 46327 | H4: =EDATE($C$4,COLUMN()-3) -> 46357 | I4: =EDATE($C$4,COLUMN()-3) -> 46388 | J4: =EDATE($C$4,COLUMN()-3) -> 46419 | K4: =EDATE($C$4,COLUMN()-3) -> 46447 | ... AF4: =EDATE($C$4,COLUMN()-3) -> 47088 | AG4: =YEAR($C$4) -> 2026 | AH4: =AG4+1 -> 2027 | AI4: =AG4+2 -> 2028 | AJ4: =AG4+3 -> 2029 | AK4: Project total
A5: Acquisition | B5: Land (at value) | C5: =IF((COLUMN()-2)=1,-Inputs!$C$30,0) -> -525000 | D5: =IF((COLUMN()-2)=1,-Inputs!$C$30,0) -> 0 | E5: =IF((COLUMN()-2)=1,-Inputs!$C$30,0) -> 0 | F5: =IF((COLUMN()-2)=1,-Inputs!$C$30,0) -> 0 | G5: =IF((COLUMN()-2)=1,-Inputs!$C$30,0) -> 0 | H5: =IF((COLUMN()-2)=1,-Inputs!$C$30,0) -> 0 | I5: =IF((COLUMN()-2)=1,-Inputs!$C$30,0) -> 0 | J5: =IF((COLUMN()-2)=1,-Inputs!$C$30,0) -> 0 | ... AF5: =IF((COLUMN()-2)=1,-Inputs!$C$30,0) -> 0 | AG5: {=SUMPRODUCT((YEAR($C$4:$AF$4)=AG$4)*$C5:$AF5)} -> -525000 | AH5: {=SUMPRODUCT((YEAR($C$4:$AF$4)=AH$4)*$C5:$AF5)} -> 0 | AI5: {=SUMPRODUCT((YEAR($C$4:$AF$4)=AI$4)*$C5:$AF5)} -> 0 | AJ5: {=SUMPRODUCT((YEAR($C$4:$AF$4)=AJ$4)*$C5:$AF5)} -> 0 | AK5: =SUM($C5:$AF5) -> -525000
B6: Stamp duty (SDLT) | C6: =IF(AND((COLUMN()-2)=1,Inputs!$C$18=1),-Inputs!$C$31,0) -> 0 | D6: =IF(AND((COLUMN()-2)=1,Inputs!$C$18=1),-Inputs!$C$31,0) -> 0 | E6: =IF(AND((COLUMN()-2)=1,Inputs!$C$18=1),-Inputs!$C$31,0) -> 0 | F6: =IF(AND((COLUMN()-2)=1,Inputs!$C$18=1),-Inputs!$C$31,0) -> 0 | G6: =IF(AND((COLUMN()-2)=1,Inputs!$C$18=1),-Inputs!$C$31,0) -> 0 | H6: =IF(AND((COLUMN()-2)=1,Inputs!$C$18=1),-Inputs!$C$31,0) -> 0 | I6: =IF(AND((COLUMN()-2)=1,Inputs!$C$18=1),-Inputs!$C$31,0) -> 0 | J6: =IF(AND((COLUMN()-2)=1,Inputs!$C$18=1),-Inputs!$C$31,0) -> 0 | ... AF6: =IF(AND((COLUMN()-2)=1,Inputs!$C$18=1),-Inputs!$C$31,0) -> 0 | AG6: {=SUMPRODUCT((YEAR($C$4:$AF$4)=AG$4)*$C6:$AF6)} -> 0 | AH6: {=SUMPRODUCT((YEAR($C$4:$AF$4)=AH$4)*$C6:$AF6)} -> 0 | AI6: {=SUMPRODUCT((YEAR($C$4:$AF$4)=AI$4)*$C6:$AF6)} -> 0 | AJ6: {=SUMPRODUCT((YEAR($C$4:$AF$4)=AJ$4)*$C6:$AF6)} -> 0 | AK6: =SUM($C6:$AF6) -> 0
B7: Acquisition and legal | C7: =IF((COLUMN()-2)<=(Inputs!$C$33-1),-Inputs!$C$29/(Inputs!$C$33-1),0) -> -1312.5 | D7: =IF((COLUMN()-2)<=(Inputs!$C$33-1),-Inputs!$C$29/(Inputs!$C$33-1),0) -> -1312.5 | E7: =IF((COLUMN()-2)<=(Inputs!$C$33-1),-Inputs!$C$29/(Inputs!$C$33-1),0) -> -1312.5 | F7: =IF((COLUMN()-2)<=(Inputs!$C$33-1),-Inputs!$C$29/(Inputs!$C$33-1),0) -> -1312.5 | G7: =IF((COLUMN()-2)<=(Inputs!$C$33-1),-Inputs!$C$29/(Inputs!$C$33-1),0) -> -1312.5 | H7: =IF((COLUMN()-2)<=(Inputs!$C$33-1),-Inputs!$C$29/(Inputs!$C$33-1),0) -> -1312.5 | I7: =IF((COLUMN()-2)<=(Inputs!$C$33-1),-Inputs!$C$29/(Inputs!$C$33-1),0) -> 0 | J7: =IF((COLUMN()-2)<=(Inputs!$C$33-1),-Inputs!$C$29/(Inputs!$C$33-1),0) -> 0 | ... AF7: =IF((COLUMN()-2)<=(Inputs!$C$33-1),-Inputs!$C$29/(Inputs!$C$33-1),0) -> 0 | AG7: {=SUMPRODUCT((YEAR($C$4:$AF$4)=AG$4)*$C7:$AF7)} -> -7875 | AH7: {=SUMPRODUCT((YEAR($C$4:$AF$4)=AH$4)*$C7:$AF7)} -> 0 | AI7: {=SUMPRODUCT((YEAR($C$4:$AF$4)=AI$4)*$C7:$AF7)} -> 0 | AJ7: {=SUMPRODUCT((YEAR($C$4:$AF$4)=AJ$4)*$C7:$AF7)} -> 0 | AK7: =SUM($C7:$AF7) -> -7875
B8: Acquisition subtotal | C8: =SUM(C5:C7) -> -526312.5 | D8: =SUM(D5:D7) -> -1312.5 | E8: =SUM(E5:E7) -> -1312.5 | F8: =SUM(F5:F7) -> -1312.5 | G8: =SUM(G5:G7) -> -1312.5 | H8: =SUM(H5:H7) -> -1312.5 | I8: =SUM(I5:I7) -> 0 | J8: =SUM(J5:J7) -> 0 | ... AF8: =SUM(AF5:AF7) -> 0 | AG8: {=SUMPRODUCT((YEAR($C$4:$AF$4)=AG$4)*$C8:$AF8)} -> -532875 | AH8: {=SUMPRODUCT((YEAR($C$4:$AF$4)=AH$4)*$C8:$AF8)} -> 0 | AI8: {=SUMPRODUCT((YEAR($C$4:$AF$4)=AI$4)*$C8:$AF8)} -> 0 | AJ8: {=SUMPRODUCT((YEAR($C$4:$AF$4)=AJ$4)*$C8:$AF8)} -> 0 | AK8: =SUM($C8:$AF8) -> -532875
A9: Design and pre-construction | B9: Professional fees | C9: =IF((COLUMN()-2)<=(Inputs!$C$33-1),-0.3*Inputs!$C$27/(Inputs!$C$33-1),0)+IF(AND((COLUMN()-2)>=Inputs!$C$33,(COLUMN()-2)<=Inputs!$C$34),-0.7*Inputs!$C$27/(Inputs!$C$34-Inputs!$C$33+1),0) -> -11078.35 | D9: =IF((COLUMN()-2)<=(Inputs!$C$33-1),-0.3*Inputs!$C$27/(Inputs!$C$33-1),0)+IF(AND((COLUMN()-2)>=Inputs!$C$33,(COLUMN()-2)<=Inputs!$C$34),-0.7*Inputs!$C$27/(Inputs!$C$34-Inputs!$C$33+1),0) -> -11078.35 | E9: =IF((COLUMN()-2)<=(Inputs!$C$33-1),-0.3*Inputs!$C$27/(Inputs!$C$33-1),0)+IF(AND((COLUMN()-2)>=Inputs!$C$33,(COLUMN()-2)<=Inputs!$C$34),-0.7*Inputs!$C$27/(Inputs!$C$34-Inputs!$C$33+1),0) -> -11078.35 | F9: =IF((COLUMN()-2)<=(Inputs!$C$33-1),-0.3*Inputs!$C$27/(Inputs!$C$33-1),0)+IF(AND((COLUMN()-2)>=Inputs!$C$33,(COLUMN()-2)<=Inputs!$C$34),-0.7*Inputs!$C$27/(Inputs!$C$34-Inputs!$C$33+1),0) -> -11078.35 | G9: =IF((COLUMN()-2)<=(Inputs!$C$33-1),-0.3*Inputs!$C$27/(Inputs!$C$33-1),0)+IF(AND((COLUMN()-2)>=Inputs!$C$33,(COLUMN()-2)<=Inputs!$C$34),-0.7*Inputs!$C$27/(Inputs!$C$34-Inputs!$C$33+1),0) -> -11078.35 | H9: =IF((COLUMN()-2)<=(Inputs!$C$33-1),-0.3*Inputs!$C$27/(Inputs!$C$33-1),0)+IF(AND((COLUMN()-2)>=Inputs!$C$33,(COLUMN()-2)<=Inputs!$C$34),-0.7*Inputs!$C$27/(Inputs!$C$34-Inputs!$C$33+1),0) -> -11078.35 | I9: =IF((COLUMN()-2)<=(Inputs!$C$33-1),-0.3*Inputs!$C$27/(Inputs!$C$33-1),0)+IF(AND((COLUMN()-2)>=Inputs!$C$33,(COLUMN()-2)<=Inputs!$C$34),-0.7*Inputs!$C$27/(Inputs!$C$34-Inputs!$C$33+1),0) -> -7385.5667 | J9: =IF((COLUMN()-2)<=(Inputs!$C$33-1),-0.3*Inputs!$C$27/(Inputs!$C$33-1),0)+IF(AND((COLUMN()-2)>=Inputs!$C$33,(COLUMN()-2)<=Inputs!$C$34),-0.7*Inputs!$C$27/(Inputs!$C$34-Inputs!$C$33+1),0) -> -7385.5667 | ... AF9: =IF((COLUMN()-2)<=(Inputs!$C$33-1),-0.3*Inputs!$C$27/(Inputs!$C$33-1),0)+IF(AND((COLUMN()-2)>=Inputs!$C$33,(COLUMN()-2)<=Inputs!$C$34),-0.7*Inputs!$C$27/(Inputs!$C$34-Inputs!$C$33+1),0) -> 0 | AG9: {=SUMPRODUCT((YEAR($C$4:$AF$4)=AG$4)*$C9:$AF9)} -> -66470.1 | AH9: {=SUMPRODUCT((YEAR($C$4:$AF$4)=AH$4)*$C9:$AF9)} -> -88626.8 | AI9: {=SUMPRODUCT((YEAR($C$4:$AF$4)=AI$4)*$C9:$AF9)} -> -66470.1 | AJ9: {=SUMPRODUCT((YEAR($C$4:$AF$4)=AJ$4)*$C9:$AF9)} -> 0 | AK9: =SUM($C9:$AF9) -> -221567
B10: Development management fee | C10: =IF(AND((COLUMN()-2)>=Inputs!$C$33,(COLUMN()-2)<=Inputs!$C$34),-Inputs!$C$50/(Inputs!$C$34-Inputs!$C$33+1),0) -> 0 | D10: =IF(AND((COLUMN()-2)>=Inputs!$C$33,(COLUMN()-2)<=Inputs!$C$34),-Inputs!$C$50/(Inputs!$C$34-Inputs!$C$33+1),0) -> 0 | E10: =IF(AND((COLUMN()-2)>=Inputs!$C$33,(COLUMN()-2)<=Inputs!$C$34),-Inputs!$C$50/(Inputs!$C$34-Inputs!$C$33+1),0) -> 0 | F10: =IF(AND((COLUMN()-2)>=Inputs!$C$33,(COLUMN()-2)<=Inputs!$C$34),-Inputs!$C$50/(Inputs!$C$34-Inputs!$C$33+1),0) -> 0 | G10: =IF(AND((COLUMN()-2)>=Inputs!$C$33,(COLUMN()-2)<=Inputs!$C$34),-Inputs!$C$50/(Inputs!$C$34-Inputs!$C$33+1),0) -> 0 | H10: =IF(AND((COLUMN()-2)>=Inputs!$C$33,(COLUMN()-2)<=Inputs!$C$34),-Inputs!$C$50/(Inputs!$C$34-Inputs!$C$33+1),0) -> 0 | I10: =IF(AND((COLUMN()-2)>=Inputs!$C$33,(COLUMN()-2)<=Inputs!$C$34),-Inputs!$C$50/(Inputs!$C$34-Inputs!$C$33+1),0) -> -3666.6667 | J10: =IF(AND((COLUMN()-2)>=Inputs!$C$33,(COLUMN()-2)<=Inputs!$C$34),-Inputs!$C$50/(Inputs!$C$34-Inputs!$C$33+1),0) -> -3666.6667 | ... AF10: =IF(AND((COLUMN()-2)>=Inputs!$C$33,(COLUMN()-2)<=Inputs!$C$34),-Inputs!$C$50/(Inputs!$C$34-Inputs!$C$33+1),0) -> 0 | AG10: {=SUMPRODUCT((YEAR($C$4:$AF$4)=AG$4)*$C10:$AF10)} -> 0 | AH10: {=SUMPRODUCT((YEAR($C$4:$AF$4)=AH$4)*$C10:$AF10)} -> -44000 | AI10: {=SUMPRODUCT((YEAR($C$4:$AF$4)=AI$4)*$C10:$AF10)} -> -33000 | AJ10: {=SUMPRODUCT((YEAR($C$4:$AF$4)=AJ$4)*$C10:$AF10)} -> 0 | AK10: =SUM($C10:$AF10) -> -77000
B11: Design and pre-construction subtotal | C11: =SUM(C9:C10) -> -11078.35 | D11: =SUM(D9:D10) -> -11078.35 | E11: =SUM(E9:E10) -> -11078.35 | F11: =SUM(F9:F10) -> -11078.35 | G11: =SUM(G9:G10) -> -11078.35 | H11: =SUM(H9:H10) -> -11078.35 | I11: =SUM(I9:I10) -> -11052.233 | J11: =SUM(J9:J10) -> -11052.233 | ... AF11: =SUM(AF9:AF10) -> 0 | AG11: {=SUMPRODUCT((YEAR($C$4:$AF$4)=AG$4)*$C11:$AF11)} -> -66470.1 | AH11: {=SUMPRODUCT((YEAR($C$4:$AF$4)=AH$4)*$C11:$AF11)} -> -132626.8 | AI11: {=SUMPRODUCT((YEAR($C$4:$AF$4)=AI$4)*$C11:$AF11)} -> -99470.1 | AJ11: {=SUMPRODUCT((YEAR($C$4:$AF$4)=AJ$4)*$C11:$AF11)} -> 0 | AK11: =SUM($C11:$AF11) -> -298567
A12: Construction | B12: Construction cost | C12: =IF(AND((COLUMN()-2)>=Inputs!$C$33,(COLUMN()-2)<=Inputs!$C$34),-Inputs!$C$97*IF(Inputs!$C$92="S-curve",(3*(((COLUMN()-2)-Inputs!$C$33+1)/(Inputs!$C$34-Inputs!$C$33+1))^2-2*(((COLUMN()-2)-Inputs!$C$33+1)/(Inputs!$C$34-Inputs!$C$33+1))^3)-(3*(((COLUMN()-2)-Inputs!$C$33)/(Inputs!$C$34-Inputs!$C$33+1))^2-2*(((COLUMN()-2)-Inputs!$C$33)/(Inputs!$C$34-Inputs!$C$33+1))^3),1/(Inputs!$C$34-Inputs!$C$33+1)),0) -> 0 | D12: =IF(AND((COLUMN()-2)>=Inputs!$C$33,(COLUMN()-2)<=Inputs!$C$34),-Inputs!$C$97*IF(Inputs!$C$92="S-curve",(3*(((COLUMN()-2)-Inputs!$C$33+1)/(Inputs!$C$34-Inputs!$C$33+1))^2-2*(((COLUMN()-2)-Inputs!$C$33+1)/(Inputs!$C$34-Inputs!$C$33+1))^3)-(3*(((COLUMN()-2)-Inputs!$C$33)/(Inputs!$C$34-Inputs!$C$33+1))^2-2*(((COLUMN()-2)-Inputs!$C$33)/(Inputs!$C$34-Inputs!$C$33+1))^3),1/(Inputs!$C$34-Inputs!$C$33+1)),0) -> 0 | E12: =IF(AND((COLUMN()-2)>=Inputs!$C$33,(COLUMN()-2)<=Inputs!$C$34),-Inputs!$C$97*IF(Inputs!$C$92="S-curve",(3*(((COLUMN()-2)-Inputs!$C$33+1)/(Inputs!$C$34-Inputs!$C$33+1))^2-2*(((COLUMN()-2)-Inputs!$C$33+1)/(Inputs!$C$34-Inputs!$C$33+1))^3)-(3*(((COLUMN()-2)-Inputs!$C$33)/(Inputs!$C$34-Inputs!$C$33+1))^2-2*(((COLUMN()-2)-Inputs!$C$33)/(Inputs!$C$34-Inputs!$C$33+1))^3),1/(Inputs!$C$34-Inputs!$C$33+1)),0) -> 0 | F12: =IF(AND((COLUMN()-2)>=Inputs!$C$33,(COLUMN()-2)<=Inputs!$C$34),-Inputs!$C$97*IF(Inputs!$C$92="S-curve",(3*(((COLUMN()-2)-Inputs!$C$33+1)/(Inputs!$C$34-Inputs!$C$33+1))^2-2*(((COLUMN()-2)-Inputs!$C$33+1)/(Inputs!$C$34-Inputs!$C$33+1))^3)-(3*(((COLUMN()-2)-Inputs!$C$33)/(Inputs!$C$34-Inputs!$C$33+1))^2-2*(((COLUMN()-2)-Inputs!$C$33)/(Inputs!$C$34-Inputs!$C$33+1))^3),1/(Inputs!$C$34-Inputs!$C$33+1)),0) -> 0 | G12: =IF(AND((COLUMN()-2)>=Inputs!$C$33,(COLUMN()-2)<=Inputs!$C$34),-Inputs!$C$97*IF(Inputs!$C$92="S-curve",(3*(((COLUMN()-2)-Inputs!$C$33+1)/(Inputs!$C$34-Inputs!$C$33+1))^2-2*(((COLUMN()-2)-Inputs!$C$33+1)/(Inputs!$C$34-Inputs!$C$33+1))^3)-(3*(((COLUMN()-2)-Inputs!$C$33)/(Inputs!$C$34-Inputs!$C$33+1))^2-2*(((COLUMN()-2)-Inputs!$C$33)/(Inputs!$C$34-Inputs!$C$33+1))^3),1/(Inputs!$C$34-Inputs!$C$33+1)),0) -> 0 | H12: =IF(AND((COLUMN()-2)>=Inputs!$C$33,(COLUMN()-2)<=Inputs!$C$34),-Inputs!$C$97*IF(Inputs!$C$92="S-curve",(3*(((COLUMN()-2)-Inputs!$C$33+1)/(Inputs!$C$34-Inputs!$C$33+1))^2-2*(((COLUMN()-2)-Inputs!$C$33+1)/(Inputs!$C$34-Inputs!$C$33+1))^3)-(3*(((COLUMN()-2)-Inputs!$C$33)/(Inputs!$C$34-Inputs!$C$33+1))^2-2*(((COLUMN()-2)-Inputs!$C$33)/(Inputs!$C$34-Inputs!$C$33+1))^3),1/(Inputs!$C$34-Inputs!$C$33+1)),0) -> 0 | I12: =IF(AND((COLUMN()-2)>=Inputs!$C$33,(COLUMN()-2)<=Inputs!$C$34),-Inputs!$C$97*IF(Inputs!$C$92="S-curve",(3*(((COLUMN()-2)-Inputs!$C$33+1)/(Inputs!$C$34-Inputs!$C$33+1))^2-2*(((COLUMN()-2)-Inputs!$C$33+1)/(Inputs!$C$34-Inputs!$C$33+1))^3)-(3*(((COLUMN()-2)-Inputs!$C$33)/(Inputs!$C$34-Inputs!$C$33+1))^2-2*(((COLUMN()-2)-Inputs!$C$33)/(Inputs!$C$34-Inputs!$C$33+1))^3),1/(Inputs!$C$34-Inputs!$C$33+1)),0) -> -95916.619 | J12: =IF(AND((COLUMN()-2)>=Inputs!$C$33,(COLUMN()-2)<=Inputs!$C$34),-Inputs!$C$97*IF(Inputs!$C$92="S-curve",(3*(((COLUMN()-2)-Inputs!$C$33+1)/(Inputs!$C$34-Inputs!$C$33+1))^2-2*(((COLUMN()-2)-Inputs!$C$33+1)/(Inputs!$C$34-Inputs!$C$33+1))^3)-(3*(((COLUMN()-2)-Inputs!$C$33)/(Inputs!$C$34-Inputs!$C$33+1))^2-2*(((COLUMN()-2)-Inputs!$C$33)/(Inputs!$C$34-Inputs!$C$33+1))^3),1/(Inputs!$C$34-Inputs!$C$33+1)),0) -> -95916.619 | ... AF12: =IF(AND((COLUMN()-2)>=Inputs!$C$33,(COLUMN()-2)<=Inputs!$C$34),-Inputs!$C$97*IF(Inputs!$C$92="S-curve",(3*(((COLUMN()-2)-Inputs!$C$33+1)/(Inputs!$C$34-Inputs!$C$33+1))^2-2*(((COLUMN()-2)-Inputs!$C$33+1)/(Inputs!$C$34-Inputs!$C$33+1))^3)-(3*(((COLUMN()-2)-Inputs!$C$33)/(Inputs!$C$34-Inputs!$C$33+1))^2-2*(((COLUMN()-2)-Inputs!$C$33)/(Inputs!$C$34-Inputs!$C$33+1))^3),1/(Inputs!$C$34-Inputs!$C$33+1)),0) -> 0 | AG12: {=SUMPRODUCT((YEAR($C$4:$AF$4)=AG$4)*$C12:$AF12)} -> 0 | AH12: {=SUMPRODUCT((YEAR($C$4:$AF$4)=AH$4)*$C12:$AF12)} -> -1150999.4 | AI12: {=SUMPRODUCT((YEAR($C$4:$AF$4)=AI$4)*$C12:$AF12)} -> -863249.57 | AJ12: {=SUMPRODUCT((YEAR($C$4:$AF$4)=AJ$4)*$C12:$AF12)} -> 0 | AK12: =SUM($C12:$AF12) -> -2014249
B13: Statutory (S106 and CIL) | C13: =IF(AND((COLUMN()-2)>=Inputs!$C$33,(COLUMN()-2)<=Inputs!$C$34),-Inputs!$C$28/(Inputs!$C$34-Inputs!$C$33+1),0) -> 0 | D13: =IF(AND((COLUMN()-2)>=Inputs!$C$33,(COLUMN()-2)<=Inputs!$C$34),-Inputs!$C$28/(Inputs!$C$34-Inputs!$C$33+1),0) -> 0 | E13: =IF(AND((COLUMN()-2)>=Inputs!$C$33,(COLUMN()-2)<=Inputs!$C$34),-Inputs!$C$28/(Inputs!$C$34-Inputs!$C$33+1),0) -> 0 | F13: =IF(AND((COLUMN()-2)>=Inputs!$C$33,(COLUMN()-2)<=Inputs!$C$34),-Inputs!$C$28/(Inputs!$C$34-Inputs!$C$33+1),0) -> 0 | G13: =IF(AND((COLUMN()-2)>=Inputs!$C$33,(COLUMN()-2)<=Inputs!$C$34),-Inputs!$C$28/(Inputs!$C$34-Inputs!$C$33+1),0) -> 0 | H13: =IF(AND((COLUMN()-2)>=Inputs!$C$33,(COLUMN()-2)<=Inputs!$C$34),-Inputs!$C$28/(Inputs!$C$34-Inputs!$C$33+1),0) -> 0 | I13: =IF(AND((COLUMN()-2)>=Inputs!$C$33,(COLUMN()-2)<=Inputs!$C$34),-Inputs!$C$28/(Inputs!$C$34-Inputs!$C$33+1),0) -> -2285.7143 | J13: =IF(AND((COLUMN()-2)>=Inputs!$C$33,(COLUMN()-2)<=Inputs!$C$34),-Inputs!$C$28/(Inputs!$C$34-Inputs!$C$33+1),0) -> -2285.7143 | ... AF13: =IF(AND((COLUMN()-2)>=Inputs!$C$33,(COLUMN()-2)<=Inputs!$C$34),-Inputs!$C$28/(Inputs!$C$34-Inputs!$C$33+1),0) -> 0 | AG13: {=SUMPRODUCT((YEAR($C$4:$AF$4)=AG$4)*$C13:$AF13)} -> 0 | AH13: {=SUMPRODUCT((YEAR($C$4:$AF$4)=AH$4)*$C13:$AF13)} -> -27428.571 | AI13: {=SUMPRODUCT((YEAR($C$4:$AF$4)=AI$4)*$C13:$AF13)} -> -20571.429 | AJ13: {=SUMPRODUCT((YEAR($C$4:$AF$4)=AJ$4)*$C13:$AF13)} -> 0 | AK13: =SUM($C13:$AF13) -> -48000
B14: Construction subtotal | C14: =SUM(C12:C13) -> 0 | D14: =SUM(D12:D13) -> 0 | E14: =SUM(E12:E13) -> 0 | F14: =SUM(F12:F13) -> 0 | G14: =SUM(G12:G13) -> 0 | H14: =SUM(H12:H13) -> 0 | I14: =SUM(I12:I13) -> -98202.333 | J14: =SUM(J12:J13) -> -98202.333 | ... AF14: =SUM(AF12:AF13) -> 0 | AG14: {=SUMPRODUCT((YEAR($C$4:$AF$4)=AG$4)*$C14:$AF14)} -> 0 | AH14: {=SUMPRODUCT((YEAR($C$4:$AF$4)=AH$4)*$C14:$AF14)} -> -1178428 | AI14: {=SUMPRODUCT((YEAR($C$4:$AF$4)=AI$4)*$C14:$AF14)} -> -883821 | AJ14: {=SUMPRODUCT((YEAR($C$4:$AF$4)=AJ$4)*$C14:$AF14)} -> 0 | AK14: =SUM($C14:$AF14) -> -2062249
A15: Finance | B15: Senior interest (rolled up) | C15: =-Engine!C$11 -> 0 | D15: =-Engine!D$11 -> -92.931375 | E15: =-Engine!E$11 -> -186.55974 | F15: =-Engine!F$11 -> -280.89031 | G15: =-Engine!G$11 -> -375.92836 | H15: =-Engine!H$11 -> -471.6792 | I15: =-Engine!I$11 -> -568.14817 | J15: =-Engine!J$11 -> -1391.8185 | ... AF15: =-Engine!AF$11 -> -13823.726 | AG15: {=SUMPRODUCT((YEAR($C$4:$AF$4)=AG$4)*$C15:$AF15)} -> -1407.989 | AH15: {=SUMPRODUCT((YEAR($C$4:$AF$4)=AH$4)*$C15:$AF15)} -> -62562.29 | AI15: {=SUMPRODUCT((YEAR($C$4:$AF$4)=AI$4)*$C15:$AF15)} -> -156092.94 | AJ15: {=SUMPRODUCT((YEAR($C$4:$AF$4)=AJ$4)*$C15:$AF15)} -> 0 | AK15: =SUM($C15:$AF15) -> -220063.22
B16: Mezzanine interest | C16: =IF((COLUMN()-2)=Inputs!$C$35,-Engine!$B$28,0) -> 0 | D16: =IF((COLUMN()-2)=Inputs!$C$35,-Engine!$B$28,0) -> 0 | E16: =IF((COLUMN()-2)=Inputs!$C$35,-Engine!$B$28,0) -> 0 | F16: =IF((COLUMN()-2)=Inputs!$C$35,-Engine!$B$28,0) -> 0 | G16: =IF((COLUMN()-2)=Inputs!$C$35,-Engine!$B$28,0) -> 0 | H16: =IF((COLUMN()-2)=Inputs!$C$35,-Engine!$B$28,0) -> 0 | I16: =IF((COLUMN()-2)=Inputs!$C$35,-Engine!$B$28,0) -> 0 | J16: =IF((COLUMN()-2)=Inputs!$C$35,-Engine!$B$28,0) -> 0 | ... AF16: =IF((COLUMN()-2)=Inputs!$C$35,-Engine!$B$28,0) -> 0 | AG16: {=SUMPRODUCT((YEAR($C$4:$AF$4)=AG$4)*$C16:$AF16)} -> 0 | AH16: {=SUMPRODUCT((YEAR($C$4:$AF$4)=AH$4)*$C16:$AF16)} -> 0 | AI16: {=SUMPRODUCT((YEAR($C$4:$AF$4)=AI$4)*$C16:$AF16)} -> 0 | AJ16: {=SUMPRODUCT((YEAR($C$4:$AF$4)=AJ$4)*$C16:$AF16)} -> 0 | AK16: =SUM($C16:$AF16) -> 0
B17: Arrangement fee | C17: =IF((COLUMN()-2)=1,-Engine!$B$18,0) -> -26043.219 | D17: =IF((COLUMN()-2)=1,-Engine!$B$18,0) -> 0 | E17: =IF((COLUMN()-2)=1,-Engine!$B$18,0) -> 0 | F17: =IF((COLUMN()-2)=1,-Engine!$B$18,0) -> 0 | G17: =IF((COLUMN()-2)=1,-Engine!$B$18,0) -> 0 | H17: =IF((COLUMN()-2)=1,-Engine!$B$18,0) -> 0 | I17: =IF((COLUMN()-2)=1,-Engine!$B$18,0) -> 0 | J17: =IF((COLUMN()-2)=1,-Engine!$B$18,0) -> 0 | ... AF17: =IF((COLUMN()-2)=1,-Engine!$B$18,0) -> 0 | AG17: {=SUMPRODUCT((YEAR($C$4:$AF$4)=AG$4)*$C17:$AF17)} -> -26043.219 | AH17: {=SUMPRODUCT((YEAR($C$4:$AF$4)=AH$4)*$C17:$AF17)} -> 0 | AI17: {=SUMPRODUCT((YEAR($C$4:$AF$4)=AI$4)*$C17:$AF17)} -> 0 | AJ17: {=SUMPRODUCT((YEAR($C$4:$AF$4)=AJ$4)*$C17:$AF17)} -> 0 | AK17: =SUM($C17:$AF17) -> -26043.219
B18: Exit fee | C18: =IF((COLUMN()-2)=Inputs!$C$35,-Engine!$B$19,0) -> 0 | D18: =IF((COLUMN()-2)=Inputs!$C$35,-Engine!$B$19,0) -> 0 | E18: =IF((COLUMN()-2)=Inputs!$C$35,-Engine!$B$19,0) -> 0 | F18: =IF((COLUMN()-2)=Inputs!$C$35,-Engine!$B$19,0) -> 0 | G18: =IF((COLUMN()-2)=Inputs!$C$35,-Engine!$B$19,0) -> 0 | H18: =IF((COLUMN()-2)=Inputs!$C$35,-Engine!$B$19,0) -> 0 | I18: =IF((COLUMN()-2)=Inputs!$C$35,-Engine!$B$19,0) -> 0 | J18: =IF((COLUMN()-2)=Inputs!$C$35,-Engine!$B$19,0) -> 0 | ... AF18: =IF((COLUMN()-2)=Inputs!$C$35,-Engine!$B$19,0) -> -18569.871 | AG18: {=SUMPRODUCT((YEAR($C$4:$AF$4)=AG$4)*$C18:$AF18)} -> 0 | AH18: {=SUMPRODUCT((YEAR($C$4:$AF$4)=AH$4)*$C18:$AF18)} -> 0 | AI18: {=SUMPRODUCT((YEAR($C$4:$AF$4)=AI$4)*$C18:$AF18)} -> -18569.871 | AJ18: {=SUMPRODUCT((YEAR($C$4:$AF$4)=AJ$4)*$C18:$AF18)} -> 0 | AK18: =SUM($C18:$AF18) -> -18569.871
B19: Finance and holding subtotal | C19: =SUM(C15:C18)-IF(AND((COLUMN()-2)>Inputs!$C$34,(COLUMN()-2)<=Inputs!$C$35),Inputs!$C$86,0) -> -26043.219 | D19: =SUM(D15:D18)-IF(AND((COLUMN()-2)>Inputs!$C$34,(COLUMN()-2)<=Inputs!$C$35),Inputs!$C$86,0) -> -92.931375 | E19: =SUM(E15:E18)-IF(AND((COLUMN()-2)>Inputs!$C$34,(COLUMN()-2)<=Inputs!$C$35),Inputs!$C$86,0) -> -186.55974 | F19: =SUM(F15:F18)-IF(AND((COLUMN()-2)>Inputs!$C$34,(COLUMN()-2)<=Inputs!$C$35),Inputs!$C$86,0) -> -280.89031 | G19: =SUM(G15:G18)-IF(AND((COLUMN()-2)>Inputs!$C$34,(COLUMN()-2)<=Inputs!$C$35),Inputs!$C$86,0) -> -375.92836 | H19: =SUM(H15:H18)-IF(AND((COLUMN()-2)>Inputs!$C$34,(COLUMN()-2)<=Inputs!$C$35),Inputs!$C$86,0) -> -471.6792 | I19: =SUM(I15:I18)-IF(AND((COLUMN()-2)>Inputs!$C$34,(COLUMN()-2)<=Inputs!$C$35),Inputs!$C$86,0) -> -568.14817 | J19: =SUM(J15:J18)-IF(AND((COLUMN()-2)>Inputs!$C$34,(COLUMN()-2)<=Inputs!$C$35),Inputs!$C$86,0) -> -1391.8185 | ... AF19: =SUM(AF15:AF18)-IF(AND((COLUMN()-2)>Inputs!$C$34,(COLUMN()-2)<=Inputs!$C$35),Inputs!$C$86,0) -> -32393.597 | AG19: {=SUMPRODUCT((YEAR($C$4:$AF$4)=AG$4)*$C19:$AF19)} -> -27451.208 | AH19: {=SUMPRODUCT((YEAR($C$4:$AF$4)=AH$4)*$C19:$AF19)} -> -62562.29 | AI19: {=SUMPRODUCT((YEAR($C$4:$AF$4)=AI$4)*$C19:$AF19)} -> -174662.81 | AJ19: {=SUMPRODUCT((YEAR($C$4:$AF$4)=AJ$4)*$C19:$AF19)} -> 0 | AK19: =SUM($C19:$AF19) -> -264676.31
A20: Sales and disposal | B20: Gross development value | C20: =IF((COLUMN()-2)=Inputs!$C$35,Inputs!$C$25/(1-Inputs!$C$24)-Engine!$B$30/(1-Inputs!$C$24),0)+Engine!C6/(1-Inputs!$C$24) -> 0 | D20: =IF((COLUMN()-2)=Inputs!$C$35,Inputs!$C$25/(1-Inputs!$C$24)-Engine!$B$30/(1-Inputs!$C$24),0)+Engine!D6/(1-Inputs!$C$24) -> 0 | E20: =IF((COLUMN()-2)=Inputs!$C$35,Inputs!$C$25/(1-Inputs!$C$24)-Engine!$B$30/(1-Inputs!$C$24),0)+Engine!E6/(1-Inputs!$C$24) -> 0 | F20: =IF((COLUMN()-2)=Inputs!$C$35,Inputs!$C$25/(1-Inputs!$C$24)-Engine!$B$30/(1-Inputs!$C$24),0)+Engine!F6/(1-Inputs!$C$24) -> 0 | G20: =IF((COLUMN()-2)=Inputs!$C$35,Inputs!$C$25/(1-Inputs!$C$24)-Engine!$B$30/(1-Inputs!$C$24),0)+Engine!G6/(1-Inputs!$C$24) -> 0 | H20: =IF((COLUMN()-2)=Inputs!$C$35,Inputs!$C$25/(1-Inputs!$C$24)-Engine!$B$30/(1-Inputs!$C$24),0)+Engine!H6/(1-Inputs!$C$24) -> 0 | I20: =IF((COLUMN()-2)=Inputs!$C$35,Inputs!$C$25/(1-Inputs!$C$24)-Engine!$B$30/(1-Inputs!$C$24),0)+Engine!I6/(1-Inputs!$C$24) -> 0 | J20: =IF((COLUMN()-2)=Inputs!$C$35,Inputs!$C$25/(1-Inputs!$C$24)-Engine!$B$30/(1-Inputs!$C$24),0)+Engine!J6/(1-Inputs!$C$24) -> 0 | ... AF20: =IF((COLUMN()-2)=Inputs!$C$35,Inputs!$C$25/(1-Inputs!$C$24)-Engine!$B$30/(1-Inputs!$C$24),0)+Engine!AF6/(1-Inputs!$C$24) -> 3850000 | AG20: {=SUMPRODUCT((YEAR($C$4:$AF$4)=AG$4)*$C20:$AF20)} -> 0 | AH20: {=SUMPRODUCT((YEAR($C$4:$AF$4)=AH$4)*$C20:$AF20)} -> 0 | AI20: {=SUMPRODUCT((YEAR($C$4:$AF$4)=AI$4)*$C20:$AF20)} -> 3850000 | AJ20: {=SUMPRODUCT((YEAR($C$4:$AF$4)=AJ$4)*$C20:$AF20)} -> 0 | AK20: =SUM($C20:$AF20) -> 3850000
B21: Sales costs | C21: =-C20*Inputs!$C$24 -> 0 | D21: =-D20*Inputs!$C$24 -> 0 | E21: =-E20*Inputs!$C$24 -> 0 | F21: =-F20*Inputs!$C$24 -> 0 | G21: =-G20*Inputs!$C$24 -> 0 | H21: =-H20*Inputs!$C$24 -> 0 | I21: =-I20*Inputs!$C$24 -> 0 | J21: =-J20*Inputs!$C$24 -> 0 | ... AF21: =-AF20*Inputs!$C$24 -> -77000 | AG21: {=SUMPRODUCT((YEAR($C$4:$AF$4)=AG$4)*$C21:$AF21)} -> 0 | AH21: {=SUMPRODUCT((YEAR($C$4:$AF$4)=AH$4)*$C21:$AF21)} -> 0 | AI21: {=SUMPRODUCT((YEAR($C$4:$AF$4)=AI$4)*$C21:$AF21)} -> -77000 | AJ21: {=SUMPRODUCT((YEAR($C$4:$AF$4)=AJ$4)*$C21:$AF21)} -> 0 | AK21: =SUM($C21:$AF21) -> -77000
B22: Sales and disposal subtotal | C22: =SUM(C20:C21) -> 0 | D22: =SUM(D20:D21) -> 0 | E22: =SUM(E20:E21) -> 0 | F22: =SUM(F20:F21) -> 0 | G22: =SUM(G20:G21) -> 0 | H22: =SUM(H20:H21) -> 0 | I22: =SUM(I20:I21) -> 0 | J22: =SUM(J20:J21) -> 0 | ... AF22: =SUM(AF20:AF21) -> 3773000 | AG22: {=SUMPRODUCT((YEAR($C$4:$AF$4)=AG$4)*$C22:$AF22)} -> 0 | AH22: {=SUMPRODUCT((YEAR($C$4:$AF$4)=AH$4)*$C22:$AF22)} -> 0 | AI22: {=SUMPRODUCT((YEAR($C$4:$AF$4)=AI$4)*$C22:$AF22)} -> 3773000 | AJ22: {=SUMPRODUCT((YEAR($C$4:$AF$4)=AJ$4)*$C22:$AF22)} -> 0 | AK22: =SUM($C22:$AF22) -> 3773000
AG23: {=SUMPRODUCT((YEAR($C$4:$AF$4)=AG$4)*$C23:$AF23)} -> 0 | AH23: {=SUMPRODUCT((YEAR($C$4:$AF$4)=AH$4)*$C23:$AF23)} -> 0 | AI23: {=SUMPRODUCT((YEAR($C$4:$AF$4)=AI$4)*$C23:$AF23)} -> 0 | AJ23: {=SUMPRODUCT((YEAR($C$4:$AF$4)=AJ$4)*$C23:$AF23)} -> 0 | AK23: =SUM($C23:$AF23) -> 0
B24: Net movement | C24: =C8+C11+C14+C19+C22 -> -563434.07 | D24: =D8+D11+D14+D19+D22 -> -12483.781 | E24: =E8+E11+E14+E19+E22 -> -12577.41 | F24: =F8+F11+F14+F19+F22 -> -12671.74 | G24: =G8+G11+G14+G19+G22 -> -12766.778 | H24: =H8+H11+H14+H19+H22 -> -12862.529 | I24: =I8+I11+I14+I19+I22 -> -109822.71 | J24: =J8+J11+J14+J19+J22 -> -110646.39 | ... AF24: =AF8+AF11+AF14+AF19+AF22 -> 3740606.4 | AG24: {=SUMPRODUCT((YEAR($C$4:$AF$4)=AG$4)*$C24:$AF24)} -> -626796.31 | AH24: {=SUMPRODUCT((YEAR($C$4:$AF$4)=AH$4)*$C24:$AF24)} -> -1373617.1 | AI24: {=SUMPRODUCT((YEAR($C$4:$AF$4)=AI$4)*$C24:$AF24)} -> 2615046.1 | AJ24: {=SUMPRODUCT((YEAR($C$4:$AF$4)=AJ$4)*$C24:$AF24)} -> 0 | AK24: =SUM($C24:$AF24) -> 614632.69
B25: Cumulative cash position | C25: =C24 -> -563434.07 | D25: =C25+D24 -> -575917.85 | E25: =D25+E24 -> -588495.26 | F25: =E25+F24 -> -601167 | G25: =F25+G24 -> -613933.78 | H25: =G25+H24 -> -626796.31 | I25: =H25+I24 -> -736619.02 | J25: =I25+J24 -> -847265.41 | K25: =J25+K24 -> -958741.64 | ... AF25: =AE25+AF24 -> 614632.69 | AG25: {=SUMPRODUCT((YEAR($C$4:$AF$4)<=AG$4)*$C$24:$AF$24)} -> -626796.31 | AK25: =AF25 -> 614632.69
B27: Peak funding requirement | C27: =MIN(C25:AF25) -> -3125973.7

Sheet Waterfall
A1: ENGINE | Distribution waterfall (JV with land-for-equity)
A2: ="Net proceeds repay senior debt, then return capital, then pay the preferred return, then split residual with the sponsor promote. The pref accrues on contributed capital, so the whole waterfall is deterministic. All amounts in "&Inputs!$C$80&" ("&Inputs!$C$79&")." -> Net proceeds repay senior debt, then return capital, then pay the preferred return, then split residual with the sponsor promote. The pref accrues on contributed capital, so the whole waterfall is deterministic. All amounts in NGN (₦).
A4: Capital contributed
A5: Party | C5: Sponsor | D5: Funding partner | E5: Landowner | F5: Total
A6: Capital contributed | C6: =Engine!$B$24+Inputs!$C$30*IF(Inputs!$C$9="Yes",1,0) -> 219530.12 | D6: =Engine!$B$25 -> 512236.95 | E6: =Inputs!$C$30*Inputs!$C$16*IF(Inputs!$C$9="Yes",0,1) -> 525000 | F6: =SUM(C6:E6) -> 1256767.1
A7: Contribution type | C7: cash | D7: cash | E7: land at valuation
A9: Proceeds and senior repayment
A10: Net development value (NDV) | F10: =Inputs!$C$25 -> 3773000
A11: Less senior, mezzanine and pre-sale debt reduction | F11: =-(Engine!$B$20+Engine!$B$29+Engine!$B$30+Engine!$B$31) -> -1901600.2
A12: Proceeds available to equity | F12: =F10+F11 -> 1871399.8
A14: Tier 1, return of capital (pro-rata)
A15: Return of capital pool | F15: =MIN(Waterfall!$F$12,Waterfall!$F$6) -> 1256767.1
A16: Return of capital | C16: =IF($F$6=0,0,$F$15*C6/$F$6) -> 219530.12 | D16: =IF($F$6=0,0,$F$15*D6/$F$6) -> 512236.95 | E16: =IF($F$6=0,0,$F$15*E6/$F$6) -> 525000 | F16: =SUM(C16:E16) -> 1256767.1
A17: Proceeds after return of capital | F17: =Waterfall!$F$12-Waterfall!$F$15 -> 614632.69
A19: ="Tier 2, return hurdle ("&Inputs!$C$59&")" -> Tier 2, return hurdle (Preferred return)
A20: Pref accrual period | C20: =(Inputs!$C$35-(Inputs!$C$33+Inputs!$C$34)/2)/12 -> 1.0833333 | D20: =(Inputs!$C$35-(Inputs!$C$33+Inputs!$C$34)/2)/12 -> 1.0833333 | E20: =Inputs!$C$35/12 -> 2.5 | F20: cash mid-build; land from outset
A21: Preferred return accrued | C21: =Inputs!$C$20*C6*IF(Inputs!$C$59="Equity multiple",(Inputs!$C$60-1),((1+Inputs!$C$44)^C20-1)) -> 23878.633 | D21: =Inputs!$C$20*D6*IF(Inputs!$C$59="Equity multiple",(Inputs!$C$60-1),((1+Inputs!$C$44)^D20-1)) -> 55716.809 | E21: =Inputs!$C$20*E6*IF(Inputs!$C$59="Equity multiple",(Inputs!$C$60-1),((1+Inputs!$C$44)^E20-1)) -> 141255.82 | F21: =SUM(C21:E21) -> 220851.26
A22: Preferred return paid | C22: =IF($F$21=0,0,MIN($F$17,$F$21)*C21/$F$21) -> 23878.633 | D22: =IF($F$21=0,0,MIN($F$17,$F$21)*D21/$F$21) -> 55716.809 | E22: =IF($F$21=0,0,MIN($F$17,$F$21)*E21/$F$21) -> 141255.82 | F22: =SUM(C22:E22) -> 220851.26
A23: Proceeds after pref | F23: =Waterfall!$F$17-MIN(Waterfall!$F$17,Waterfall!$F$21) -> 393781.43
A25: ="Tier 3, "&IF(Inputs!$C$70="Yes","GP catch-up and carry","residual profit and sponsor promote") -> Tier 3, residual profit and sponsor promote
A26: Residual profit | F26: =MAX(0,Waterfall!$F$23) -> 393781.43
A27: To capital, pro-rata | C27: =IF(Inputs!$C$70="Yes",IF($F$6=0,0,($F$26-$C$29)*(1-Inputs!$C$71)*C6/$F$6),IF($F$6=0,0,$F$26*Inputs!$C$46*C6/$F$6)) -> 34392.564 | D27: =IF(Inputs!$C$70="Yes",IF($F$6=0,0,($F$26-$C$29)*(1-Inputs!$C$71)*D6/$F$6),IF($F$6=0,0,$F$26*Inputs!$C$46*D6/$F$6)) -> 80249.317 | E27: =IF(Inputs!$C$70="Yes",IF($F$6=0,0,($F$26-$C$29)*(1-Inputs!$C$71)*E6/$F$6),IF($F$6=0,0,$F$26*Inputs!$C$46*E6/$F$6)) -> 82248.833 | F27: =SUM(C27:E27) -> 196890.71
A28: Promote to sponsor | C28: =$F$26-(C27+D27+E27) -> 196890.71 | F28: =C28 -> 196890.71
A29: of which GP catch-up (memo) | C29: =IF(Inputs!$C$70="Yes",MIN($F$26,(Inputs!$C$71/(1-Inputs!$C$71))*($D$22+$E$22)),0) -> 0
A30: Party outcomes
A31: Development fee (sponsor income) | C31: =Inputs!$C$50 -> 77000
A32: Total received from waterfall | C32: =C16+C22+C27+C28 -> 474692.03 | D32: =D16+D22+D27 -> 648203.08 | E32: =E16+E22+E27 -> 748504.65 | F32: =SUM(C32:E32) -> 1871399.8
A33: Total cash to party (incl fee) | C33: =C32+C31 -> 551692.03 | D33: =D32 -> 648203.08 | E33: =E32 -> 748504.65
A34: Less capital contributed | C34: =-Waterfall!$C$6 -> -219530.12 | D34: =-Waterfall!$D$6 -> -512236.95 | E34: =-Waterfall!$E$6 -> -525000
A35: Profit to party | C35: =C33-Waterfall!$C$6 -> 332161.91 | D35: =D33-Waterfall!$D$6 -> 135966.13 | E35: =E33-Waterfall!$E$6 -> 223504.65
A36: Return multiple on capital | C36: =IF($C$6=0,0,C33/$C$6) -> 2.5130585 | D36: =IF($D$6=0,0,D33/$D$6) -> 1.265436 | E36: =IF($E$6=0,0,E33/$E$6) -> 1.4257231
A38: Reconciliation
A39: NDV less (senior redemption + all waterfall takes) | F39: =Inputs!$C$25-(Engine!$B$20+Engine!$B$29+Engine!$B$30+Engine!$B$31+C32+D32+E32) -> 0
A40: Should be zero. The development fee is excluded; it is a cost already funded, not a share of proceeds.

Sheet Sensitivity
A1: ENGINE | Sensitivity
A2: ="Two questions, two grids. Both re-derive the output as a live formula, not a native data table, so they recalculate cleanly. What is held is stated on each grid. All amounts in "&Inputs!$C$80&" ("&Inputs!$C$79&")." -> Two questions, two grids. Both re-derive the output as a live formula, not a native data table, so they recalculate cleanly. What is held is stated on each grid. All amounts in NGN (₦).
A4: Grid 1: scheme viability
A5: Profit on cost as GDV (across) and build cost (down) move. Finance, fees, statutory and land held at the base run.
A6: Base GDV | B6: =Inputs!$C$23 -> 3850000
A7: Base construction | B7: =Inputs!$C$26 -> 2014249
A9: PoC: build (down) vs GDV (right) | B9: -0.1 | C9: -0.05 | D9: 0 | E9: 0.05 | F9: 0.1
A10: -0.1 | B10: =(($B$6*(1+B$9)*(1-Inputs!$C$24))-(($B$7*(1+$A10))+(Inputs!$C$27+Inputs!$C$28+Inputs!$C$29+Inputs!$C$50+Inputs!$C$30+Engine!$B$21)))/(($B$7*(1+$A10))+(Inputs!$C$27+Inputs!$C$28+Inputs!$C$29+Inputs!$C$50+Inputs!$C$30+Engine!$B$21)) -> 0.14838219 | C10: =(($B$6*(1+C$9)*(1-Inputs!$C$24))-(($B$7*(1+$A10))+(Inputs!$C$27+Inputs!$C$28+Inputs!$C$29+Inputs!$C$50+Inputs!$C$30+Engine!$B$21)))/(($B$7*(1+$A10))+(Inputs!$C$27+Inputs!$C$28+Inputs!$C$29+Inputs!$C$50+Inputs!$C$30+Engine!$B$21)) -> 0.2121812 | D10: =(($B$6*(1+D$9)*(1-Inputs!$C$24))-(($B$7*(1+$A10))+(Inputs!$C$27+Inputs!$C$28+Inputs!$C$29+Inputs!$C$50+Inputs!$C$30+Engine!$B$21)))/(($B$7*(1+$A10))+(Inputs!$C$27+Inputs!$C$28+Inputs!$C$29+Inputs!$C$50+Inputs!$C$30+Engine!$B$21)) -> 0.27598021 | E10: =(($B$6*(1+E$9)*(1-Inputs!$C$24))-(($B$7*(1+$A10))+(Inputs!$C$27+Inputs!$C$28+Inputs!$C$29+Inputs!$C$50+Inputs!$C$30+Engine!$B$21)))/(($B$7*(1+$A10))+(Inputs!$C$27+Inputs!$C$28+Inputs!$C$29+Inputs!$C$50+Inputs!$C$30+Engine!$B$21)) -> 0.33977922 | F10: =(($B$6*(1+F$9)*(1-Inputs!$C$24))-(($B$7*(1+$A10))+(Inputs!$C$27+Inputs!$C$28+Inputs!$C$29+Inputs!$C$50+Inputs!$C$30+Engine!$B$21)))/(($B$7*(1+$A10))+(Inputs!$C$27+Inputs!$C$28+Inputs!$C$29+Inputs!$C$50+Inputs!$C$30+Engine!$B$21)) -> 0.40357823
A11: -0.05 | B11: =(($B$6*(1+B$9)*(1-Inputs!$C$24))-(($B$7*(1+$A11))+(Inputs!$C$27+Inputs!$C$28+Inputs!$C$29+Inputs!$C$50+Inputs!$C$30+Engine!$B$21)))/(($B$7*(1+$A11))+(Inputs!$C$27+Inputs!$C$28+Inputs!$C$29+Inputs!$C$50+Inputs!$C$30+Engine!$B$21)) -> 0.110557 | C11: =(($B$6*(1+C$9)*(1-Inputs!$C$24))-(($B$7*(1+$A11))+(Inputs!$C$27+Inputs!$C$28+Inputs!$C$29+Inputs!$C$50+Inputs!$C$30+Engine!$B$21)))/(($B$7*(1+$A11))+(Inputs!$C$27+Inputs!$C$28+Inputs!$C$29+Inputs!$C$50+Inputs!$C$30+Engine!$B$21)) -> 0.17225461 | D11: =(($B$6*(1+D$9)*(1-Inputs!$C$24))-(($B$7*(1+$A11))+(Inputs!$C$27+Inputs!$C$28+Inputs!$C$29+Inputs!$C$50+Inputs!$C$30+Engine!$B$21)))/(($B$7*(1+$A11))+(Inputs!$C$27+Inputs!$C$28+Inputs!$C$29+Inputs!$C$50+Inputs!$C$30+Engine!$B$21)) -> 0.23395222 | E11: =(($B$6*(1+E$9)*(1-Inputs!$C$24))-(($B$7*(1+$A11))+(Inputs!$C$27+Inputs!$C$28+Inputs!$C$29+Inputs!$C$50+Inputs!$C$30+Engine!$B$21)))/(($B$7*(1+$A11))+(Inputs!$C$27+Inputs!$C$28+Inputs!$C$29+Inputs!$C$50+Inputs!$C$30+Engine!$B$21)) -> 0.29564983 | F11: =(($B$6*(1+F$9)*(1-Inputs!$C$24))-(($B$7*(1+$A11))+(Inputs!$C$27+Inputs!$C$28+Inputs!$C$29+Inputs!$C$50+Inputs!$C$30+Engine!$B$21)))/(($B$7*(1+$A11))+(Inputs!$C$27+Inputs!$C$28+Inputs!$C$29+Inputs!$C$50+Inputs!$C$30+Engine!$B$21)) -> 0.35734744
A12: 0 | B12: =(($B$6*(1+B$9)*(1-Inputs!$C$24))-(($B$7*(1+$A12))+(Inputs!$C$27+Inputs!$C$28+Inputs!$C$29+Inputs!$C$50+Inputs!$C$30+Engine!$B$21)))/(($B$7*(1+$A12))+(Inputs!$C$27+Inputs!$C$28+Inputs!$C$29+Inputs!$C$50+Inputs!$C$30+Engine!$B$21)) -> 0.075144107 | C12: =(($B$6*(1+C$9)*(1-Inputs!$C$24))-(($B$7*(1+$A12))+(Inputs!$C$27+Inputs!$C$28+Inputs!$C$29+Inputs!$C$50+Inputs!$C$30+Engine!$B$21)))/(($B$7*(1+$A12))+(Inputs!$C$27+Inputs!$C$28+Inputs!$C$29+Inputs!$C$50+Inputs!$C$30+Engine!$B$21)) -> 0.13487434 | D12: =(($B$6*(1+D$9)*(1-Inputs!$C$24))-(($B$7*(1+$A12))+(Inputs!$C$27+Inputs!$C$28+Inputs!$C$29+Inputs!$C$50+Inputs!$C$30+Engine!$B$21)))/(($B$7*(1+$A12))+(Inputs!$C$27+Inputs!$C$28+Inputs!$C$29+Inputs!$C$50+Inputs!$C$30+Engine!$B$21)) -> 0.19460456 | E12: =(($B$6*(1+E$9)*(1-Inputs!$C$24))-(($B$7*(1+$A12))+(Inputs!$C$27+Inputs!$C$28+Inputs!$C$29+Inputs!$C$50+Inputs!$C$30+Engine!$B$21)))/(($B$7*(1+$A12))+(Inputs!$C$27+Inputs!$C$28+Inputs!$C$29+Inputs!$C$50+Inputs!$C$30+Engine!$B$21)) -> 0.25433479 | F12: =(($B$6*(1+F$9)*(1-Inputs!$C$24))-(($B$7*(1+$A12))+(Inputs!$C$27+Inputs!$C$28+Inputs!$C$29+Inputs!$C$50+Inputs!$C$30+Engine!$B$21)))/(($B$7*(1+$A12))+(Inputs!$C$27+Inputs!$C$28+Inputs!$C$29+Inputs!$C$50+Inputs!$C$30+Engine!$B$21)) -> 0.31406502
A13: 0.05 | B13: =(($B$6*(1+B$9)*(1-Inputs!$C$24))-(($B$7*(1+$A13))+(Inputs!$C$27+Inputs!$C$28+Inputs!$C$29+Inputs!$C$50+Inputs!$C$30+Engine!$B$21)))/(($B$7*(1+$A13))+(Inputs!$C$27+Inputs!$C$28+Inputs!$C$29+Inputs!$C$50+Inputs!$C$30+Engine!$B$21)) -> 0.041919883 | C13: =(($B$6*(1+C$9)*(1-Inputs!$C$24))-(($B$7*(1+$A13))+(Inputs!$C$27+Inputs!$C$28+Inputs!$C$29+Inputs!$C$50+Inputs!$C$30+Engine!$B$21)))/(($B$7*(1+$A13))+(Inputs!$C$27+Inputs!$C$28+Inputs!$C$29+Inputs!$C$50+Inputs!$C$30+Engine!$B$21)) -> 0.099804321 | D13: =(($B$6*(1+D$9)*(1-Inputs!$C$24))-(($B$7*(1+$A13))+(Inputs!$C$27+Inputs!$C$28+Inputs!$C$29+Inputs!$C$50+Inputs!$C$30+Engine!$B$21)))/(($B$7*(1+$A13))+(Inputs!$C$27+Inputs!$C$28+Inputs!$C$29+Inputs!$C$50+Inputs!$C$30+Engine!$B$21)) -> 0.15768876 | E13: =(($B$6*(1+E$9)*(1-Inputs!$C$24))-(($B$7*(1+$A13))+(Inputs!$C$27+Inputs!$C$28+Inputs!$C$29+Inputs!$C$50+Inputs!$C$30+Engine!$B$21)))/(($B$7*(1+$A13))+(Inputs!$C$27+Inputs!$C$28+Inputs!$C$29+Inputs!$C$50+Inputs!$C$30+Engine!$B$21)) -> 0.2155732 | F13: =(($B$6*(1+F$9)*(1-Inputs!$C$24))-(($B$7*(1+$A13))+(Inputs!$C$27+Inputs!$C$28+Inputs!$C$29+Inputs!$C$50+Inputs!$C$30+Engine!$B$21)))/(($B$7*(1+$A13))+(Inputs!$C$27+Inputs!$C$28+Inputs!$C$29+Inputs!$C$50+Inputs!$C$30+Engine!$B$21)) -> 0.27345763
A14: 0.1 | B14: =(($B$6*(1+B$9)*(1-Inputs!$C$24))-(($B$7*(1+$A14))+(Inputs!$C$27+Inputs!$C$28+Inputs!$C$29+Inputs!$C$50+Inputs!$C$30+Engine!$B$21)))/(($B$7*(1+$A14))+(Inputs!$C$27+Inputs!$C$28+Inputs!$C$29+Inputs!$C$50+Inputs!$C$30+Engine!$B$21)) -> 0.010687504 | C14: =(($B$6*(1+C$9)*(1-Inputs!$C$24))-(($B$7*(1+$A14))+(Inputs!$C$27+Inputs!$C$28+Inputs!$C$29+Inputs!$C$50+Inputs!$C$30+Engine!$B$21)))/(($B$7*(1+$A14))+(Inputs!$C$27+Inputs!$C$28+Inputs!$C$29+Inputs!$C$50+Inputs!$C$30+Engine!$B$21)) -> 0.066836809 | D14: =(($B$6*(1+D$9)*(1-Inputs!$C$24))-(($B$7*(1+$A14))+(Inputs!$C$27+Inputs!$C$28+Inputs!$C$29+Inputs!$C$50+Inputs!$C$30+Engine!$B$21)))/(($B$7*(1+$A14))+(Inputs!$C$27+Inputs!$C$28+Inputs!$C$29+Inputs!$C$50+Inputs!$C$30+Engine!$B$21)) -> 0.12298612 | E14: =(($B$6*(1+E$9)*(1-Inputs!$C$24))-(($B$7*(1+$A14))+(Inputs!$C$27+Inputs!$C$28+Inputs!$C$29+Inputs!$C$50+Inputs!$C$30+Engine!$B$21)))/(($B$7*(1+$A14))+(Inputs!$C$27+Inputs!$C$28+Inputs!$C$29+Inputs!$C$50+Inputs!$C$30+Engine!$B$21)) -> 0.17913542 | F14: =(($B$6*(1+F$9)*(1-Inputs!$C$24))-(($B$7*(1+$A14))+(Inputs!$C$27+Inputs!$C$28+Inputs!$C$29+Inputs!$C$50+Inputs!$C$30+Engine!$B$21)))/(($B$7*(1+$A14))+(Inputs!$C$27+Inputs!$C$28+Inputs!$C$29+Inputs!$C$50+Inputs!$C$30+Engine!$B$21)) -> 0.23528473
A15: 0.15 | B15: =(($B$6*(1+B$9)*(1-Inputs!$C$24))-(($B$7*(1+$A15))+(Inputs!$C$27+Inputs!$C$28+Inputs!$C$29+Inputs!$C$50+Inputs!$C$30+Engine!$B$21)))/(($B$7*(1+$A15))+(Inputs!$C$27+Inputs!$C$28+Inputs!$C$29+Inputs!$C$50+Inputs!$C$30+Engine!$B$21)) -> -0.018726939 | C15: =(($B$6*(1+C$9)*(1-Inputs!$C$24))-(($B$7*(1+$A15))+(Inputs!$C$27+Inputs!$C$28+Inputs!$C$29+Inputs!$C$50+Inputs!$C$30+Engine!$B$21)))/(($B$7*(1+$A15))+(Inputs!$C$27+Inputs!$C$28+Inputs!$C$29+Inputs!$C$50+Inputs!$C$30+Engine!$B$21)) -> 0.035788231 | D15: =(($B$6*(1+D$9)*(1-Inputs!$C$24))-(($B$7*(1+$A15))+(Inputs!$C$27+Inputs!$C$28+Inputs!$C$29+Inputs!$C$50+Inputs!$C$30+Engine!$B$21)))/(($B$7*(1+$A15))+(Inputs!$C$27+Inputs!$C$28+Inputs!$C$29+Inputs!$C$50+Inputs!$C$30+Engine!$B$21)) -> 0.090303401 | E15: =(($B$6*(1+E$9)*(1-Inputs!$C$24))-(($B$7*(1+$A15))+(Inputs!$C$27+Inputs!$C$28+Inputs!$C$29+Inputs!$C$50+Inputs!$C$30+Engine!$B$21)))/(($B$7*(1+$A15))+(Inputs!$C$27+Inputs!$C$28+Inputs!$C$29+Inputs!$C$50+Inputs!$C$30+Engine!$B$21)) -> 0.14481857 | F15: =(($B$6*(1+F$9)*(1-Inputs!$C$24))-(($B$7*(1+$A15))+(Inputs!$C$27+Inputs!$C$28+Inputs!$C$29+Inputs!$C$50+Inputs!$C$30+Engine!$B$21)))/(($B$7*(1+$A15))+(Inputs!$C$27+Inputs!$C$28+Inputs!$C$29+Inputs!$C$50+Inputs!$C$30+Engine!$B$21)) -> 0.19933374
A18: Grid 2: the JV deal terms
A19: Sponsor multiple as preferred return (down) and promote to sponsor (across) move. Proceeds to equity and capital held at the base run, so this isolates the split.
A20: Base sponsor multiple | B20: =Waterfall!$C$36 -> 2.5130585
A22: Mult: pref (down) vs promote (right) | B22: 0.3 | C22: 0.4 | D22: 0.5 | E22: 0.6 | F22: 0.7
A23: 0.06 | B23: =(Waterfall!$C$6+IF(((Waterfall!$C$6*((1+$A23)^Waterfall!$C$20-1))+(Waterfall!$D$6*((1+$A23)^Waterfall!$C$20-1))+(Waterfall!$E$6*((1+$A23)^Waterfall!$E$20-1)))>0,MIN((Waterfall!$F$12-Waterfall!$F$6),((Waterfall!$C$6*((1+$A23)^Waterfall!$C$20-1))+(Waterfall!$D$6*((1+$A23)^Waterfall!$C$20-1))+(Waterfall!$E$6*((1+$A23)^Waterfall!$E$20-1))))*(Waterfall!$C$6*((1+$A23)^Waterfall!$C$20-1))/((Waterfall!$C$6*((1+$A23)^Waterfall!$C$20-1))+(Waterfall!$D$6*((1+$A23)^Waterfall!$C$20-1))+(Waterfall!$E$6*((1+$A23)^Waterfall!$E$20-1))),0)+(MAX(0,(Waterfall!$F$12-Waterfall!$F$6)-MIN((Waterfall!$F$12-Waterfall!$F$6),((Waterfall!$C$6*((1+$A23)^Waterfall!$C$20-1))+(Waterfall!$D$6*((1+$A23)^Waterfall!$C$20-1))+(Waterfall!$E$6*((1+$A23)^Waterfall!$E$20-1)))))*(1-B$22)*Waterfall!$C$6/Waterfall!$F$6)+(MAX(0,(Waterfall!$F$12-Waterfall!$F$6)-MIN((Waterfall!$F$12-Waterfall!$F$6),((Waterfall!$C$6*((1+$A23)^Waterfall!$C$20-1))+(Waterfall!$D$6*((1+$A23)^Waterfall!$C$20-1))+(Waterfall!$E$6*((1+$A23)^Waterfall!$E$20-1)))))*B$22)+Inputs!$C$50)/Waterfall!$C$6 -> 2.3480986 | C23: =(Waterfall!$C$6+IF(((Waterfall!$C$6*((1+$A23)^Waterfall!$C$20-1))+(Waterfall!$D$6*((1+$A23)^Waterfall!$C$20-1))+(Waterfall!$E$6*((1+$A23)^Waterfall!$E$20-1)))>0,MIN((Waterfall!$F$12-Waterfall!$F$6),((Waterfall!$C$6*((1+$A23)^Waterfall!$C$20-1))+(Waterfall!$D$6*((1+$A23)^Waterfall!$C$20-1))+(Waterfall!$E$6*((1+$A23)^Waterfall!$E$20-1))))*(Waterfall!$C$6*((1+$A23)^Waterfall!$C$20-1))/((Waterfall!$C$6*((1+$A23)^Waterfall!$C$20-1))+(Waterfall!$D$6*((1+$A23)^Waterfall!$C$20-1))+(Waterfall!$E$6*((1+$A23)^Waterfall!$E$20-1))),0)+(MAX(0,(Waterfall!$F$12-Waterfall!$F$6)-MIN((Waterfall!$F$12-Waterfall!$F$6),((Waterfall!$C$6*((1+$A23)^Waterfall!$C$20-1))+(Waterfall!$D$6*((1+$A23)^Waterfall!$C$20-1))+(Waterfall!$E$6*((1+$A23)^Waterfall!$E$20-1)))))*(1-C$22)*Waterfall!$C$6/Waterfall!$F$6)+(MAX(0,(Waterfall!$F$12-Waterfall!$F$6)-MIN((Waterfall!$F$12-Waterfall!$F$6),((Waterfall!$C$6*((1+$A23)^Waterfall!$C$20-1))+(Waterfall!$D$6*((1+$A23)^Waterfall!$C$20-1))+(Waterfall!$E$6*((1+$A23)^Waterfall!$E$20-1)))))*C$22)+Inputs!$C$50)/Waterfall!$C$6 -> 2.5302919 | D23: =(Waterfall!$C$6+IF(((Waterfall!$C$6*((1+$A23)^Waterfall!$C$20-1))+(Waterfall!$D$6*((1+$A23)^Waterfall!$C$20-1))+(Waterfall!$E$6*((1+$A23)^Waterfall!$E$20-1)))>0,MIN((Waterfall!$F$12-Waterfall!$F$6),((Waterfall!$C$6*((1+$A23)^Waterfall!$C$20-1))+(Waterfall!$D$6*((1+$A23)^Waterfall!$C$20-1))+(Waterfall!$E$6*((1+$A23)^Waterfall!$E$20-1))))*(Waterfall!$C$6*((1+$A23)^Waterfall!$C$20-1))/((Waterfall!$C$6*((1+$A23)^Waterfall!$C$20-1))+(Waterfall!$D$6*((1+$A23)^Waterfall!$C$20-1))+(Waterfall!$E$6*((1+$A23)^Waterfall!$E$20-1))),0)+(MAX(0,(Waterfall!$F$12-Waterfall!$F$6)-MIN((Waterfall!$F$12-Waterfall!$F$6),((Waterfall!$C$6*((1+$A23)^Waterfall!$C$20-1))+(Waterfall!$D$6*((1+$A23)^Waterfall!$C$20-1))+(Waterfall!$E$6*((1+$A23)^Waterfall!$E$20-1)))))*(1-D$22)*Waterfall!$C$6/Waterfall!$F$6)+(MAX(0,(Waterfall!$F$12-Waterfall!$F$6)-MIN((Waterfall!$F$12-Waterfall!$F$6),((Waterfall!$C$6*((1+$A23)^Waterfall!$C$20-1))+(Waterfall!$D$6*((1+$A23)^Waterfall!$C$20-1))+(Waterfall!$E$6*((1+$A23)^Waterfall!$E$20-1)))))*D$22)+Inputs!$C$50)/Waterfall!$C$6 -> 2.7124851 | E23: =(Waterfall!$C$6+IF(((Waterfall!$C$6*((1+$A23)^Waterfall!$C$20-1))+(Waterfall!$D$6*((1+$A23)^Waterfall!$C$20-1))+(Waterfall!$E$6*((1+$A23)^Waterfall!$E$20-1)))>0,MIN((Waterfall!$F$12-Waterfall!$F$6),((Waterfall!$C$6*((1+$A23)^Waterfall!$C$20-1))+(Waterfall!$D$6*((1+$A23)^Waterfall!$C$20-1))+(Waterfall!$E$6*((1+$A23)^Waterfall!$E$20-1))))*(Waterfall!$C$6*((1+$A23)^Waterfall!$C$20-1))/((Waterfall!$C$6*((1+$A23)^Waterfall!$C$20-1))+(Waterfall!$D$6*((1+$A23)^Waterfall!$C$20-1))+(Waterfall!$E$6*((1+$A23)^Waterfall!$E$20-1))),0)+(MAX(0,(Waterfall!$F$12-Waterfall!$F$6)-MIN((Waterfall!$F$12-Waterfall!$F$6),((Waterfall!$C$6*((1+$A23)^Waterfall!$C$20-1))+(Waterfall!$D$6*((1+$A23)^Waterfall!$C$20-1))+(Waterfall!$E$6*((1+$A23)^Waterfall!$E$20-1)))))*(1-E$22)*Waterfall!$C$6/Waterfall!$F$6)+(MAX(0,(Waterfall!$F$12-Waterfall!$F$6)-MIN((Waterfall!$F$12-Waterfall!$F$6),((Waterfall!$C$6*((1+$A23)^Waterfall!$C$20-1))+(Waterfall!$D$6*((1+$A23)^Waterfall!$C$20-1))+(Waterfall!$E$6*((1+$A23)^Waterfall!$E$20-1)))))*E$22)+Inputs!$C$50)/Waterfall!$C$6 -> 2.8946784 | F23: =(Waterfall!$C$6+IF(((Waterfall!$C$6*((1+$A23)^Waterfall!$C$20-1))+(Waterfall!$D$6*((1+$A23)^Waterfall!$C$20-1))+(Waterfall!$E$6*((1+$A23)^Waterfall!$E$20-1)))>0,MIN((Waterfall!$F$12-Waterfall!$F$6),((Waterfall!$C$6*((1+$A23)^Waterfall!$C$20-1))+(Waterfall!$D$6*((1+$A23)^Waterfall!$C$20-1))+(Waterfall!$E$6*((1+$A23)^Waterfall!$E$20-1))))*(Waterfall!$C$6*((1+$A23)^Waterfall!$C$20-1))/((Waterfall!$C$6*((1+$A23)^Waterfall!$C$20-1))+(Waterfall!$D$6*((1+$A23)^Waterfall!$C$20-1))+(Waterfall!$E$6*((1+$A23)^Waterfall!$E$20-1))),0)+(MAX(0,(Waterfall!$F$12-Waterfall!$F$6)-MIN((Waterfall!$F$12-Waterfall!$F$6),((Waterfall!$C$6*((1+$A23)^Waterfall!$C$20-1))+(Waterfall!$D$6*((1+$A23)^Waterfall!$C$20-1))+(Waterfall!$E$6*((1+$A23)^Waterfall!$E$20-1)))))*(1-F$22)*Waterfall!$C$6/Waterfall!$F$6)+(MAX(0,(Waterfall!$F$12-Waterfall!$F$6)-MIN((Waterfall!$F$12-Waterfall!$F$6),((Waterfall!$C$6*((1+$A23)^Waterfall!$C$20-1))+(Waterfall!$D$6*((1+$A23)^Waterfall!$C$20-1))+(Waterfall!$E$6*((1+$A23)^Waterfall!$E$20-1)))))*F$22)+Inputs!$C$50)/Waterfall!$C$6 -> 3.0768716
A24: 0.08 | B24: =(Waterfall!$C$6+IF(((Waterfall!$C$6*((1+$A24)^Waterfall!$C$20-1))+(Waterfall!$D$6*((1+$A24)^Waterfall!$C$20-1))+(Waterfall!$E$6*((1+$A24)^Waterfall!$E$20-1)))>0,MIN((Waterfall!$F$12-Waterfall!$F$6),((Waterfall!$C$6*((1+$A24)^Waterfall!$C$20-1))+(Waterfall!$D$6*((1+$A24)^Waterfall!$C$20-1))+(Waterfall!$E$6*((1+$A24)^Waterfall!$E$20-1))))*(Waterfall!$C$6*((1+$A24)^Waterfall!$C$20-1))/((Waterfall!$C$6*((1+$A24)^Waterfall!$C$20-1))+(Waterfall!$D$6*((1+$A24)^Waterfall!$C$20-1))+(Waterfall!$E$6*((1+$A24)^Waterfall!$E$20-1))),0)+(MAX(0,(Waterfall!$F$12-Waterfall!$F$6)-MIN((Waterfall!$F$12-Waterfall!$F$6),((Waterfall!$C$6*((1+$A24)^Waterfall!$C$20-1))+(Waterfall!$D$6*((1+$A24)^Waterfall!$C$20-1))+(Waterfall!$E$6*((1+$A24)^Waterfall!$E$20-1)))))*(1-B$22)*Waterfall!$C$6/Waterfall!$F$6)+(MAX(0,(Waterfall!$F$12-Waterfall!$F$6)-MIN((Waterfall!$F$12-Waterfall!$F$6),((Waterfall!$C$6*((1+$A24)^Waterfall!$C$20-1))+(Waterfall!$D$6*((1+$A24)^Waterfall!$C$20-1))+(Waterfall!$E$6*((1+$A24)^Waterfall!$E$20-1)))))*B$22)+Inputs!$C$50)/Waterfall!$C$6 -> 2.2833307 | C24: =(Waterfall!$C$6+IF(((Waterfall!$C$6*((1+$A24)^Waterfall!$C$20-1))+(Waterfall!$D$6*((1+$A24)^Waterfall!$C$20-1))+(Waterfall!$E$6*((1+$A24)^Waterfall!$E$20-1)))>0,MIN((Waterfall!$F$12-Waterfall!$F$6),((Waterfall!$C$6*((1+$A24)^Waterfall!$C$20-1))+(Waterfall!$D$6*((1+$A24)^Waterfall!$C$20-1))+(Waterfall!$E$6*((1+$A24)^Waterfall!$E$20-1))))*(Waterfall!$C$6*((1+$A24)^Waterfall!$C$20-1))/((Waterfall!$C$6*((1+$A24)^Waterfall!$C$20-1))+(Waterfall!$D$6*((1+$A24)^Waterfall!$C$20-1))+(Waterfall!$E$6*((1+$A24)^Waterfall!$E$20-1))),0)+(MAX(0,(Waterfall!$F$12-Waterfall!$F$6)-MIN((Waterfall!$F$12-Waterfall!$F$6),((Waterfall!$C$6*((1+$A24)^Waterfall!$C$20-1))+(Waterfall!$D$6*((1+$A24)^Waterfall!$C$20-1))+(Waterfall!$E$6*((1+$A24)^Waterfall!$E$20-1)))))*(1-C$22)*Waterfall!$C$6/Waterfall!$F$6)+(MAX(0,(Waterfall!$F$12-Waterfall!$F$6)-MIN((Waterfall!$F$12-Waterfall!$F$6),((Waterfall!$C$6*((1+$A24)^Waterfall!$C$20-1))+(Waterfall!$D$6*((1+$A24)^Waterfall!$C$20-1))+(Waterfall!$E$6*((1+$A24)^Waterfall!$E$20-1)))))*C$22)+Inputs!$C$50)/Waterfall!$C$6 -> 2.4486067 | D24: =(Waterfall!$C$6+IF(((Waterfall!$C$6*((1+$A24)^Waterfall!$C$20-1))+(Waterfall!$D$6*((1+$A24)^Waterfall!$C$20-1))+(Waterfall!$E$6*((1+$A24)^Waterfall!$E$20-1)))>0,MIN((Waterfall!$F$12-Waterfall!$F$6),((Waterfall!$C$6*((1+$A24)^Waterfall!$C$20-1))+(Waterfall!$D$6*((1+$A24)^Waterfall!$C$20-1))+(Waterfall!$E$6*((1+$A24)^Waterfall!$E$20-1))))*(Waterfall!$C$6*((1+$A24)^Waterfall!$C$20-1))/((Waterfall!$C$6*((1+$A24)^Waterfall!$C$20-1))+(Waterfall!$D$6*((1+$A24)^Waterfall!$C$20-1))+(Waterfall!$E$6*((1+$A24)^Waterfall!$E$20-1))),0)+(MAX(0,(Waterfall!$F$12-Waterfall!$F$6)-MIN((Waterfall!$F$12-Waterfall!$F$6),((Waterfall!$C$6*((1+$A24)^Waterfall!$C$20-1))+(Waterfall!$D$6*((1+$A24)^Waterfall!$C$20-1))+(Waterfall!$E$6*((1+$A24)^Waterfall!$E$20-1)))))*(1-D$22)*Waterfall!$C$6/Waterfall!$F$6)+(MAX(0,(Waterfall!$F$12-Waterfall!$F$6)-MIN((Waterfall!$F$12-Waterfall!$F$6),((Waterfall!$C$6*((1+$A24)^Waterfall!$C$20-1))+(Waterfall!$D$6*((1+$A24)^Waterfall!$C$20-1))+(Waterfall!$E$6*((1+$A24)^Waterfall!$E$20-1)))))*D$22)+Inputs!$C$50)/Waterfall!$C$6 -> 2.6138827 | E24: =(Waterfall!$C$6+IF(((Waterfall!$C$6*((1+$A24)^Waterfall!$C$20-1))+(Waterfall!$D$6*((1+$A24)^Waterfall!$C$20-1))+(Waterfall!$E$6*((1+$A24)^Waterfall!$E$20-1)))>0,MIN((Waterfall!$F$12-Waterfall!$F$6),((Waterfall!$C$6*((1+$A24)^Waterfall!$C$20-1))+(Waterfall!$D$6*((1+$A24)^Waterfall!$C$20-1))+(Waterfall!$E$6*((1+$A24)^Waterfall!$E$20-1))))*(Waterfall!$C$6*((1+$A24)^Waterfall!$C$20-1))/((Waterfall!$C$6*((1+$A24)^Waterfall!$C$20-1))+(Waterfall!$D$6*((1+$A24)^Waterfall!$C$20-1))+(Waterfall!$E$6*((1+$A24)^Waterfall!$E$20-1))),0)+(MAX(0,(Waterfall!$F$12-Waterfall!$F$6)-MIN((Waterfall!$F$12-Waterfall!$F$6),((Waterfall!$C$6*((1+$A24)^Waterfall!$C$20-1))+(Waterfall!$D$6*((1+$A24)^Waterfall!$C$20-1))+(Waterfall!$E$6*((1+$A24)^Waterfall!$E$20-1)))))*(1-E$22)*Waterfall!$C$6/Waterfall!$F$6)+(MAX(0,(Waterfall!$F$12-Waterfall!$F$6)-MIN((Waterfall!$F$12-Waterfall!$F$6),((Waterfall!$C$6*((1+$A24)^Waterfall!$C$20-1))+(Waterfall!$D$6*((1+$A24)^Waterfall!$C$20-1))+(Waterfall!$E$6*((1+$A24)^Waterfall!$E$20-1)))))*E$22)+Inputs!$C$50)/Waterfall!$C$6 -> 2.7791587 | F24: =(Waterfall!$C$6+IF(((Waterfall!$C$6*((1+$A24)^Waterfall!$C$20-1))+(Waterfall!$D$6*((1+$A24)^Waterfall!$C$20-1))+(Waterfall!$E$6*((1+$A24)^Waterfall!$E$20-1)))>0,MIN((Waterfall!$F$12-Waterfall!$F$6),((Waterfall!$C$6*((1+$A24)^Waterfall!$C$20-1))+(Waterfall!$D$6*((1+$A24)^Waterfall!$C$20-1))+(Waterfall!$E$6*((1+$A24)^Waterfall!$E$20-1))))*(Waterfall!$C$6*((1+$A24)^Waterfall!$C$20-1))/((Waterfall!$C$6*((1+$A24)^Waterfall!$C$20-1))+(Waterfall!$D$6*((1+$A24)^Waterfall!$C$20-1))+(Waterfall!$E$6*((1+$A24)^Waterfall!$E$20-1))),0)+(MAX(0,(Waterfall!$F$12-Waterfall!$F$6)-MIN((Waterfall!$F$12-Waterfall!$F$6),((Waterfall!$C$6*((1+$A24)^Waterfall!$C$20-1))+(Waterfall!$D$6*((1+$A24)^Waterfall!$C$20-1))+(Waterfall!$E$6*((1+$A24)^Waterfall!$E$20-1)))))*(1-F$22)*Waterfall!$C$6/Waterfall!$F$6)+(MAX(0,(Waterfall!$F$12-Waterfall!$F$6)-MIN((Waterfall!$F$12-Waterfall!$F$6),((Waterfall!$C$6*((1+$A24)^Waterfall!$C$20-1))+(Waterfall!$D$6*((1+$A24)^Waterfall!$C$20-1))+(Waterfall!$E$6*((1+$A24)^Waterfall!$E$20-1)))))*F$22)+Inputs!$C$50)/Waterfall!$C$6 -> 2.9444347
A25: 0.1 | B25: =(Waterfall!$C$6+IF(((Waterfall!$C$6*((1+$A25)^Waterfall!$C$20-1))+(Waterfall!$D$6*((1+$A25)^Waterfall!$C$20-1))+(Waterfall!$E$6*((1+$A25)^Waterfall!$E$20-1)))>0,MIN((Waterfall!$F$12-Waterfall!$F$6),((Waterfall!$C$6*((1+$A25)^Waterfall!$C$20-1))+(Waterfall!$D$6*((1+$A25)^Waterfall!$C$20-1))+(Waterfall!$E$6*((1+$A25)^Waterfall!$E$20-1))))*(Waterfall!$C$6*((1+$A25)^Waterfall!$C$20-1))/((Waterfall!$C$6*((1+$A25)^Waterfall!$C$20-1))+(Waterfall!$D$6*((1+$A25)^Waterfall!$C$20-1))+(Waterfall!$E$6*((1+$A25)^Waterfall!$E$20-1))),0)+(MAX(0,(Waterfall!$F$12-Waterfall!$F$6)-MIN((Waterfall!$F$12-Waterfall!$F$6),((Waterfall!$C$6*((1+$A25)^Waterfall!$C$20-1))+(Waterfall!$D$6*((1+$A25)^Waterfall!$C$20-1))+(Waterfall!$E$6*((1+$A25)^Waterfall!$E$20-1)))))*(1-B$22)*Waterfall!$C$6/Waterfall!$F$6)+(MAX(0,(Waterfall!$F$12-Waterfall!$F$6)-MIN((Waterfall!$F$12-Waterfall!$F$6),((Waterfall!$C$6*((1+$A25)^Waterfall!$C$20-1))+(Waterfall!$D$6*((1+$A25)^Waterfall!$C$20-1))+(Waterfall!$E$6*((1+$A25)^Waterfall!$E$20-1)))))*B$22)+Inputs!$C$50)/Waterfall!$C$6 -> 2.2169749 | C25: =(Waterfall!$C$6+IF(((Waterfall!$C$6*((1+$A25)^Waterfall!$C$20-1))+(Waterfall!$D$6*((1+$A25)^Waterfall!$C$20-1))+(Waterfall!$E$6*((1+$A25)^Waterfall!$E$20-1)))>0,MIN((Waterfall!$F$12-Waterfall!$F$6),((Waterfall!$C$6*((1+$A25)^Waterfall!$C$20-1))+(Waterfall!$D$6*((1+$A25)^Waterfall!$C$20-1))+(Waterfall!$E$6*((1+$A25)^Waterfall!$E$20-1))))*(Waterfall!$C$6*((1+$A25)^Waterfall!$C$20-1))/((Waterfall!$C$6*((1+$A25)^Waterfall!$C$20-1))+(Waterfall!$D$6*((1+$A25)^Waterfall!$C$20-1))+(Waterfall!$E$6*((1+$A25)^Waterfall!$E$20-1))),0)+(MAX(0,(Waterfall!$F$12-Waterfall!$F$6)-MIN((Waterfall!$F$12-Waterfall!$F$6),((Waterfall!$C$6*((1+$A25)^Waterfall!$C$20-1))+(Waterfall!$D$6*((1+$A25)^Waterfall!$C$20-1))+(Waterfall!$E$6*((1+$A25)^Waterfall!$E$20-1)))))*(1-C$22)*Waterfall!$C$6/Waterfall!$F$6)+(MAX(0,(Waterfall!$F$12-Waterfall!$F$6)-MIN((Waterfall!$F$12-Waterfall!$F$6),((Waterfall!$C$6*((1+$A25)^Waterfall!$C$20-1))+(Waterfall!$D$6*((1+$A25)^Waterfall!$C$20-1))+(Waterfall!$E$6*((1+$A25)^Waterfall!$E$20-1)))))*C$22)+Inputs!$C$50)/Waterfall!$C$6 -> 2.3650167 | D25: =(Waterfall!$C$6+IF(((Waterfall!$C$6*((1+$A25)^Waterfall!$C$20-1))+(Waterfall!$D$6*((1+$A25)^Waterfall!$C$20-1))+(Waterfall!$E$6*((1+$A25)^Waterfall!$E$20-1)))>0,MIN((Waterfall!$F$12-Waterfall!$F$6),((Waterfall!$C$6*((1+$A25)^Waterfall!$C$20-1))+(Waterfall!$D$6*((1+$A25)^Waterfall!$C$20-1))+(Waterfall!$E$6*((1+$A25)^Waterfall!$E$20-1))))*(Waterfall!$C$6*((1+$A25)^Waterfall!$C$20-1))/((Waterfall!$C$6*((1+$A25)^Waterfall!$C$20-1))+(Waterfall!$D$6*((1+$A25)^Waterfall!$C$20-1))+(Waterfall!$E$6*((1+$A25)^Waterfall!$E$20-1))),0)+(MAX(0,(Waterfall!$F$12-Waterfall!$F$6)-MIN((Waterfall!$F$12-Waterfall!$F$6),((Waterfall!$C$6*((1+$A25)^Waterfall!$C$20-1))+(Waterfall!$D$6*((1+$A25)^Waterfall!$C$20-1))+(Waterfall!$E$6*((1+$A25)^Waterfall!$E$20-1)))))*(1-D$22)*Waterfall!$C$6/Waterfall!$F$6)+(MAX(0,(Waterfall!$F$12-Waterfall!$F$6)-MIN((Waterfall!$F$12-Waterfall!$F$6),((Waterfall!$C$6*((1+$A25)^Waterfall!$C$20-1))+(Waterfall!$D$6*((1+$A25)^Waterfall!$C$20-1))+(Waterfall!$E$6*((1+$A25)^Waterfall!$E$20-1)))))*D$22)+Inputs!$C$50)/Waterfall!$C$6 -> 2.5130585 | E25: =(Waterfall!$C$6+IF(((Waterfall!$C$6*((1+$A25)^Waterfall!$C$20-1))+(Waterfall!$D$6*((1+$A25)^Waterfall!$C$20-1))+(Waterfall!$E$6*((1+$A25)^Waterfall!$E$20-1)))>0,MIN((Waterfall!$F$12-Waterfall!$F$6),((Waterfall!$C$6*((1+$A25)^Waterfall!$C$20-1))+(Waterfall!$D$6*((1+$A25)^Waterfall!$C$20-1))+(Waterfall!$E$6*((1+$A25)^Waterfall!$E$20-1))))*(Waterfall!$C$6*((1+$A25)^Waterfall!$C$20-1))/((Waterfall!$C$6*((1+$A25)^Waterfall!$C$20-1))+(Waterfall!$D$6*((1+$A25)^Waterfall!$C$20-1))+(Waterfall!$E$6*((1+$A25)^Waterfall!$E$20-1))),0)+(MAX(0,(Waterfall!$F$12-Waterfall!$F$6)-MIN((Waterfall!$F$12-Waterfall!$F$6),((Waterfall!$C$6*((1+$A25)^Waterfall!$C$20-1))+(Waterfall!$D$6*((1+$A25)^Waterfall!$C$20-1))+(Waterfall!$E$6*((1+$A25)^Waterfall!$E$20-1)))))*(1-E$22)*Waterfall!$C$6/Waterfall!$F$6)+(MAX(0,(Waterfall!$F$12-Waterfall!$F$6)-MIN((Waterfall!$F$12-Waterfall!$F$6),((Waterfall!$C$6*((1+$A25)^Waterfall!$C$20-1))+(Waterfall!$D$6*((1+$A25)^Waterfall!$C$20-1))+(Waterfall!$E$6*((1+$A25)^Waterfall!$E$20-1)))))*E$22)+Inputs!$C$50)/Waterfall!$C$6 -> 2.6611003 | F25: =(Waterfall!$C$6+IF(((Waterfall!$C$6*((1+$A25)^Waterfall!$C$20-1))+(Waterfall!$D$6*((1+$A25)^Waterfall!$C$20-1))+(Waterfall!$E$6*((1+$A25)^Waterfall!$E$20-1)))>0,MIN((Waterfall!$F$12-Waterfall!$F$6),((Waterfall!$C$6*((1+$A25)^Waterfall!$C$20-1))+(Waterfall!$D$6*((1+$A25)^Waterfall!$C$20-1))+(Waterfall!$E$6*((1+$A25)^Waterfall!$E$20-1))))*(Waterfall!$C$6*((1+$A25)^Waterfall!$C$20-1))/((Waterfall!$C$6*((1+$A25)^Waterfall!$C$20-1))+(Waterfall!$D$6*((1+$A25)^Waterfall!$C$20-1))+(Waterfall!$E$6*((1+$A25)^Waterfall!$E$20-1))),0)+(MAX(0,(Waterfall!$F$12-Waterfall!$F$6)-MIN((Waterfall!$F$12-Waterfall!$F$6),((Waterfall!$C$6*((1+$A25)^Waterfall!$C$20-1))+(Waterfall!$D$6*((1+$A25)^Waterfall!$C$20-1))+(Waterfall!$E$6*((1+$A25)^Waterfall!$E$20-1)))))*(1-F$22)*Waterfall!$C$6/Waterfall!$F$6)+(MAX(0,(Waterfall!$F$12-Waterfall!$F$6)-MIN((Waterfall!$F$12-Waterfall!$F$6),((Waterfall!$C$6*((1+$A25)^Waterfall!$C$20-1))+(Waterfall!$D$6*((1+$A25)^Waterfall!$C$20-1))+(Waterfall!$E$6*((1+$A25)^Waterfall!$E$20-1)))))*F$22)+Inputs!$C$50)/Waterfall!$C$6 -> 2.809142
A26: 0.12 | B26: =(Waterfall!$C$6+IF(((Waterfall!$C$6*((1+$A26)^Waterfall!$C$20-1))+(Waterfall!$D$6*((1+$A26)^Waterfall!$C$20-1))+(Waterfall!$E$6*((1+$A26)^Waterfall!$E$20-1)))>0,MIN((Waterfall!$F$12-Waterfall!$F$6),((Waterfall!$C$6*((1+$A26)^Waterfall!$C$20-1))+(Waterfall!$D$6*((1+$A26)^Waterfall!$C$20-1))+(Waterfall!$E$6*((1+$A26)^Waterfall!$E$20-1))))*(Waterfall!$C$6*((1+$A26)^Waterfall!$C$20-1))/((Waterfall!$C$6*((1+$A26)^Waterfall!$C$20-1))+(Waterfall!$D$6*((1+$A26)^Waterfall!$C$20-1))+(Waterfall!$E$6*((1+$A26)^Waterfall!$E$20-1))),0)+(MAX(0,(Waterfall!$F$12-Waterfall!$F$6)-MIN((Waterfall!$F$12-Waterfall!$F$6),((Waterfall!$C$6*((1+$A26)^Waterfall!$C$20-1))+(Waterfall!$D$6*((1+$A26)^Waterfall!$C$20-1))+(Waterfall!$E$6*((1+$A26)^Waterfall!$E$20-1)))))*(1-B$22)*Waterfall!$C$6/Waterfall!$F$6)+(MAX(0,(Waterfall!$F$12-Waterfall!$F$6)-MIN((Waterfall!$F$12-Waterfall!$F$6),((Waterfall!$C$6*((1+$A26)^Waterfall!$C$20-1))+(Waterfall!$D$6*((1+$A26)^Waterfall!$C$20-1))+(Waterfall!$E$6*((1+$A26)^Waterfall!$E$20-1)))))*B$22)+Inputs!$C$50)/Waterfall!$C$6 -> 2.1490169 | C26: =(Waterfall!$C$6+IF(((Waterfall!$C$6*((1+$A26)^Waterfall!$C$20-1))+(Waterfall!$D$6*((1+$A26)^Waterfall!$C$20-1))+(Waterfall!$E$6*((1+$A26)^Waterfall!$E$20-1)))>0,MIN((Waterfall!$F$12-Waterfall!$F$6),((Waterfall!$C$6*((1+$A26)^Waterfall!$C$20-1))+(Waterfall!$D$6*((1+$A26)^Waterfall!$C$20-1))+(Waterfall!$E$6*((1+$A26)^Waterfall!$E$20-1))))*(Waterfall!$C$6*((1+$A26)^Waterfall!$C$20-1))/((Waterfall!$C$6*((1+$A26)^Waterfall!$C$20-1))+(Waterfall!$D$6*((1+$A26)^Waterfall!$C$20-1))+(Waterfall!$E$6*((1+$A26)^Waterfall!$E$20-1))),0)+(MAX(0,(Waterfall!$F$12-Waterfall!$F$6)-MIN((Waterfall!$F$12-Waterfall!$F$6),((Waterfall!$C$6*((1+$A26)^Waterfall!$C$20-1))+(Waterfall!$D$6*((1+$A26)^Waterfall!$C$20-1))+(Waterfall!$E$6*((1+$A26)^Waterfall!$E$20-1)))))*(1-C$22)*Waterfall!$C$6/Waterfall!$F$6)+(MAX(0,(Waterfall!$F$12-Waterfall!$F$6)-MIN((Waterfall!$F$12-Waterfall!$F$6),((Waterfall!$C$6*((1+$A26)^Waterfall!$C$20-1))+(Waterfall!$D$6*((1+$A26)^Waterfall!$C$20-1))+(Waterfall!$E$6*((1+$A26)^Waterfall!$E$20-1)))))*C$22)+Inputs!$C$50)/Waterfall!$C$6 -> 2.2795049 | D26: =(Waterfall!$C$6+IF(((Waterfall!$C$6*((1+$A26)^Waterfall!$C$20-1))+(Waterfall!$D$6*((1+$A26)^Waterfall!$C$20-1))+(Waterfall!$E$6*((1+$A26)^Waterfall!$E$20-1)))>0,MIN((Waterfall!$F$12-Waterfall!$F$6),((Waterfall!$C$6*((1+$A26)^Waterfall!$C$20-1))+(Waterfall!$D$6*((1+$A26)^Waterfall!$C$20-1))+(Waterfall!$E$6*((1+$A26)^Waterfall!$E$20-1))))*(Waterfall!$C$6*((1+$A26)^Waterfall!$C$20-1))/((Waterfall!$C$6*((1+$A26)^Waterfall!$C$20-1))+(Waterfall!$D$6*((1+$A26)^Waterfall!$C$20-1))+(Waterfall!$E$6*((1+$A26)^Waterfall!$E$20-1))),0)+(MAX(0,(Waterfall!$F$12-Waterfall!$F$6)-MIN((Waterfall!$F$12-Waterfall!$F$6),((Waterfall!$C$6*((1+$A26)^Waterfall!$C$20-1))+(Waterfall!$D$6*((1+$A26)^Waterfall!$C$20-1))+(Waterfall!$E$6*((1+$A26)^Waterfall!$E$20-1)))))*(1-D$22)*Waterfall!$C$6/Waterfall!$F$6)+(MAX(0,(Waterfall!$F$12-Waterfall!$F$6)-MIN((Waterfall!$F$12-Waterfall!$F$6),((Waterfall!$C$6*((1+$A26)^Waterfall!$C$20-1))+(Waterfall!$D$6*((1+$A26)^Waterfall!$C$20-1))+(Waterfall!$E$6*((1+$A26)^Waterfall!$E$20-1)))))*D$22)+Inputs!$C$50)/Waterfall!$C$6 -> 2.4099928 | E26: =(Waterfall!$C$6+IF(((Waterfall!$C$6*((1+$A26)^Waterfall!$C$20-1))+(Waterfall!$D$6*((1+$A26)^Waterfall!$C$20-1))+(Waterfall!$E$6*((1+$A26)^Waterfall!$E$20-1)))>0,MIN((Waterfall!$F$12-Waterfall!$F$6),((Waterfall!$C$6*((1+$A26)^Waterfall!$C$20-1))+(Waterfall!$D$6*((1+$A26)^Waterfall!$C$20-1))+(Waterfall!$E$6*((1+$A26)^Waterfall!$E$20-1))))*(Waterfall!$C$6*((1+$A26)^Waterfall!$C$20-1))/((Waterfall!$C$6*((1+$A26)^Waterfall!$C$20-1))+(Waterfall!$D$6*((1+$A26)^Waterfall!$C$20-1))+(Waterfall!$E$6*((1+$A26)^Waterfall!$E$20-1))),0)+(MAX(0,(Waterfall!$F$12-Waterfall!$F$6)-MIN((Waterfall!$F$12-Waterfall!$F$6),((Waterfall!$C$6*((1+$A26)^Waterfall!$C$20-1))+(Waterfall!$D$6*((1+$A26)^Waterfall!$C$20-1))+(Waterfall!$E$6*((1+$A26)^Waterfall!$E$20-1)))))*(1-E$22)*Waterfall!$C$6/Waterfall!$F$6)+(MAX(0,(Waterfall!$F$12-Waterfall!$F$6)-MIN((Waterfall!$F$12-Waterfall!$F$6),((Waterfall!$C$6*((1+$A26)^Waterfall!$C$20-1))+(Waterfall!$D$6*((1+$A26)^Waterfall!$C$20-1))+(Waterfall!$E$6*((1+$A26)^Waterfall!$E$20-1)))))*E$22)+Inputs!$C$50)/Waterfall!$C$6 -> 2.5404808 | F26: =(Waterfall!$C$6+IF(((Waterfall!$C$6*((1+$A26)^Waterfall!$C$20-1))+(Waterfall!$D$6*((1+$A26)^Waterfall!$C$20-1))+(Waterfall!$E$6*((1+$A26)^Waterfall!$E$20-1)))>0,MIN((Waterfall!$F$12-Waterfall!$F$6),((Waterfall!$C$6*((1+$A26)^Waterfall!$C$20-1))+(Waterfall!$D$6*((1+$A26)^Waterfall!$C$20-1))+(Waterfall!$E$6*((1+$A26)^Waterfall!$E$20-1))))*(Waterfall!$C$6*((1+$A26)^Waterfall!$C$20-1))/((Waterfall!$C$6*((1+$A26)^Waterfall!$C$20-1))+(Waterfall!$D$6*((1+$A26)^Waterfall!$C$20-1))+(Waterfall!$E$6*((1+$A26)^Waterfall!$E$20-1))),0)+(MAX(0,(Waterfall!$F$12-Waterfall!$F$6)-MIN((Waterfall!$F$12-Waterfall!$F$6),((Waterfall!$C$6*((1+$A26)^Waterfall!$C$20-1))+(Waterfall!$D$6*((1+$A26)^Waterfall!$C$20-1))+(Waterfall!$E$6*((1+$A26)^Waterfall!$E$20-1)))))*(1-F$22)*Waterfall!$C$6/Waterfall!$F$6)+(MAX(0,(Waterfall!$F$12-Waterfall!$F$6)-MIN((Waterfall!$F$12-Waterfall!$F$6),((Waterfall!$C$6*((1+$A26)^Waterfall!$C$20-1))+(Waterfall!$D$6*((1+$A26)^Waterfall!$C$20-1))+(Waterfall!$E$6*((1+$A26)^Waterfall!$E$20-1)))))*F$22)+Inputs!$C$50)/Waterfall!$C$6 -> 2.6709688
A27: 0.15 | B27: =(Waterfall!$C$6+IF(((Waterfall!$C$6*((1+$A27)^Waterfall!$C$20-1))+(Waterfall!$D$6*((1+$A27)^Waterfall!$C$20-1))+(Waterfall!$E$6*((1+$A27)^Waterfall!$E$20-1)))>0,MIN((Waterfall!$F$12-Waterfall!$F$6),((Waterfall!$C$6*((1+$A27)^Waterfall!$C$20-1))+(Waterfall!$D$6*((1+$A27)^Waterfall!$C$20-1))+(Waterfall!$E$6*((1+$A27)^Waterfall!$E$20-1))))*(Waterfall!$C$6*((1+$A27)^Waterfall!$C$20-1))/((Waterfall!$C$6*((1+$A27)^Waterfall!$C$20-1))+(Waterfall!$D$6*((1+$A27)^Waterfall!$C$20-1))+(Waterfall!$E$6*((1+$A27)^Waterfall!$E$20-1))),0)+(MAX(0,(Waterfall!$F$12-Waterfall!$F$6)-MIN((Waterfall!$F$12-Waterfall!$F$6),((Waterfall!$C$6*((1+$A27)^Waterfall!$C$20-1))+(Waterfall!$D$6*((1+$A27)^Waterfall!$C$20-1))+(Waterfall!$E$6*((1+$A27)^Waterfall!$E$20-1)))))*(1-B$22)*Waterfall!$C$6/Waterfall!$F$6)+(MAX(0,(Waterfall!$F$12-Waterfall!$F$6)-MIN((Waterfall!$F$12-Waterfall!$F$6),((Waterfall!$C$6*((1+$A27)^Waterfall!$C$20-1))+(Waterfall!$D$6*((1+$A27)^Waterfall!$C$20-1))+(Waterfall!$E$6*((1+$A27)^Waterfall!$E$20-1)))))*B$22)+Inputs!$C$50)/Waterfall!$C$6 -> 2.0440448 | C27: =(Waterfall!$C$6+IF(((Waterfall!$C$6*((1+$A27)^Waterfall!$C$20-1))+(Waterfall!$D$6*((1+$A27)^Waterfall!$C$20-1))+(Waterfall!$E$6*((1+$A27)^Waterfall!$E$20-1)))>0,MIN((Waterfall!$F$12-Waterfall!$F$6),((Waterfall!$C$6*((1+$A27)^Waterfall!$C$20-1))+(Waterfall!$D$6*((1+$A27)^Waterfall!$C$20-1))+(Waterfall!$E$6*((1+$A27)^Waterfall!$E$20-1))))*(Waterfall!$C$6*((1+$A27)^Waterfall!$C$20-1))/((Waterfall!$C$6*((1+$A27)^Waterfall!$C$20-1))+(Waterfall!$D$6*((1+$A27)^Waterfall!$C$20-1))+(Waterfall!$E$6*((1+$A27)^Waterfall!$E$20-1))),0)+(MAX(0,(Waterfall!$F$12-Waterfall!$F$6)-MIN((Waterfall!$F$12-Waterfall!$F$6),((Waterfall!$C$6*((1+$A27)^Waterfall!$C$20-1))+(Waterfall!$D$6*((1+$A27)^Waterfall!$C$20-1))+(Waterfall!$E$6*((1+$A27)^Waterfall!$E$20-1)))))*(1-C$22)*Waterfall!$C$6/Waterfall!$F$6)+(MAX(0,(Waterfall!$F$12-Waterfall!$F$6)-MIN((Waterfall!$F$12-Waterfall!$F$6),((Waterfall!$C$6*((1+$A27)^Waterfall!$C$20-1))+(Waterfall!$D$6*((1+$A27)^Waterfall!$C$20-1))+(Waterfall!$E$6*((1+$A27)^Waterfall!$E$20-1)))))*C$22)+Inputs!$C$50)/Waterfall!$C$6 -> 2.147597 | D27: =(Waterfall!$C$6+IF(((Waterfall!$C$6*((1+$A27)^Waterfall!$C$20-1))+(Waterfall!$D$6*((1+$A27)^Waterfall!$C$20-1))+(Waterfall!$E$6*((1+$A27)^Waterfall!$E$20-1)))>0,MIN((Waterfall!$F$12-Waterfall!$F$6),((Waterfall!$C$6*((1+$A27)^Waterfall!$C$20-1))+(Waterfall!$D$6*((1+$A27)^Waterfall!$C$20-1))+(Waterfall!$E$6*((1+$A27)^Waterfall!$E$20-1))))*(Waterfall!$C$6*((1+$A27)^Waterfall!$C$20-1))/((Waterfall!$C$6*((1+$A27)^Waterfall!$C$20-1))+(Waterfall!$D$6*((1+$A27)^Waterfall!$C$20-1))+(Waterfall!$E$6*((1+$A27)^Waterfall!$E$20-1))),0)+(MAX(0,(Waterfall!$F$12-Waterfall!$F$6)-MIN((Waterfall!$F$12-Waterfall!$F$6),((Waterfall!$C$6*((1+$A27)^Waterfall!$C$20-1))+(Waterfall!$D$6*((1+$A27)^Waterfall!$C$20-1))+(Waterfall!$E$6*((1+$A27)^Waterfall!$E$20-1)))))*(1-D$22)*Waterfall!$C$6/Waterfall!$F$6)+(MAX(0,(Waterfall!$F$12-Waterfall!$F$6)-MIN((Waterfall!$F$12-Waterfall!$F$6),((Waterfall!$C$6*((1+$A27)^Waterfall!$C$20-1))+(Waterfall!$D$6*((1+$A27)^Waterfall!$C$20-1))+(Waterfall!$E$6*((1+$A27)^Waterfall!$E$20-1)))))*D$22)+Inputs!$C$50)/Waterfall!$C$6 -> 2.2511491 | E27: =(Waterfall!$C$6+IF(((Waterfall!$C$6*((1+$A27)^Waterfall!$C$20-1))+(Waterfall!$D$6*((1+$A27)^Waterfall!$C$20-1))+(Waterfall!$E$6*((1+$A27)^Waterfall!$E$20-1)))>0,MIN((Waterfall!$F$12-Waterfall!$F$6),((Waterfall!$C$6*((1+$A27)^Waterfall!$C$20-1))+(Waterfall!$D$6*((1+$A27)^Waterfall!$C$20-1))+(Waterfall!$E$6*((1+$A27)^Waterfall!$E$20-1))))*(Waterfall!$C$6*((1+$A27)^Waterfall!$C$20-1))/((Waterfall!$C$6*((1+$A27)^Waterfall!$C$20-1))+(Waterfall!$D$6*((1+$A27)^Waterfall!$C$20-1))+(Waterfall!$E$6*((1+$A27)^Waterfall!$E$20-1))),0)+(MAX(0,(Waterfall!$F$12-Waterfall!$F$6)-MIN((Waterfall!$F$12-Waterfall!$F$6),((Waterfall!$C$6*((1+$A27)^Waterfall!$C$20-1))+(Waterfall!$D$6*((1+$A27)^Waterfall!$C$20-1))+(Waterfall!$E$6*((1+$A27)^Waterfall!$E$20-1)))))*(1-E$22)*Waterfall!$C$6/Waterfall!$F$6)+(MAX(0,(Waterfall!$F$12-Waterfall!$F$6)-MIN((Waterfall!$F$12-Waterfall!$F$6),((Waterfall!$C$6*((1+$A27)^Waterfall!$C$20-1))+(Waterfall!$D$6*((1+$A27)^Waterfall!$C$20-1))+(Waterfall!$E$6*((1+$A27)^Waterfall!$E$20-1)))))*E$22)+Inputs!$C$50)/Waterfall!$C$6 -> 2.3547013 | F27: =(Waterfall!$C$6+IF(((Waterfall!$C$6*((1+$A27)^Waterfall!$C$20-1))+(Waterfall!$D$6*((1+$A27)^Waterfall!$C$20-1))+(Waterfall!$E$6*((1+$A27)^Waterfall!$E$20-1)))>0,MIN((Waterfall!$F$12-Waterfall!$F$6),((Waterfall!$C$6*((1+$A27)^Waterfall!$C$20-1))+(Waterfall!$D$6*((1+$A27)^Waterfall!$C$20-1))+(Waterfall!$E$6*((1+$A27)^Waterfall!$E$20-1))))*(Waterfall!$C$6*((1+$A27)^Waterfall!$C$20-1))/((Waterfall!$C$6*((1+$A27)^Waterfall!$C$20-1))+(Waterfall!$D$6*((1+$A27)^Waterfall!$C$20-1))+(Waterfall!$E$6*((1+$A27)^Waterfall!$E$20-1))),0)+(MAX(0,(Waterfall!$F$12-Waterfall!$F$6)-MIN((Waterfall!$F$12-Waterfall!$F$6),((Waterfall!$C$6*((1+$A27)^Waterfall!$C$20-1))+(Waterfall!$D$6*((1+$A27)^Waterfall!$C$20-1))+(Waterfall!$E$6*((1+$A27)^Waterfall!$E$20-1)))))*(1-F$22)*Waterfall!$C$6/Waterfall!$F$6)+(MAX(0,(Waterfall!$F$12-Waterfall!$F$6)-MIN((Waterfall!$F$12-Waterfall!$F$6),((Waterfall!$C$6*((1+$A27)^Waterfall!$C$20-1))+(Waterfall!$D$6*((1+$A27)^Waterfall!$C$20-1))+(Waterfall!$E$6*((1+$A27)^Waterfall!$E$20-1)))))*F$22)+Inputs!$C$50)/Waterfall!$C$6 -> 2.4582534
A29: A higher pref or a smaller promote lowers the sponsor multiple. The cell at pref 10% and promote 50% is the base case.
A31: BREAK-EVEN HEADROOM
A32: GDV fall to break-even (profit = 0) | B32: =Summary!$M$8/Inputs!$C$25 -> 0.16290291
A33: Cost overrun to break-even (profit = 0) | B33: =Summary!$M$8/(Inputs!$C$53+Engine!$B$21) -> 0.19460456
A34: GDV at break-even | B34: =(Inputs!$C$53+Engine!$B$21)/(1-Inputs!$C$24) -> 3222823.8
A35: Margin vs target (profit on cost less target) | B35: =Summary!$M$8/(Inputs!$C$53+Engine!$B$21)-Inputs!$C$47 -> -0.0053954365
A36: How far each driver can move before profit hits zero, holding the others at the base run. GDV fall equals the profit-on-GDV margin; cost overrun equals the profit on cost.

Sheet Comparison
A1: OUTPUT | The same scheme, funded five ways
A2: ="Self-funded, Bank-financed, Mixed and Off-plan are like-for-like closed-form estimates. The last column links the exact engine for the route selected on Inputs. All amounts in "&Inputs!$C$80&" ("&Inputs!$C$79&")." -> Self-funded, Bank-financed, Mixed and Off-plan are like-for-like closed-form estimates. The last column links the exact engine for the route selected on Inputs. All amounts in NGN (₦).
A4: Comparison assumptions (transparent, editable)
A5: Average drawn balance factor (interest estimate) | C5: 0.55 | D5: of facility, over the active period
A6: Active period for interest | C6: =Inputs!$C$35/12 -> 2.5 | D6: years
A7: Mixed: combined senior + mezzanine, loan to cost | C7: 0.8 | D7: of cost ex finance
A8: Mixed: mezzanine interest rate | C8: 0.12 | D8: % pa
A9: Off-plan: units pre-sold | C9: 0.5 | D9: of GDV
A10: Off-plan: pre-sale cash received during build | C10: 0.5 | D10: of pre-sold value
A11: Off-plan: bridge rate | C11: 0.1 | D11: % pa
A13: Funding configuration
A14: Approach | C14: Self-funded | D14: Bank-financed | E14: Mixed senior+mezz | F14: =IF(Inputs!$C$5="Joint venture","JV plus land-for-equity","Selected route: "&Inputs!$C$5) -> JV plus land-for-equity | G14: Off-plan
A15: Senior debt (or bridge) | C15: =0 -> 0 | D15: =MIN(Inputs!$C$39*(Inputs!$C$51+Inputs!$C$30+Inputs!$C$31),Inputs!$C$40*Inputs!$C$23) -> 1705764.6 | E15: =MIN(Inputs!$C$39*(Inputs!$C$51+Inputs!$C$30+Inputs!$C$31),Inputs!$C$40*Inputs!$C$23) -> 1705764.6 | F15: =Inputs!$C$54 -> 1736214.6 | G15: =MAX(0,(Inputs!$C$29+0.3*Inputs!$C$27+Inputs!$C$30+Inputs!$C$31)) -> 625595.1
A16: Mezzanine | C16: =0 -> 0 | D16: =0 -> 0 | E16: =MAX(0,Comparison!$C$7*(Inputs!$C$51+Inputs!$C$30+Inputs!$C$31)-Comparison!E15) -> 568588.2 | F16: =0 -> 0 | G16: =0 -> 0
A17: Pre-sale receipts funding the build | C17: =0 -> 0 | D17: =0 -> 0 | E17: =0 -> 0 | F17: =0 -> 0 | G17: =Comparison!$C$9*Inputs!$C$25*Comparison!$C$10 -> 943250
A19: Cost and finance
A20: Total development cost (ex finance) | C20: =(Inputs!$C$51+Inputs!$C$30+Inputs!$C$31) -> 2842941 | D20: =(Inputs!$C$51+Inputs!$C$30+Inputs!$C$31) -> 2842941 | E20: =(Inputs!$C$51+Inputs!$C$30+Inputs!$C$31) -> 2842941 | F20: =(Inputs!$C$51+Inputs!$C$50+Inputs!$C$30) -> 2893691 | G20: =(Inputs!$C$51+Inputs!$C$30+Inputs!$C$31) -> 2842941
A21: Finance / holding cost (estimate) | C21: =0 -> 0 | D21: =Comparison!D15*Inputs!$C$41*Comparison!$C$5*Comparison!$C$6+Comparison!D15*Inputs!$C$42+Comparison!D15*Inputs!$C$43 -> 253732.48 | E21: =Comparison!E15*Inputs!$C$41*Comparison!$C$5*Comparison!$C$6+Comparison!E15*Inputs!$C$42+Comparison!E15*Inputs!$C$43+Comparison!E16*Comparison!$C$8*Comparison!$C$5*Comparison!$C$6 -> 347549.54 | F21: =Engine!$B$21 -> 264676.31 | G21: =Comparison!G15*Comparison!$C$11*0.6*(Inputs!$C$34-Inputs!$C$33+1)/12 -> 65687.485
A22: Total cost (incl finance) | C22: =Comparison!C20+Comparison!C21 -> 2842941 | D22: =Comparison!D20+Comparison!D21 -> 3096673.5 | E22: =Comparison!E20+Comparison!E21 -> 3190490.5 | F22: =Comparison!F20+Comparison!F21 -> 3158367.3 | G22: =Comparison!G20+Comparison!G21 -> 2908628.5
A24: Equity and total funding
A25: Sponsor cash equity | C25: =Comparison!C22 -> 2842941 | D25: =Comparison!D22-Comparison!D15 -> 1390908.9 | E25: =Comparison!E22-Comparison!E15-Comparison!E16 -> 916137.74 | F25: =Engine!$B$24 -> 219530.12 | G25: =MAX(0,Comparison!G22-Comparison!G15-Comparison!G17) -> 1339783.4
A26: Funding partner cash equity | C26: =0 -> 0 | D26: =0 -> 0 | E26: =0 -> 0 | F26: =Engine!$B$25 -> 512236.95 | G26: =0 -> 0
A27: Landowner land (equity) | C27: =0 -> 0 | D27: =0 -> 0 | E27: =0 -> 0 | F27: =Inputs!$C$30 -> 525000 | G27: =0 -> 0
A28: Total funding committed | C28: =Comparison!C15+Comparison!C16+Comparison!C25+Comparison!C26+Comparison!C27 -> 2842941 | D28: =Comparison!D15+Comparison!D16+Comparison!D25+Comparison!D26+Comparison!D27 -> 3096673.5 | E28: =Comparison!E15+Comparison!E16+Comparison!E25+Comparison!E26+Comparison!E27 -> 3190490.5 | F28: =Comparison!F15+Comparison!F16+Comparison!F25+Comparison!F26+Comparison!F27 -> 2992981.7 | G28: =Comparison!G15+Comparison!G16+Comparison!G25+Comparison!G26+Comparison!G27 -> 1965378.5
A30: Returns
A31: Project profit | C31: =Inputs!$C$25-Comparison!C22 -> 930059 | D31: =Inputs!$C$25-Comparison!D22 -> 676326.52 | E31: =Inputs!$C$25-Comparison!E22 -> 582509.46 | F31: =Inputs!$C$25-Comparison!F22 -> 614632.69 | G31: =Inputs!$C$25-Comparison!G22 -> 864371.51
A32: Profit on cost | C32: =Comparison!C31/Comparison!C22 -> 0.32714678 | D32: =Comparison!D31/Comparison!D22 -> 0.21840421 | E32: =Comparison!E31/Comparison!E22 -> 0.18257677 | F32: =Comparison!F31/Comparison!F22 -> 0.19460456 | G32: =Comparison!G31/Comparison!G22 -> 0.29717495
A33: Sponsor cash in | C33: =Comparison!C25 -> 2842941 | D33: =Comparison!D25 -> 1390908.9 | E33: =Comparison!E25 -> 916137.74 | F33: =Comparison!F25 -> 219530.12 | G33: =Comparison!G25 -> 1339783.4
A34: Sponsor total out | C34: =Comparison!C31+Comparison!C25 -> 3773000 | D34: =Comparison!D31+Comparison!D25 -> 2067235.4 | E34: =Comparison!E31+Comparison!E25 -> 1498647.2 | F34: =Waterfall!$C$33 -> 551692.03 | G34: =Comparison!G31+Comparison!G25 -> 2204154.9
A35: Sponsor profit | C35: =Comparison!C31 -> 930059 | D35: =Comparison!D31 -> 676326.52 | E35: =Comparison!E31 -> 582509.46 | F35: =Waterfall!$C$33-Engine!$B$24 -> 332161.91 | G35: =Comparison!G31 -> 864371.51
A36: Sponsor multiple on equity | C36: =IFERROR(Comparison!C34/Comparison!C25,"-") -> 1.3271468 | D36: =IFERROR(Comparison!D34/Comparison!D25,"-") -> 1.4862479 | E36: =IFERROR(Comparison!E34/Comparison!E25,"-") -> 1.6358318 | F36: =IFERROR(Comparison!F34/Comparison!F25,"-") -> 2.5130585 | G36: =IFERROR(Comparison!G34/Comparison!G25,"-") -> 1.6451577
A37: Funding partner multiple | C37: ="-" -> - | D37: ="-" -> - | E37: ="-" -> - | F37: =Waterfall!$D$33/Engine!$B$25 -> 1.265436 | G37: ="-" -> -
A38: Landowner cash out | C38: =Inputs!$C$30 -> 525000 | D38: =Inputs!$C$30 -> 525000 | E38: =Inputs!$C$30 -> 525000 | F38: =Waterfall!$E$33 -> 748504.65 | G38: =Inputs!$C$30 -> 525000
A39: Equity multiple (whole project) | C39: =(C25+C26+C27+C31)/(C25+C26+C27) -> 1.3271468 | D39: =(D25+D26+D27+D31)/(D25+D26+D27) -> 1.4862479 | E39: =(E25+E26+E27+E31)/(E25+E26+E27) -> 1.6358318 | F39: =Engine!$B$41 -> 1.4890586 | G39: =(G25+G26+G27+G31)/(G25+G26+G27) -> 1.6451577
A40: Equity IRR (annual) | C40: =C39^(1/(Inputs!$C$35/12))-1 -> 0.11986993 | D40: =D39^(1/(Inputs!$C$35/12))-1 -> 0.17175415 | E40: =E39^(1/(Inputs!$C$35/12))-1 -> 0.21757425 | F40: =Engine!$B$40 -> 0.32250519 | G40: =G39^(1/(Inputs!$C$35/12))-1 -> 0.22034608
A41: Equity multiple is whole-project (all equity: sponsor, partner and contributed land). Equity IRR for the selected route links the live monthly XIRR (column F); the other routes annualise the multiple over the programme as closed-form estimates.
A42: Landowner: cash sale on most routes; land-for-equity on the JV returns land value plus a profit share.
A44: Note: Off-plan is shown with a simplified pre-sale model. It changes when revenue arrives, not just the funding mix, so the full engine extends the cashflow to bring pre-sale receipts in during the build. Illustrative.

Sheet Engine
A1: ENGINE | Senior debt schedule and funding stack
A2: ="Cash uses are funded by senior debt to its cap, then by cash equity. Senior interest accrues on the opening balance, so there is no circular reference. Land is contributed as equity, not cash; it enters in the waterfall. All amounts in "&Inputs!$C$80&" ("&Inputs!$C$79&")." -> Cash uses are funded by senior debt to its cap, then by cash equity. Senior interest accrues on the opening balance, so there is no circular reference. Land is contributed as equity, not cash; it enters in the waterfall. All amounts in NGN (₦).
A3: Month | B3: Total | C3: 1 | D3: 2 | E3: 3 | F3: 4 | G3: 5 | H3: 6 | I3: 7 | J3: 8 | K3: 9 | L3: 10 | M3: 11 | N3: 12 | O3: 13 | P3: 14 | Q3: 15 | R3: 16 | S3: 17 | T3: 18 | U3: 19 | V3: 20 | W3: 21 | X3: 22 | Y3: 23 | Z3: 24 | AA3: 25 | AB3: 26 | AC3: 27 | AD3: 28 | AE3: 29 | AF3: 30
A5: Cost outflow (cash uses spread) | B5: =SUM(C5:AF5) -> 2368691 | C5: =IF(C3<=(Inputs!$C$33-1),(Inputs!$C$29+0.3*Inputs!$C$27)/(Inputs!$C$33-1),0)+IF(AND(C3>=Inputs!$C$33,C3<=Inputs!$C$34),(Inputs!$C$97+0.7*Inputs!$C$27+Inputs!$C$28+Inputs!$C$50)*IF(Inputs!$C$92="S-curve",(3*((C3-Inputs!$C$33+1)/(Inputs!$C$34-Inputs!$C$33+1))^2-2*((C3-Inputs!$C$33+1)/(Inputs!$C$34-Inputs!$C$33+1))^3)-(3*((C3-Inputs!$C$33)/(Inputs!$C$34-Inputs!$C$33+1))^2-2*((C3-Inputs!$C$33)/(Inputs!$C$34-Inputs!$C$33+1))^3),1/(Inputs!$C$34-Inputs!$C$33+1)),0)+IF(AND(C3=1,Inputs!$C$18=1),Inputs!$C$30+Inputs!$C$31,0) -> 12390.85 | D5: =IF(D3<=(Inputs!$C$33-1),(Inputs!$C$29+0.3*Inputs!$C$27)/(Inputs!$C$33-1),0)+IF(AND(D3>=Inputs!$C$33,D3<=Inputs!$C$34),(Inputs!$C$97+0.7*Inputs!$C$27+Inputs!$C$28+Inputs!$C$50)*IF(Inputs!$C$92="S-curve",(3*((D3-Inputs!$C$33+1)/(Inputs!$C$34-Inputs!$C$33+1))^2-2*((D3-Inputs!$C$33+1)/(Inputs!$C$34-Inputs!$C$33+1))^3)-(3*((D3-Inputs!$C$33)/(Inputs!$C$34-Inputs!$C$33+1))^2-2*((D3-Inputs!$C$33)/(Inputs!$C$34-Inputs!$C$33+1))^3),1/(Inputs!$C$34-Inputs!$C$33+1)),0)+IF(AND(D3=1,Inputs!$C$18=1),Inputs!$C$30+Inputs!$C$31,0) -> 12390.85 | E5: =IF(E3<=(Inputs!$C$33-1),(Inputs!$C$29+0.3*Inputs!$C$27)/(Inputs!$C$33-1),0)+IF(AND(E3>=Inputs!$C$33,E3<=Inputs!$C$34),(Inputs!$C$97+0.7*Inputs!$C$27+Inputs!$C$28+Inputs!$C$50)*IF(Inputs!$C$92="S-curve",(3*((E3-Inputs!$C$33+1)/(Inputs!$C$34-Inputs!$C$33+1))^2-2*((E3-Inputs!$C$33+1)/(Inputs!$C$34-Inputs!$C$33+1))^3)-(3*((E3-Inputs!$C$33)/(Inputs!$C$34-Inputs!$C$33+1))^2-2*((E3-Inputs!$C$33)/(Inputs!$C$34-Inputs!$C$33+1))^3),1/(Inputs!$C$34-Inputs!$C$33+1)),0)+IF(AND(E3=1,Inputs!$C$18=1),Inputs!$C$30+Inputs!$C$31,0) -> 12390.85 | F5: =IF(F3<=(Inputs!$C$33-1),(Inputs!$C$29+0.3*Inputs!$C$27)/(Inputs!$C$33-1),0)+IF(AND(F3>=Inputs!$C$33,F3<=Inputs!$C$34),(Inputs!$C$97+0.7*Inputs!$C$27+Inputs!$C$28+Inputs!$C$50)*IF(Inputs!$C$92="S-curve",(3*((F3-Inputs!$C$33+1)/(Inputs!$C$34-Inputs!$C$33+1))^2-2*((F3-Inputs!$C$33+1)/(Inputs!$C$34-Inputs!$C$33+1))^3)-(3*((F3-Inputs!$C$33)/(Inputs!$C$34-Inputs!$C$33+1))^2-2*((F3-Inputs!$C$33)/(Inputs!$C$34-Inputs!$C$33+1))^3),1/(Inputs!$C$34-Inputs!$C$33+1)),0)+IF(AND(F3=1,Inputs!$C$18=1),Inputs!$C$30+Inputs!$C$31,0) -> 12390.85 | G5: =IF(G3<=(Inputs!$C$33-1),(Inputs!$C$29+0.3*Inputs!$C$27)/(Inputs!$C$33-1),0)+IF(AND(G3>=Inputs!$C$33,G3<=Inputs!$C$34),(Inputs!$C$97+0.7*Inputs!$C$27+Inputs!$C$28+Inputs!$C$50)*IF(Inputs!$C$92="S-curve",(3*((G3-Inputs!$C$33+1)/(Inputs!$C$34-Inputs!$C$33+1))^2-2*((G3-Inputs!$C$33+1)/(Inputs!$C$34-Inputs!$C$33+1))^3)-(3*((G3-Inputs!$C$33)/(Inputs!$C$34-Inputs!$C$33+1))^2-2*((G3-Inputs!$C$33)/(Inputs!$C$34-Inputs!$C$33+1))^3),1/(Inputs!$C$34-Inputs!$C$33+1)),0)+IF(AND(G3=1,Inputs!$C$18=1),Inputs!$C$30+Inputs!$C$31,0) -> 12390.85 | H5: =IF(H3<=(Inputs!$C$33-1),(Inputs!$C$29+0.3*Inputs!$C$27)/(Inputs!$C$33-1),0)+IF(AND(H3>=Inputs!$C$33,H3<=Inputs!$C$34),(Inputs!$C$97+0.7*Inputs!$C$27+Inputs!$C$28+Inputs!$C$50)*IF(Inputs!$C$92="S-curve",(3*((H3-Inputs!$C$33+1)/(Inputs!$C$34-Inputs!$C$33+1))^2-2*((H3-Inputs!$C$33+1)/(Inputs!$C$34-Inputs!$C$33+1))^3)-(3*((H3-Inputs!$C$33)/(Inputs!$C$34-Inputs!$C$33+1))^2-2*((H3-Inputs!$C$33)/(Inputs!$C$34-Inputs!$C$33+1))^3),1/(Inputs!$C$34-Inputs!$C$33+1)),0)+IF(AND(H3=1,Inputs!$C$18=1),Inputs!$C$30+Inputs!$C$31,0) -> 12390.85 | I5: =IF(I3<=(Inputs!$C$33-1),(Inputs!$C$29+0.3*Inputs!$C$27)/(Inputs!$C$33-1),0)+IF(AND(I3>=Inputs!$C$33,I3<=Inputs!$C$34),(Inputs!$C$97+0.7*Inputs!$C$27+Inputs!$C$28+Inputs!$C$50)*IF(Inputs!$C$92="S-curve",(3*((I3-Inputs!$C$33+1)/(Inputs!$C$34-Inputs!$C$33+1))^2-2*((I3-Inputs!$C$33+1)/(Inputs!$C$34-Inputs!$C$33+1))^3)-(3*((I3-Inputs!$C$33)/(Inputs!$C$34-Inputs!$C$33+1))^2-2*((I3-Inputs!$C$33)/(Inputs!$C$34-Inputs!$C$33+1))^3),1/(Inputs!$C$34-Inputs!$C$33+1)),0)+IF(AND(I3=1,Inputs!$C$18=1),Inputs!$C$30+Inputs!$C$31,0) -> 109254.57 | J5: =IF(J3<=(Inputs!$C$33-1),(Inputs!$C$29+0.3*Inputs!$C$27)/(Inputs!$C$33-1),0)+IF(AND(J3>=Inputs!$C$33,J3<=Inputs!$C$34),(Inputs!$C$97+0.7*Inputs!$C$27+Inputs!$C$28+Inputs!$C$50)*IF(Inputs!$C$92="S-curve",(3*((J3-Inputs!$C$33+1)/(Inputs!$C$34-Inputs!$C$33+1))^2-2*((J3-Inputs!$C$33+1)/(Inputs!$C$34-Inputs!$C$33+1))^3)-(3*((J3-Inputs!$C$33)/(Inputs!$C$34-Inputs!$C$33+1))^2-2*((J3-Inputs!$C$33)/(Inputs!$C$34-Inputs!$C$33+1))^3),1/(Inputs!$C$34-Inputs!$C$33+1)),0)+IF(AND(J3=1,Inputs!$C$18=1),Inputs!$C$30+Inputs!$C$31,0) -> 109254.57 | ... AF5: =IF(AF3<=(Inputs!$C$33-1),(Inputs!$C$29+0.3*Inputs!$C$27)/(Inputs!$C$33-1),0)+IF(AND(AF3>=Inputs!$C$33,AF3<=Inputs!$C$34),(Inputs!$C$97+0.7*Inputs!$C$27+Inputs!$C$28+Inputs!$C$50)*IF(Inputs!$C$92="S-curve",(3*((AF3-Inputs!$C$33+1)/(Inputs!$C$34-Inputs!$C$33+1))^2-2*((AF3-Inputs!$C$33+1)/(Inputs!$C$34-Inputs!$C$33+1))^3)-(3*((AF3-Inputs!$C$33)/(Inputs!$C$34-Inputs!$C$33+1))^2-2*((AF3-Inputs!$C$33)/(Inputs!$C$34-Inputs!$C$33+1))^3),1/(Inputs!$C$34-Inputs!$C$33+1)),0)+IF(AND(AF3=1,Inputs!$C$18=1),Inputs!$C$30+Inputs!$C$31,0) -> 0
A6: Pre-sale receipts (applied) | C6: =IF(Inputs!$C$63="Yes",1,0)*MIN(Inputs!$C$64*Inputs!$C$25*IF(AND(C3>=Inputs!$C$33,C3<=Inputs!$C$34),1/(Inputs!$C$34-Inputs!$C$33+1),0),C5) -> 0 | D6: =IF(Inputs!$C$63="Yes",1,0)*MIN(Inputs!$C$64*Inputs!$C$25*IF(AND(D3>=Inputs!$C$33,D3<=Inputs!$C$34),1/(Inputs!$C$34-Inputs!$C$33+1),0),D5) -> 0 | E6: =IF(Inputs!$C$63="Yes",1,0)*MIN(Inputs!$C$64*Inputs!$C$25*IF(AND(E3>=Inputs!$C$33,E3<=Inputs!$C$34),1/(Inputs!$C$34-Inputs!$C$33+1),0),E5) -> 0 | F6: =IF(Inputs!$C$63="Yes",1,0)*MIN(Inputs!$C$64*Inputs!$C$25*IF(AND(F3>=Inputs!$C$33,F3<=Inputs!$C$34),1/(Inputs!$C$34-Inputs!$C$33+1),0),F5) -> 0 | G6: =IF(Inputs!$C$63="Yes",1,0)*MIN(Inputs!$C$64*Inputs!$C$25*IF(AND(G3>=Inputs!$C$33,G3<=Inputs!$C$34),1/(Inputs!$C$34-Inputs!$C$33+1),0),G5) -> 0 | H6: =IF(Inputs!$C$63="Yes",1,0)*MIN(Inputs!$C$64*Inputs!$C$25*IF(AND(H3>=Inputs!$C$33,H3<=Inputs!$C$34),1/(Inputs!$C$34-Inputs!$C$33+1),0),H5) -> 0 | I6: =IF(Inputs!$C$63="Yes",1,0)*MIN(Inputs!$C$64*Inputs!$C$25*IF(AND(I3>=Inputs!$C$33,I3<=Inputs!$C$34),1/(Inputs!$C$34-Inputs!$C$33+1),0),I5) -> 0 | J6: =IF(Inputs!$C$63="Yes",1,0)*MIN(Inputs!$C$64*Inputs!$C$25*IF(AND(J3>=Inputs!$C$33,J3<=Inputs!$C$34),1/(Inputs!$C$34-Inputs!$C$33+1),0),J5) -> 0 | ... AF6: =IF(Inputs!$C$63="Yes",1,0)*MIN(Inputs!$C$64*Inputs!$C$25*IF(AND(AF3>=Inputs!$C$33,AF3<=Inputs!$C$34),1/(Inputs!$C$34-Inputs!$C$33+1),0),AF5) -> 0
A7: Senior debt schedule (interest on opening balance, rolled up)
A8: Senior facility limit | B8: =Inputs!$C$54 -> 1736214.6
A9: Monthly interest rate | B9: =Inputs!$C$41/12 -> 0.0075
A10: Opening balance | C10: =0 -> 0 | D10: =C13 -> 12390.85 | E10: =D13 -> 24874.631 | F10: =E13 -> 37452.041 | G10: =F13 -> 50123.781 | H10: =G13 -> 62890.56 | I10: =H13 -> 75753.089 | J10: =I13 -> 185575.8 | K10: =J13 -> 296222.19 | ... AF10: =AE13 -> 1843163.4
A11: Interest (rolled up) | B11: =SUM(C11:AF11) -> 220063.22 | C11: =IF(Inputs!$C$89="Average balance",(C10+0.5*C12)*$B$9,C10*$B$9) -> 0 | D11: =IF(Inputs!$C$89="Average balance",(D10+0.5*D12)*$B$9,D10*$B$9) -> 92.931375 | E11: =IF(Inputs!$C$89="Average balance",(E10+0.5*E12)*$B$9,E10*$B$9) -> 186.55974 | F11: =IF(Inputs!$C$89="Average balance",(F10+0.5*F12)*$B$9,F10*$B$9) -> 280.89031 | G11: =IF(Inputs!$C$89="Average balance",(G10+0.5*G12)*$B$9,G10*$B$9) -> 375.92836 | H11: =IF(Inputs!$C$89="Average balance",(H10+0.5*H12)*$B$9,H10*$B$9) -> 471.6792 | I11: =IF(Inputs!$C$89="Average balance",(I10+0.5*I12)*$B$9,I10*$B$9) -> 568.14817 | J11: =IF(Inputs!$C$89="Average balance",(J10+0.5*J12)*$B$9,J10*$B$9) -> 1391.8185 | ... AF11: =IF(Inputs!$C$89="Average balance",(AF10+0.5*AF12)*$B$9,AF10*$B$9) -> 13823.726
A12: Senior draw | B12: =SUM(C12:AF12) -> 1636923.9 | C12: =IF(AND(Inputs!$C$100="Equity first",C3<Inputs!$C$33),0,MIN(MAX(0,C5-C6),MAX(0,$B$8-(C10+C10*$B$9)))) -> 12390.85 | D12: =IF(AND(Inputs!$C$100="Equity first",D3<Inputs!$C$33),0,MIN(MAX(0,D5-D6),MAX(0,$B$8-(D10+D10*$B$9)))) -> 12390.85 | E12: =IF(AND(Inputs!$C$100="Equity first",E3<Inputs!$C$33),0,MIN(MAX(0,E5-E6),MAX(0,$B$8-(E10+E10*$B$9)))) -> 12390.85 | F12: =IF(AND(Inputs!$C$100="Equity first",F3<Inputs!$C$33),0,MIN(MAX(0,F5-F6),MAX(0,$B$8-(F10+F10*$B$9)))) -> 12390.85 | G12: =IF(AND(Inputs!$C$100="Equity first",G3<Inputs!$C$33),0,MIN(MAX(0,G5-G6),MAX(0,$B$8-(G10+G10*$B$9)))) -> 12390.85 | H12: =IF(AND(Inputs!$C$100="Equity first",H3<Inputs!$C$33),0,MIN(MAX(0,H5-H6),MAX(0,$B$8-(H10+H10*$B$9)))) -> 12390.85 | I12: =IF(AND(Inputs!$C$100="Equity first",I3<Inputs!$C$33),0,MIN(MAX(0,I5-I6),MAX(0,$B$8-(I10+I10*$B$9)))) -> 109254.57 | J12: =IF(AND(Inputs!$C$100="Equity first",J3<Inputs!$C$33),0,MIN(MAX(0,J5-J6),MAX(0,$B$8-(J10+J10*$B$9)))) -> 109254.57 | ... AF12: =IF(AND(Inputs!$C$100="Equity first",AF3<Inputs!$C$33),0,MIN(MAX(0,AF5-AF6),MAX(0,$B$8-(AF10+AF10*$B$9)))) -> 0
A13: Closing balance | C13: =C10+C11+C12 -> 12390.85 | D13: =D10+D11+D12 -> 24874.631 | E13: =E10+E11+E12 -> 37452.041 | F13: =F10+F11+F12 -> 50123.781 | G13: =G10+G11+G12 -> 62890.56 | H13: =H10+H11+H12 -> 75753.089 | I13: =I10+I11+I12 -> 185575.8 | J13: =J10+J11+J12 -> 296222.19 | ... AF13: =AF10+AF11+AF12 -> 1856987.1
A14: Cash equity draw (gap not covered by senior) | B14: =SUM(C14:AF14) -> 731767.07 | C14: =MAX(0,C5-C6)-C12 -> 0 | D14: =MAX(0,D5-D6)-D12 -> 0 | E14: =MAX(0,E5-E6)-E12 -> 0 | F14: =MAX(0,F5-F6)-F12 -> 0 | G14: =MAX(0,G5-G6)-G12 -> 0 | H14: =MAX(0,H5-H6)-H12 -> 0 | I14: =MAX(0,I5-I6)-I12 -> 0 | J14: =MAX(0,J5-J6)-J12 -> 0 | ... AF14: =MAX(0,AF5-AF6)-AF12 -> 0
A16: Funding outputs
A17: Senior closing balance at completion | B17: =INDEX(C13:AF13,MATCH(Inputs!$C$35,C3:AF3,0)) -> 1856987.1 | C17: Drawn principal plus rolled interest.
A18: Senior arrangement fee | B18: =$B$8*Inputs!$C$42 -> 26043.219
A19: Senior exit fee | B19: =Engine!$B$17*Inputs!$C$43 -> 18569.871
A20: Senior redemption from NDV | B20: =Engine!$B$17+Engine!$B$18+Engine!$B$19 -> 1901600.2 | C20: Repaid first from the NDV.
A21: Total finance and holding cost | B21: =SUM(C11:AF11)+Engine!$B$18+Engine!$B$19+Engine!$B$28+Engine!$B$31 -> 264676.31 | C21: Interest plus arrangement plus exit.
A22: Peak senior debt | B22: =MAX(C13:AF13) -> 1856987.1
A23: Total cash equity | B23: =MAX(0,SUM(C14:AF14)-$B$27) -> 731767.07
A24: Sponsor cash equity | B24: =Engine!$B$23*(1-Inputs!$C$19) -> 219530.12
A25: Funding partner cash equity | B25: =Engine!$B$23*Inputs!$C$19 -> 512236.95
A26: Reconciliation: cash uses funded vs cash uses | B26: =(B23+SUM(C12:AF12)+$B$30+$B$27)-Inputs!$C$52 -> 0 | C26: Should be zero.
A27: Mezzanine facility | B27: =Inputs!$C$14*MAX(0,Inputs!$C$21*Inputs!$C$53-Inputs!$C$54) -> 0
A28: Mezzanine interest (rolled up) | B28: =$B$27*((1+Inputs!$C$11)^((Inputs!$C$35-(Inputs!$C$33+Inputs!$C$34)/2)/12)-1) -> 0
A29: Mezzanine redemption from NDV | B29: =$B$27+$B$28 -> 0
A30: Pre-sale debt reduction (total) | B30: =SUM(C6:AF6) -> 0
A31: Holding cost (void) | B31: =Inputs!$C$86*MAX(0,Inputs!$C$35-Inputs!$C$34) -> 0
A32: TIME-BASED RETURNS (live, selected route)
B33: Month date | C33: =Cashflow!C4 -> 46204 | D33: =Cashflow!D4 -> 46235 | E33: =Cashflow!E4 -> 46266 | F33: =Cashflow!F4 -> 46296 | G33: =Cashflow!G4 -> 46327 | H33: =Cashflow!H4 -> 46357 | I33: =Cashflow!I4 -> 46388 | J33: =Cashflow!J4 -> 46419 | ... AF33: =Cashflow!AF4 -> 47088
B34: Project net cash flow (unlevered, ex finance) | C34: =Cashflow!C24-Cashflow!C19 -> -537390.85 | D34: =Cashflow!D24-Cashflow!D19 -> -12390.85 | E34: =Cashflow!E24-Cashflow!E19 -> -12390.85 | F34: =Cashflow!F24-Cashflow!F19 -> -12390.85 | G34: =Cashflow!G24-Cashflow!G19 -> -12390.85 | H34: =Cashflow!H24-Cashflow!H19 -> -12390.85 | I34: =Cashflow!I24-Cashflow!I19 -> -109254.57 | J34: =Cashflow!J24-Cashflow!J19 -> -109254.57 | ... AF34: =Cashflow!AF24-Cashflow!AF19 -> 3773000
B35: Equity net cash flow (levered) | C35: =-C14+IF(C$3=1,-IF(Inputs!$C$17=1,Inputs!$C$30,0),0)+IF(C$3=Inputs!$C$35,Inputs!$C$25-$B$30-$B$20-$B$29-$B$31,0) -> -525000 | D35: =-D14+IF(D$3=1,-IF(Inputs!$C$17=1,Inputs!$C$30,0),0)+IF(D$3=Inputs!$C$35,Inputs!$C$25-$B$30-$B$20-$B$29-$B$31,0) -> 0 | E35: =-E14+IF(E$3=1,-IF(Inputs!$C$17=1,Inputs!$C$30,0),0)+IF(E$3=Inputs!$C$35,Inputs!$C$25-$B$30-$B$20-$B$29-$B$31,0) -> 0 | F35: =-F14+IF(F$3=1,-IF(Inputs!$C$17=1,Inputs!$C$30,0),0)+IF(F$3=Inputs!$C$35,Inputs!$C$25-$B$30-$B$20-$B$29-$B$31,0) -> 0 | G35: =-G14+IF(G$3=1,-IF(Inputs!$C$17=1,Inputs!$C$30,0),0)+IF(G$3=Inputs!$C$35,Inputs!$C$25-$B$30-$B$20-$B$29-$B$31,0) -> 0 | H35: =-H14+IF(H$3=1,-IF(Inputs!$C$17=1,Inputs!$C$30,0),0)+IF(H$3=Inputs!$C$35,Inputs!$C$25-$B$30-$B$20-$B$29-$B$31,0) -> 0 | I35: =-I14+IF(I$3=1,-IF(Inputs!$C$17=1,Inputs!$C$30,0),0)+IF(I$3=Inputs!$C$35,Inputs!$C$25-$B$30-$B$20-$B$29-$B$31,0) -> 0 | J35: =-J14+IF(J$3=1,-IF(Inputs!$C$17=1,Inputs!$C$30,0),0)+IF(J$3=Inputs!$C$35,Inputs!$C$25-$B$30-$B$20-$B$29-$B$31,0) -> 0 | ... AF35: =-AF14+IF(AF$3=1,-IF(Inputs!$C$17=1,Inputs!$C$30,0),0)+IF(AF$3=Inputs!$C$35,Inputs!$C$25-$B$30-$B$20-$B$29-$B$31,0) -> 1871399.8
B36: After-tax equity net cash flow | C36: =C35-IF(C$3=Inputs!$C$35,$B$43,0) -> -525000 | D36: =D35-IF(D$3=Inputs!$C$35,$B$43,0) -> 0 | E36: =E35-IF(E$3=Inputs!$C$35,$B$43,0) -> 0 | F36: =F35-IF(F$3=Inputs!$C$35,$B$43,0) -> 0 | G36: =G35-IF(G$3=Inputs!$C$35,$B$43,0) -> 0 | H36: =H35-IF(H$3=Inputs!$C$35,$B$43,0) -> 0 | I36: =I35-IF(I$3=Inputs!$C$35,$B$43,0) -> 0 | J36: =J35-IF(J$3=Inputs!$C$35,$B$43,0) -> 0 | ... AF36: =AF35-IF(AF$3=Inputs!$C$35,$B$43,0) -> 1717741.6
A38: Project IRR (unlevered, p.a.) | B38: =IFERROR((1+IRR(C34:AF34,0.02))^12-1,"n/a") -> 0.20863441
A39: Project equity multiple (unlevered) | B39: =IFERROR(SUMIF(C34:AF34,">0")/-SUMIF(C34:AF34,"<0"),"n/a") -> 1.3038711
A40: Equity IRR (levered, p.a.) | B40: =IFERROR((1+IRR(C35:AF35,0.02))^12-1,"n/a") -> 0.32250519
A41: Equity multiple (levered, whole project) | B41: =IFERROR(SUMIF(C35:AF35,">0")/-SUMIF(C35:AF35,"<0"),"n/a") -> 1.4890586
A43: Corporation tax (on project profit) | B43: =MAX(0,Summary!$M$8)*Inputs!$C$67 -> 153658.17
A44: After-tax project profit | B44: =Summary!$M$8-$B$43 -> 460974.52
A45: After-tax equity IRR (p.a.) | B45: =IFERROR((1+IRR(C36:AF36,0.02))^12-1,"n/a") -> 0.25042974
A46: PER-PARTY CASH FLOWS (selected route) | B46: =IFERROR(SUMIF(C36:AF36,">0")/-SUMIF(C36:AF36,"<0"),"n/a") -> 1.3667939
B47: Sponsor net cash flow | C47: =-(C14*(1-Inputs!$C$19))+IF(C$3=1,-(Waterfall!$C$6-Engine!$B$24),0)+IF(C$3=Inputs!$C$35,Waterfall!$C$33,0) -> 0 | D47: =-(D14*(1-Inputs!$C$19))+IF(D$3=1,-(Waterfall!$C$6-Engine!$B$24),0)+IF(D$3=Inputs!$C$35,Waterfall!$C$33,0) -> 0 | E47: =-(E14*(1-Inputs!$C$19))+IF(E$3=1,-(Waterfall!$C$6-Engine!$B$24),0)+IF(E$3=Inputs!$C$35,Waterfall!$C$33,0) -> 0 | F47: =-(F14*(1-Inputs!$C$19))+IF(F$3=1,-(Waterfall!$C$6-Engine!$B$24),0)+IF(F$3=Inputs!$C$35,Waterfall!$C$33,0) -> 0 | G47: =-(G14*(1-Inputs!$C$19))+IF(G$3=1,-(Waterfall!$C$6-Engine!$B$24),0)+IF(G$3=Inputs!$C$35,Waterfall!$C$33,0) -> 0 | H47: =-(H14*(1-Inputs!$C$19))+IF(H$3=1,-(Waterfall!$C$6-Engine!$B$24),0)+IF(H$3=Inputs!$C$35,Waterfall!$C$33,0) -> 0 | I47: =-(I14*(1-Inputs!$C$19))+IF(I$3=1,-(Waterfall!$C$6-Engine!$B$24),0)+IF(I$3=Inputs!$C$35,Waterfall!$C$33,0) -> 0 | J47: =-(J14*(1-Inputs!$C$19))+IF(J$3=1,-(Waterfall!$C$6-Engine!$B$24),0)+IF(J$3=Inputs!$C$35,Waterfall!$C$33,0) -> 0 | ... AF47: =-(AF14*(1-Inputs!$C$19))+IF(AF$3=1,-(Waterfall!$C$6-Engine!$B$24),0)+IF(AF$3=Inputs!$C$35,Waterfall!$C$33,0) -> 551692.03
B48: Funding partner net cash flow | C48: =-(C14*Inputs!$C$19)+IF(C$3=Inputs!$C$35,Waterfall!$D$33,0) -> 0 | D48: =-(D14*Inputs!$C$19)+IF(D$3=Inputs!$C$35,Waterfall!$D$33,0) -> 0 | E48: =-(E14*Inputs!$C$19)+IF(E$3=Inputs!$C$35,Waterfall!$D$33,0) -> 0 | F48: =-(F14*Inputs!$C$19)+IF(F$3=Inputs!$C$35,Waterfall!$D$33,0) -> 0 | G48: =-(G14*Inputs!$C$19)+IF(G$3=Inputs!$C$35,Waterfall!$D$33,0) -> 0 | H48: =-(H14*Inputs!$C$19)+IF(H$3=Inputs!$C$35,Waterfall!$D$33,0) -> 0 | I48: =-(I14*Inputs!$C$19)+IF(I$3=Inputs!$C$35,Waterfall!$D$33,0) -> 0 | J48: =-(J14*Inputs!$C$19)+IF(J$3=Inputs!$C$35,Waterfall!$D$33,0) -> 0 | ... AF48: =-(AF14*Inputs!$C$19)+IF(AF$3=Inputs!$C$35,Waterfall!$D$33,0) -> 648203.08
B49: Landowner net cash flow | C49: =IF(C$3=1,-Waterfall!$E$6,0)+IF(C$3=Inputs!$C$35,Waterfall!$E$33,0) -> -525000 | D49: =IF(D$3=1,-Waterfall!$E$6,0)+IF(D$3=Inputs!$C$35,Waterfall!$E$33,0) -> 0 | E49: =IF(E$3=1,-Waterfall!$E$6,0)+IF(E$3=Inputs!$C$35,Waterfall!$E$33,0) -> 0 | F49: =IF(F$3=1,-Waterfall!$E$6,0)+IF(F$3=Inputs!$C$35,Waterfall!$E$33,0) -> 0 | G49: =IF(G$3=1,-Waterfall!$E$6,0)+IF(G$3=Inputs!$C$35,Waterfall!$E$33,0) -> 0 | H49: =IF(H$3=1,-Waterfall!$E$6,0)+IF(H$3=Inputs!$C$35,Waterfall!$E$33,0) -> 0 | I49: =IF(I$3=1,-Waterfall!$E$6,0)+IF(I$3=Inputs!$C$35,Waterfall!$E$33,0) -> 0 | J49: =IF(J$3=1,-Waterfall!$E$6,0)+IF(J$3=Inputs!$C$35,Waterfall!$E$33,0) -> 0 | ... AF49: =IF(AF$3=1,-Waterfall!$E$6,0)+IF(AF$3=Inputs!$C$35,Waterfall!$E$33,0) -> 748504.65
A51: Sponsor IRR (p.a.) | B51: =IFERROR((1+IRR(C47:AF47,0.02))^12-1,"n/a") -> 5.0465773
A52: Funding partner IRR (p.a.) | B52: =IFERROR((1+IRR(C48:AF48,0.02))^12-1,"n/a") -> 0.60907431
A53: Landowner IRR (p.a.) | B53: =IFERROR((1+IRR(C49:AF49,0.02))^12-1,"n/a") -> 0.15808038
